Workbook

Sheet Notes on Creative Com.
A1: We are glad to have press coverage of our studies and encourage you to share our work. We give permission for anyone to use this study’s data, analysis, and visuals as long as you:
B2: • Credit Surfshark (ideally with a link to the landing page);
B3: • Say if you made any changes to the original piece;
B4: • Don't use these materials for commercial purposes.
B5: • If you change the materials, you also need to share them under the same rules.
A6: This project is licensed under Creative Commons 3.0 and the above-mentioned conditions are taken from it. If you have any questions or concerns about sharing our work, please contact media@surfshark.com before using them.

Sheet Countries
B1: Country | C1: ISO-alpha2 Code | D1: Social media bans / heavy disruptions within the period of 2015 - present? | E1: Related w/ protests | F1: Related w/ elections | G1: Related w/ political turmoil | H1: Related w/ country’s internet law | I1: Start date | J1: End date | K1: Duration, h (ongoing cases are responsive to update date) | L1: If yes, what was the context? | M1: Scope/population? | N1: Service based restriction | O1: Facebook | P1: X (formerly Twitter) | Q1: Youtube | R1: Instagram | S1: Telegram | T1: Whatsapp | U1: Other soc. media | V1: Other VoIP apps | W1: Source
A2: Internet services restricted in the past
A3: No evidence
A4: Social media currently restricted
A5: Voice over IP (VoIP) apps currently restricted
A6: Social media and VoIP currently restricted
A7: AFRICA
A8: 1 | B8: Algeria | C8: DZ | D8: Yes | E8: TRUE | F8: FALSE | G8: FALSE | H8: FALSE | I8: 43722 | J8: 43722 | K8: 1 | L8: Internet disrupted in Algeria amid protests against military influence. | M8: Nationwide | N8: FALSE | O8: FALSE | P8: FALSE | Q8: FALSE | R8: FALSE | S8: FALSE | T8: FALSE | U8: FALSE | V8: FALSE | W8: NetBlocks
E9: FALSE | F9: FALSE | G9: TRUE | H9: FALSE | I9: 43685 | J9: 43685 | K9: 3 | L9: Algeria blocks YouTube and Google services after publication of political video. | M9: Nationwide | N9: TRUE | O9: FALSE | P9: FALSE | Q9: TRUE | R9: FALSE | S9: FALSE | T9: FALSE | U9: TRUE | V9: FALSE | W9: Netblocks
E10: TRUE | F10: FALSE | G10: FALSE | H10: FALSE | I10: 43632 | J10: 43636 | K10: 120 | L10: Algeria blocked Facebook and other social networks in an attempt tio stop students from cheating. | M10: Nationwide | N10: TRUE | O10: TRUE | P10: TRUE | Q10: FALSE | R10: TRUE | S10: TRUE | T10: TRUE | U10: TRUE | V10: TRUE | W10: Netblocks
E11: TRUE | F11: FALSE | G11: FALSE | H11: FALSE | I11: 43525 | J11: 43525 | K11: 3 | L11: Several parts of Algeria have been cut off from the internet on Friday 1 March 2019, limiting communication and media coverage of the second wave of protests against president | M11: Nationwide | N11: FALSE | O11: FALSE | P11: FALSE | Q11: FALSE | R11: FALSE | S11: FALSE | T11: FALSE | U11: FALSE | V11: FALSE | W11: Netblocks
E12: TRUE | F12: FALSE | G12: FALSE | H12: FALSE | I12: 43518 | J12: 43521 | K12: 69 | L12: The NetBlocks internet observatory has identified several regional internet disruptions across Algeria, as of Friday 22 February 2019, as the public have gone out to the streets to participate in protests. | M12: Nationwide | N12: FALSE | O12: FALSE | P12: FALSE | Q12: FALSE | R12: FALSE | S12: FALSE | T12: FALSE | U12: FALSE | V12: FALSE | W12: Netblocks
A13: 2 | B13: Angola | C13: AO | D13: No evidence | E13: FALSE | F13: FALSE | G13: FALSE | H13: FALSE | I13: N/A | J13: N/A | K13: N/A | L13: N/A | M13: N/A | N13: FALSE | O13: FALSE | P13: FALSE | Q13: FALSE | R13: FALSE | S13: FALSE | T13: FALSE | U13: FALSE | V13: FALSE
A14: 3 | B14: Benin | C14: BJ | D14: Yes | E14: FALSE | F14: TRUE | G14: FALSE | H14: FALSE | I14: 43586 | J14: 43586 | K14: 15 | L14: Internet blocked in Benin on election day. | M14: Nationwide | N14: FALSE | O14: FALSE | P14: FALSE | Q14: FALSE | R14: FALSE | S14: FALSE | T14: FALSE | U14: FALSE | V14: FALSE | W14: Netblocks
E15: TRUE | F15: FALSE | G15: FALSE | H15: FALSE | I15: 43583 | J15: 43583 | K15: 1 | L15: As Benin goes to elect its parliamentary representatives, the government has blocked social media including access to WhatsApp, Twitter, Instagram, Telegram, Facebook, LinkedIn, Tinder, and other platforms. | M15: Nationwide | N15: TRUE | O15: TRUE | P15: TRUE | Q15: FALSE | R15: TRUE | S15: TRUE | T15: TRUE | U15: TRUE | V15: FALSE | W15: Netblocks | X15: AccessNow
A16: 4 | B16: Botswana | C16: BW | D16: No evidence | E16: FALSE | F16: FALSE | G16: FALSE | H16: FALSE | I16: N/A | J16: N/A | K16: N/A | L16: N/A | M16: N/A | N16: FALSE | O16: FALSE | P16: FALSE | Q16: FALSE | R16: FALSE | S16: FALSE | T16: FALSE | U16: FALSE | V16: FALSE
A17: 5 | B17: Burkina Faso | C17: BF | D17: Social media currently restricted | E17: FALSE | F17: FALSE | G17: TRUE | H17: FALSE | I17: 44584 | J17: 44585 | K17: 35 | L17: Internet disrupted in Burkina Faso amid military uprising | M17: Nationwide | N17: FALSE | O17: FALSE | P17: FALSE | Q17: FALSE | R17: FALSE | S17: FALSE | T17: FALSE | U17: FALSE | V17: FALSE | W17: NetBlocks
E18: FALSE | F18: FALSE | G18: TRUE | H18: FALSE | I18: 44572 | J18: Ongoing | K18: =(updateDate!B$1-date(year(I18),month(I18),day(I18)+1))*24 -> 26016 | L18: On 19 January 2022, authorities admitted that they restricted access to Facebook services citing security concern. Restrictions started on 11 January. | M18: Nationwide | N18: TRUE | O18: TRUE | P18: FALSE | Q18: FALSE | R18: FALSE | S18: FALSE | T18: FALSE | U18: FALSE | V18: FALSE | W18: NetBlocks | X18: NetBlocks
E19: FALSE | F19: FALSE | G19: TRUE | H19: FALSE | I19: 44571 | J19: 44572 | K19: 15 | L19: Internet disruptions observed in Burkina Faso amid coup plot arrests. | M19: Nationwide | N19: FALSE | O19: FALSE | P19: FALSE | Q19: FALSE | R19: FALSE | S19: FALSE | T19: FALSE | U19: FALSE | V19: FALSE | W19: NetBlocks
E20: TRUE | F20: FALSE | G20: FALSE | H20: FALSE | I20: 44520 | J20: 44528 | K20: 193 | L20: Mobile internet disrupted in Burkina Faso after shooting of protesters | M20: Nationwide | N20: FALSE | O20: FALSE | P20: FALSE | Q20: FALSE | R20: FALSE | S20: FALSE | T20: FALSE | U20: FALSE | V20: FALSE | W20: NetBlocks
A21: 6 | B21: Burundi | C21: BI | D21: Yes | E21: FALSE | F21: TRUE | G21: FALSE | H21: FALSE | I21: 43971 | J21: 43972 | K21: 36 | L21: Burundi blocks social media access during presidential elections | M21: Nationwide | N21: TRUE | O21: TRUE | P21: TRUE | Q21: TRUE | R21: TRUE | S21: TRUE | T21: TRUE | U21: FALSE | V21: FALSE | W21: CPJ | X21: NetBlocks
A22: 7 | B22: Cameroon | C22: CM | D22: Yes | E22: FALSE | F22: TRUE | G22: FALSE | H22: FALSE | I22: 43394 | J22: 43394 | K22: 12 | L22: Facebook and WhatsApp restricted in Cameroon on eve of election results. | M22: Nationwide | N22: TRUE | O22: TRUE | P22: FALSE | Q22: FALSE | R22: FALSE | S22: FALSE | T22: TRUE | U22: FALSE | V22: FALSE | W22: NetBlocks
E23: TRUE | F23: FALSE | G23: FALSE | H23: FALSE | I23: 43009 | J23: 43160 | K23: 3600 | L23: The Cameroon government has again issued orders to block access to the entire internet in Anglophone regions of the country, this time in the lead up to Oct. 1, 2017, a day for planned demonstrations in those regions. | M23: Cameroon, Northwest and Southwest Regions | N23: FALSE | O23: FALSE | P23: FALSE | Q23: FALSE | R23: FALSE | S23: FALSE | T23: FALSE | U23: FALSE | V23: FALSE | W23: AccessNow | X23: AccessNow
E24: TRUE | F24: FALSE | G24: FALSE | H24: FALSE | I24: 42753 | J24: 42845 | K24: 2332 | L24: Cameroon had blocked the internet in English-speaking parts of the country. The statement also confirmed that the authorities had sent text messages direct to mobile phone subscribers, notifying them of penalties, including long jail terms, for "spreading false news" via social media. | M24: Cameroon, Northwest and Southwest Regions | N24: FALSE | O24: FALSE | P24: FALSE | Q24: FALSE | R24: FALSE | S24: FALSE | T24: FALSE | U24: FALSE | V24: FALSE | W24: Aljazeera | X24: BBC
A25: 8 | B25: Cabo Verde | C25: CV | D25: No evidence | E25: FALSE | F25: FALSE | G25: FALSE | H25: FALSE | I25: N/A | J25: N/A | K25: N/A | L25: N/A | M25: N/A | N25: FALSE | O25: FALSE | P25: FALSE | Q25: FALSE | R25: FALSE | S25: FALSE | T25: FALSE | U25: FALSE | V25: FALSE
A26: 9 | B26: The Central African Republic | C26: CF | D26: No evidence | E26: FALSE | F26: FALSE | G26: FALSE | H26: FALSE | I26: N/A | J26: N/A | K26: N/A | L26: N/A | M26: N/A | N26: FALSE | O26: FALSE | P26: FALSE | Q26: FALSE | R26: FALSE | S26: FALSE | T26: FALSE | U26: FALSE | V26: FALSE
A27: 10 | B27: Chad | C27: TD | D27: Yes | E27: FALSE | F27: FALSE | G27: TRUE | H27: FALSE | I27: 45350 | J27: 45358 | K27: 38 | L27: Metrics show a further decline in internet connectivity in #Chad following this morning's telecoms disruption; the incident comes as searches are imposed at checkpoints amid heavy gunfire in the capital following a deadly attack at the National Security Agency HQ | M27: Nationwide | N27: FALSE | O27: FALSE | P27: FALSE | Q27: FALSE | R27: FALSE | S27: FALSE | T27: FALSE | U27: FALSE | V27: FALSE | W27: Netblocks
E28: FALSE | F28: TRUE | G28: FALSE | H28: FALSE | I28: 45267 | J28: 45268 | K28: 14 | L28: Real-time network data show a nation-scale loss of internet connectivity in Chad; the incident comes amid rising political tensions just weeks ahead of a constitutional referendum | M28: Nationwide | N28: FALSE | O28: FALSE | P28: FALSE | Q28: FALSE | R28: FALSE | S28: FALSE | T28: FALSE | U28: FALSE | V28: FALSE | W28: Netblocks
E29: FALSE | F29: FALSE | G29: TRUE | H29: FALSE | I29: 44255 | J29: 44256 | K29: 32 | L29: Internet connectivity has been severely disrupted in Chad since the morning of Sunday 28 February 2021 amid reports of a deadly armed raid at the house of opposition candidate Yaya Dillo. | M29: Nationwide | N29: FALSE | O29: FALSE | P29: FALSE | Q29: FALSE | R29: FALSE | S29: FALSE | T29: FALSE | U29: FALSE | V29: FALSE | W29: NetBlocks
E30: FALSE | F30: FALSE | G30: TRUE | H30: FALSE | I30: 44034 | J30: 44116 | K30: 1961 | L30: WhatsApp messaging service blocked in Chad. | M30: Nationwide | N30: TRUE | O30: FALSE | P30: FALSE | Q30: FALSE | R30: FALSE | S30: FALSE | T30: TRUE | U30: FALSE | V30: FALSE | W30: NetBlocks
E31: TRUE | F31: FALSE | G31: FALSE | H31: FALSE | I31: 43187 | J31: 43659 | K31: 11359 | L31: Chad cut access to social media platforms, including WhatsApp, Twitter, Facebook, Instagram, and YouTube, for a staggering 472 days between 2018 and 2019. The government attempted to justify the social media blackout, stating that it was necessary for “security reasons.” However, authorities blocked access just as President Idriss Deby, who has been president of Chad since the 1990s, was pushing to stay in power until 2033. | M31: Nationwide | N31: TRUE | O31: TRUE | P31: TRUE | Q31: TRUE | R31: TRUE | S31: FALSE | T31: TRUE | U31: FALSE | V31: FALSE | W31: CNN
E32: TRUE | F32: FALSE | G32: FALSE | H32: FALSE | I32: 43125 | J32: 43126 | K32: 20 | L32: Internet access has been restored in Chad after the government ordered a shutdown in response to national protest action backed by trade unions and civil society organisations using social media. | M32: Nationwide | N32: FALSE | O32: FALSE | P32: FALSE | Q32: FALSE | R32: FALSE | S32: FALSE | T32: FALSE | U32: FALSE | V32: FALSE | W32: AccessNow | X32: ITweb
E33: FALSE | F33: TRUE | G33: FALSE | H33: FALSE | I33: 42469 | J33: 42473 | K33: 96 | L33: Chad Elections: Major internet blackout ahead of declaration | M33: Nationwide | N33: FALSE | O33: FALSE | P33: FALSE | Q33: FALSE | R33: FALSE | S33: FALSE | T33: FALSE | U33: FALSE | V33: FALSE | W33: AccessNow | X33: AfricanNews
A34: 11 | B34: Comoros | C34: KM | D34: Yes | E34: TRUE | F34: FALSE | G34: FALSE | H34: FALSE | I34: 45308 | J34: 45309 | K34: 24 | L34: Comoros disrupts internet access amid post-election protests. | M34: Nationwide | N34: FALSE | O34: FALSE | P34: FALSE | Q34: FALSE | R34: FALSE | S34: FALSE | T34: FALSE | U34: FALSE | V34: FALSE | W34: Access Now
A35: 12 | B35: Congo | C35: CG | D35: Yes | E35: FALSE | F35: TRUE | G35: FALSE | H35: FALSE | I35: 44276 | J35: 44278 | K35: 72 | L35: Republic of the Congo shut down the internet amid the presidential election. | M35: Nationwide | N35: FALSE | O35: FALSE | P35: FALSE | Q35: FALSE | R35: FALSE | S35: FALSE | T35: FALSE | U35: FALSE | V35: FALSE | W35: NetBlocks
E36: FALSE | F36: TRUE | G36: FALSE | H36: FALSE | I36: 42449 | J36: 42453 | K36: 96 | L36: Republic of the Congo shut down the internet amid the presidential election. | M36: Nationwide | N36: FALSE | O36: FALSE | P36: FALSE | Q36: FALSE | R36: FALSE | S36: FALSE | T36: FALSE | U36: FALSE | V36: FALSE | W36: Codastory | X36: Reuters
E37: FALSE | F37: FALSE | G37: TRUE | H37: FALSE | I37: 42297 | J37: 42297 | K37: 18 | L37: Government may have ordered internet shutdown in Congo-Brazzaville | M37: Nationwide | N37: FALSE | O37: FALSE | P37: FALSE | Q37: FALSE | R37: FALSE | S37: FALSE | T37: FALSE | U37: FALSE | V37: FALSE | W37: RSF | X37: AcessNow
A38: 13 | B38: Ivory Coast | C38: CI | D38: No evidence | E38: FALSE | F38: FALSE | G38: FALSE | H38: FALSE | I38: N/A | J38: N/A | K38: N/A | L38: N/A | M38: N/A | N38: FALSE | O38: FALSE | P38: FALSE | Q38: FALSE | R38: FALSE | S38: FALSE | T38: FALSE | U38: FALSE | V38: FALSE
A39: 14 | B39: Congo DR | C39: CD | D39: Yes | E39: FALSE | F39: TRUE | G39: FALSE | H39: FALSE | I39: 43465 | J39: 43465 | K39: 480 | L39: The NetBlocks internet shutdown observatory has collected technical evidence of multiple internet disruptions in the Democratic Republic of Congo as of Monday 31 December 2018 amid contested general elections. | M39: Nationwide | N39: FALSE | O39: FALSE | P39: FALSE | Q39: FALSE | R39: FALSE | S39: FALSE | T39: FALSE | U39: FALSE | V39: FALSE | W39: NetBlocks | X39: Aljazeera
E40: TRUE | F40: FALSE | G40: FALSE | H40: FALSE | I40: 43156 | J40: 43156 | K40: 10 | L40: at around 9 A.M. on February 25, 2018, internet and SMS services were blocked–this time for about 10 hours–as more protests occurred across the country, | M40: Nationwide | N40: FALSE | O40: FALSE | P40: FALSE | Q40: FALSE | R40: FALSE | S40: FALSE | T40: FALSE | U40: FALSE | V40: FALSE | W40: CPJ
E41: TRUE | F41: FALSE | G41: FALSE | H41: FALSE | I41: 43121 | J41: 43124 | K41: 84 | L41: DRC blocks internet ahead of banned protests | M41: Nationwide | N41: FALSE | O41: FALSE | P41: FALSE | Q41: FALSE | R41: FALSE | S41: FALSE | T41: FALSE | U41: FALSE | V41: FALSE | W41: AccessNow | X41: News24
E42: TRUE | F42: FALSE | G42: FALSE | H42: FALSE | I42: 43099 | J42: 43105 | K42: 144 | L42: DRC blocks internet as anti-Kabila protests planned | M42: Nationwide | N42: FALSE | O42: FALSE | P42: FALSE | Q42: FALSE | R42: FALSE | S42: FALSE | T42: FALSE | U42: FALSE | V42: FALSE | W42: Aljazeera
E43: TRUE | F43: FALSE | G43: FALSE | H43: FALSE | I43: 42954 | J43: 42958 | K43: 93 | L43: Democratic Republic of Congo orders telco Orange to slow internet capacity | M43: Nationwide | N43: TRUE | O43: TRUE | P43: TRUE | Q43: FALSE | R43: TRUE | S43: FALSE | T43: TRUE | U43: FALSE | V43: FALSE | W43: AccessNow
E44: TRUE | F44: FALSE | G44: FALSE | H44: FALSE | I44: 42723 | J44: 42723 | K44: 12 | L44: The government of the Democratic Republic of the Congo blocked social media sites. | M44: Nationwide | N44: TRUE | O44: TRUE | P44: TRUE | Q44: FALSE | R44: FALSE | S44: FALSE | T44: TRUE | U44: FALSE | V44: FALSE | W44: CGTN | X44: AccessNow
A45: 15 | B45: Djibouti | C45: DJ | D45: No evidence | E45: FALSE | F45: FALSE | G45: FALSE | H45: FALSE | I45: N/A | J45: N/A | K45: N/A | L45: N/A | M45: N/A | N45: FALSE | O45: FALSE | P45: FALSE | Q45: FALSE | R45: FALSE | S45: FALSE | T45: FALSE | U45: FALSE | V45: FALSE
A46: 16 | B46: Egypt | C46: EG | D46: Yes | E46: TRUE | F46: FALSE | G46: FALSE | H46: FALSE | I46: 43730 | J46: 43732 | K46: 54 | L46: Facebook Messenger, social media and news sites were disrupted in Egypt amid protests in 2019, September. | M46: Nationwide | N46: TRUE | O46: TRUE | P46: TRUE | Q46: FALSE | R46: FALSE | S46: FALSE | T46: FALSE | U46: FALSE | V46: TRUE | W46: Netblocks
A47: 17 | B47: Equatorial Guinea | C47: GQ | D47: Yes | E47: FALSE | F47: TRUE | G47: FALSE | H47: FALSE | I47: 43035 | J47: 43051 | K47: 240 | L47: The government restricted and disrupted access to the internet and censored online content. During the 2017 legislative and municipal elections, the government blocked all access to the internet for approximately 10 days. | M47: Nationwide | N47: FALSE | O47: FALSE | P47: FALSE | Q47: FALSE | R47: FALSE | S47: FALSE | T47: FALSE | U47: FALSE | V47: FALSE | W47: State GOV Report | X47: eNCA
E48: FALSE | F48: TRUE | G48: FALSE | H48: FALSE | I48: 43051 | J48: 43051 | K48: 144 | L48: During the November elections, authorities completely shut down the internet. | M48: Nationwide | N48: FALSE | O48: FALSE | P48: FALSE | Q48: FALSE | R48: FALSE | S48: FALSE | T48: FALSE | U48: FALSE | V48: FALSE | W48: State GOV Report | X48: IODA
A49: 18 | B49: Eritrea | C49: ER | D49: Social media currently restricted | E49: TRUE | F49: FALSE | G49: FALSE | H49: FALSE | I49: 43600 | J49: 43609 | K49: 240 | L49: Eritrea's government closed access to social media in the days leading up to the country’s Independence Day on May 24, 2019, forcing citizens to use proxy servers and VPNs to bypass those restrictions. | M49: Nationwide | N49: TRUE | O49: TRUE | P49: TRUE | Q49: FALSE | R49: TRUE | S49: FALSE | T49: FALSE | U49: FALSE | V49: FALSE | W49: African State | X49: CPJ org | Y49: Borgen Project
E50: FALSE | F50: FALSE | G50: TRUE | H50: FALSE | I50: 40544 | J50: Ongoing | K50: =(updateDate!B$1-date(year(I50),month(I50),day(I50)+1))*24 -> 122688 | L50: According to Freedom House, Eritrea has one of the worst infrastructures in Africa, it is possible that some ISPs deliberately block services, but the government’s poor human rights record indicates that the inaccessibility of YouTube could be related to censorship. | M50: Nationwide | N50: TRUE | O50: FALSE | P50: FALSE | Q50: TRUE | R50: FALSE | S50: FALSE | T50: FALSE | U50: FALSE | V50: FALSE | W50: MotherJones
A51: 19 | B51: Eswatini | C51: SZ | D51: Yes | E51: TRUE | F51: FALSE | G51: FALSE | H51: FALSE | I51: 44484 | J51: 44484 | K51: 2 | L51: Authorities in Eswatini have again disrupted access to the internet and social media platforms in response to ongoing pro-democracy protests. The government shut down social media platforms including Facebook, WhatsApp, and Twitter for approximately two hours. | M51: Nationwide | N51: TRUE | O51: TRUE | P51: TRUE | Q51: FALSE | R51: FALSE | S51: FALSE | T51: TRUE | U51: FALSE | V51: FALSE | W51: AccessNow
E52: TRUE | F52: FALSE | G52: FALSE | H52: FALSE | I52: 44376 | J52: 44380 | K52: 89 | L52: Authorities shut internet down on June 29, in response to large-scale pro-democracy protests. | M52: Nationwide | N52: FALSE | O52: FALSE | P52: FALSE | Q52: FALSE | R52: FALSE | S52: FALSE | T52: FALSE | U52: FALSE | V52: FALSE | W52: AccessNow
A53: 20 | B53: Ethiopia | C53: ET | D53: Yes | E53: TRUE | F53: FALSE | G53: FALSE | H53: FALSE | I53: 44967 | J53: Ongoing | K53: =(updateDate!B$1-date(year(I53),month(I53),day(I53)+1))*24 -> 16536 | L53: YouTube has also been restricted following protests and deadly violence over an apparent state attempt to divide the Ethiopian Orthodox Church. | M53: Nationwide | N53: TRUE | O53: FALSE | P53: FALSE | Q53: TRUE | R53: FALSE | S53: FALSE | T53: FALSE | U53: FALSE | V53: FALSE | W53: NetBlocks
E54: TRUE | F54: FALSE | G54: FALSE | H54: FALSE | I54: 44966 | J54: Ongoing | K54: =(updateDate!B$1-date(year(I54),month(I54),day(I54)+1))*24 -> 16560 | L54: Facebook, Telegram and TikTok restricted amid protests over the split of the Ethiopian Orthodox Tewhado Church. | M54: Nationwide | N54: TRUE | O54: TRUE | P54: FALSE | Q54: FALSE | R54: FALSE | S54: TRUE | T54: FALSE | U54: TRUE | V54: FALSE | W54: NetBlocks
E55: TRUE | F55: FALSE | G55: FALSE | H55: FALSE | I55: 44012 | J55: 44035 | K55: 552 | L55: Ethiopia is entering its third week without internet service after days of deadly unrest, as the government in Africa's diplomatic and aviation hub says it's trying to prevent speech that could further inflame ethnic tensions. | M55: Nationwide | N55: FALSE | O55: FALSE | P55: FALSE | Q55: FALSE | R55: FALSE | S55: FALSE | T55: FALSE | U55: FALSE | V55: FALSE | W55: Twitter | X55: NetBlocks
E56: FALSE | F56: FALSE | G56: TRUE | H56: FALSE | I56: 44139 | J56: Ongoing | K56: =(updateDate!B$1-date(year(I56),month(I56),day(I56)+1))*24 -> 36408 | L56: Tigray has been mostly without internet, telecommunications and banking since war broke out between federal government troops and forces led by the Tigray People’s Liberation Front (TPLF) in November 2020. A ceasefire deal between the warring sides was signed in South Africa in November of 2022. It commits Ethiopia’s government to restoring Tigray’s basic services, but the communications blackout has not yet been lifted. | M56: Tigray region | N56: FALSE | O56: FALSE | P56: FALSE | Q56: FALSE | R56: FALSE | S56: FALSE | T56: FALSE | U56: FALSE | V56: FALSE | W56: DW.com
E57: FALSE | F57: FALSE | G57: TRUE | H57: FALSE | I57: 43833 | J57: 43922 | K57: 2136 | L57: The shutdown has been imposed in areas under federal military control and comes amid reports of government military operations against the armed wing of the once-banned Oromo Liberation Front (OLF). | M57: Oromia | N57: FALSE | O57: FALSE | P57: FALSE | Q57: FALSE | R57: FALSE | S57: FALSE | T57: FALSE | U57: FALSE | V57: FALSE | W57: AccessNow | X57: HRW
E58: FALSE | F58: FALSE | G58: TRUE | H58: FALSE | I58: 43643 | J58: 43699 | K58: 1368 | L58: Several social media platforms, including WhatsApp, Telegram, and Facebook, were blocked intermittently in June. | M58: Nationwide | N58: TRUE | O58: TRUE | P58: FALSE | Q58: FALSE | R58: TRUE | S58: TRUE | T58: TRUE | U58: FALSE | V58: FALSE | W58: Freedom House | X58: Netblocks
E59: FALSE | F59: FALSE | G59: TRUE | H59: FALSE | I59: 43643 | J59: 43648 | K59: 144 | L59: Several social media platforms, including WhatsApp, Telegram, and Facebook, were blocked intermittently in June. | M59: Nationwide | N59: TRUE | O59: FALSE | P59: FALSE | Q59: TRUE | R59: FALSE | S59: FALSE | T59: FALSE | U59: FALSE | V59: FALSE | W59: Freedom House | X59: Netblocks
E60: FALSE | F60: FALSE | G60: TRUE | H60: FALSE | I60: 43639 | J60: 43643 | K60: 108 | L60: Internet shutdown in Ethiopia amid reports of attempted coup. | M60: Nationwide | N60: FALSE | O60: FALSE | P60: FALSE | Q60: FALSE | R60: FALSE | S60: FALSE | T60: FALSE | U60: FALSE | V60: FALSE | W60: Netblocks | X60: Netblocks
E61: TRUE | F61: FALSE | G61: FALSE | H61: FALSE | I61: 43360 | J61: 43362 | K61: 36 | L61: In Ethiopia, mobile internet cut in the capital amid clashes and protests | M61: Addis Ababa | N61: FALSE | O61: FALSE | P61: FALSE | Q61: FALSE | R61: FALSE | S61: FALSE | T61: FALSE | U61: FALSE | V61: FALSE | W61: AccessNow | X61: CPJ
E62: FALSE | F62: FALSE | G62: TRUE | H62: FALSE | I62: 43316 | J62: 43336 | K62: 480 | L62: Amid growing tensions between the national and regional governments in the Somali region of Ethiopia, the national government has resorted to shutting off broadband and mobile internet. | M62: Harar, Dire Dawa and Somali | N62: FALSE | O62: FALSE | P62: FALSE | Q62: FALSE | R62: FALSE | S62: FALSE | T62: FALSE | U62: FALSE | V62: FALSE | W62: AccessNow
E63: TRUE | F63: FALSE | G63: FALSE | H63: FALSE | I63: 43081 | J63: 43206 | K63: 2952 | L63: Government repeatedly was cutting off the internet in order to control the spread of information and materials relating to anti-government protests and human rights abuse. | M63: Nationwide | N63: FALSE | O63: FALSE | P63: FALSE | Q63: FALSE | R63: FALSE | S63: FALSE | T63: FALSE | U63: FALSE | V63: FALSE | W63: AccessNow | X63: African news | Y63: Reuters
E64: TRUE | F64: FALSE | G64: FALSE | H64: FALSE | I64: 42588 | J64: 42590 | K64: 40 | L64: Several people are feared dead in clashes in north-western Ethiopia between police and anti-government protesters, amid a wave of unrest. Authorities have banned demonstrations and blocked social media. | M64: Nationwide | N64: TRUE | O64: FALSE | P64: FALSE | Q64: TRUE | R64: FALSE | S64: FALSE | T64: FALSE | U64: TRUE | V64: FALSE | W64: AccessNow | X64: BBC
A65: 21 | B65: Gabon | C65: GA | D65: Yes | E65: FALSE | F65: TRUE | G65: FALSE | H65: FALSE | I65: 45164 | J65: 45168 | K65: 96 | L65: Following presidential, legislative and municipal elections, which were criticized by the opposition, the internet has been restricted nationwide. | M65: Nationwide | N65: FALSE | O65: FALSE | P65: FALSE | Q65: FALSE | R65: FALSE | S65: FALSE | T65: FALSE | U65: FALSE | V65: FALSE | W65: France24 | X65: IODA | Y65: NetBlocks
E66: FALSE | F66: FALSE | G66: TRUE | H66: FALSE | I66: 43472 | J66: 43473 | K66: 28 | L66: The NetBlocks internet shutdown observatory has detected evidence of a major internet disruption in Gabon. The shutdown comes as military forces have reportedly gained power, with President Ali Bongo reportedly abroad seeking medical treatment. | M66: Libreville and Port-Gentil | N66: FALSE | O66: FALSE | P66: FALSE | Q66: FALSE | R66: FALSE | S66: FALSE | T66: FALSE | U66: FALSE | V66: FALSE | W66: NetBlocks
E67: FALSE | F67: TRUE | G67: FALSE | H67: FALSE | I67: 42614 | J67: 42641 | K67: 372 | L67: The internet and social media platforms were blocked after the re-election of Bongo. On September 5th, a 12-hour-a-day internet curfew was imposed. | M67: Nationwide | N67: FALSE | O67: FALSE | P67: FALSE | Q67: FALSE | R67: FALSE | S67: FALSE | T67: FALSE | U67: FALSE | V67: FALSE | W67: QZ | X67: QZ
A68: 22 | B68: Gambia | C68: GM | D68: Yes | E68: FALSE | F68: TRUE | G68: FALSE | H68: FALSE | I68: 42705 | J68: 42706 | K68: 38 | L68: Gambia’s government has shut down the internet on the eve of elections | M68: Nationwide | N68: FALSE | O68: FALSE | P68: FALSE | Q68: FALSE | R68: FALSE | S68: FALSE | T68: FALSE | U68: FALSE | V68: FALSE | W68: QZ
A69: 23 | B69: Ghana | C69: GH | D69: No evidence | E69: FALSE | F69: FALSE | G69: FALSE | H69: FALSE | I69: N/A | J69: N/A | K69: N/A | L69: N/A | M69: N/A | N69: FALSE | O69: FALSE | P69: FALSE | Q69: FALSE | R69: FALSE | S69: FALSE | T69: FALSE | U69: FALSE | V69: FALSE
A70: 24 | B70: Guinea | C70: GN | D70: Yes | E70: FALSE | F70: FALSE | G70: TRUE | H70: FALSE | I70: 45254 | J70: Ongoing | K70: =(updateDate!B$1-date(year(I70),month(I70),day(I70)+1))*24 -> 9648 | L70: Metrics show a disruption to multiple social media and messaging platforms in the Republic of #Guinea including Facebook, WhatsApp, Telegram; access remains possible through the use of VPN services. The incident comes amid political tension in the country. | M70: Nationwide | N70: TRUE | O70: TRUE | P70: FALSE | Q70: FALSE | R70: FALSE | S70: TRUE | T70: TRUE | U70: FALSE | V70: FALSE | W70: Netblocks
E71: TRUE | F71: FALSE | G71: FALSE | H71: FALSE | I71: 45063 | J71: 45069 | K71: 168 | L71: Many of the most popular social media platforms, including Facebook, Instagram and WhatsApp, were restricted across the country. The incident came as citizens prepared to take the streets for anti-government demonstrations. | M71: Nationwide | N71: TRUE | O71: TRUE | P71: FALSE | Q71: TRUE | R71: TRUE | S71: TRUE | T71: TRUE | U71: TRUE | V71: TRUE | W71: NetBlocks | X71: TechRadar
E72: FALSE | F72: TRUE | G72: FALSE | H72: FALSE | I72: 44127 | J72: 44131 | K72: 100 | L72: Internet disrupted in Guinea ahead of presidential election. | M72: Nationwide | N72: FALSE | O72: FALSE | P72: FALSE | Q72: FALSE | R72: FALSE | S72: FALSE | T72: FALSE | U72: FALSE | V72: FALSE | W72: NetBlocks
E73: FALSE | F73: TRUE | G73: FALSE | H73: FALSE | I73: 43911 | J73: 43912 | K73: 22 | L73: Guinea cuts internet access and blocks social media on referendum day. | M73: Nationwide | N73: TRUE | O73: TRUE | P73: TRUE | Q73: FALSE | R73: TRUE | S73: FALSE | T73: TRUE | U73: FALSE | V73: FALSE | W73: AccessNow | X73: NetBlocks
E74: FALSE | F74: TRUE | G74: FALSE | H74: FALSE | I74: 43910 | J74: 43911 | K74: 3 | L74: Internet cut across Guinea ahead of elections. | M74: Nationwide | N74: FALSE | O74: FALSE | P74: FALSE | Q74: FALSE | R74: FALSE | S74: FALSE | T74: FALSE | U74: FALSE | V74: FALSE | W74: NetBlocks
A75: 25 | B75: Guinea-Bissau | C75: GW | D75: No evidence | E75: FALSE | F75: FALSE | G75: FALSE | H75: FALSE | I75: N/A | J75: N/A | K75: N/A | L75: N/A | M75: N/A | N75: FALSE | O75: FALSE | P75: FALSE | Q75: FALSE | R75: FALSE | S75: FALSE | T75: FALSE | U75: FALSE | V75: FALSE
A76: 26 | B76: Kenya | C76: KE | D76: Yes | E76: FALSE | F76: FALSE | G76: TRUE | H76: FALSE | I76: 45604 | J76: Ongoing | K76: =(updateDate!B$1-date(year(I76),month(I76),day(I76)+1))*24 -> 1248 | L76: Metrics show that Telegram has been restricted in #Kenya, corroborating user reports of disruption; the measure comes as students sit KCSE exams and is consistent with past restrictions of Telegram observed in the country as a measure to limit cheating during exams | M76: Nationwide | N76: TRUE | O76: FALSE | P76: FALSE | Q76: FALSE | R76: FALSE | S76: TRUE | T76: FALSE | U76: FALSE | V76: FALSE | W76: NetBlocks
E77: TRUE | F77: FALSE | G77: FALSE | H77: FALSE | I77: 45468 | J77: 45468 | K77: 7 | L77: Live network data show a major disruption to internet connectivity in #Kenya; the incident comes amidst a deadly crackdown by police on #RejectFinanceBill2024 protesters a day after authorities claimed there would be no internet shutdown | M77: Nationwide | N77: FALSE | O77: FALSE | P77: FALSE | Q77: FALSE | R77: FALSE | S77: FALSE | T77: FALSE | U77: FALSE | V77: FALSE | W77: https://x.com/netblocks/status/1805598808035774970
A78: 27 | B78: Lesotho | C78: LS | D78: No evidence | E78: FALSE | F78: FALSE | G78: FALSE | H78: FALSE | I78: N/A | J78: N/A | K78: N/A | L78: N/A | M78: N/A | N78: FALSE | O78: FALSE | P78: FALSE | Q78: FALSE | R78: FALSE | S78: FALSE | T78: FALSE | U78: FALSE | V78: FALSE
A79: 28 | B79: Liberia | C79: LR | D79: Yes | E79: TRUE | F79: FALSE | G79: FALSE | H79: FALSE | I79: 43623 | J79: 43623 | K79: 6 | L79: Twitter, Facebook, Instagram, Snapchat and messaging app WhatsApp have been blocked by internet providers in Liberia as of Friday 7 June according to real-time network measurement data from the NetBlocks internet observatory. | M79: Nationwide | N79: TRUE | O79: TRUE | P79: TRUE | Q79: FALSE | R79: TRUE | S79: FALSE | T79: TRUE | U79: TRUE | V79: FALSE | W79: Netblocks
A80: 29 | B80: Libya | C80: LY | D80: Yes | E80: FALSE | F80: FALSE | G80: TRUE | H80: FALSE | I80: 42570 | J80: 42570 | K80: 10 | L80: "Act of sabotage" takes down much of Internet in Libya | M80: Misurata, Zliten and Al-Khamis | N80: FALSE | O80: FALSE | P80: FALSE | Q80: FALSE | R80: FALSE | S80: FALSE | T80: FALSE | U80: FALSE | V80: FALSE | W80: AccessNow | X80: Eanlibya
A81: 30 | B81: Madagascar | C81: MG | D81: No evidence | E81: FALSE | F81: FALSE | G81: FALSE | H81: FALSE | I81: N/A | J81: N/A | K81: N/A | L81: N/A | M81: N/A | N81: FALSE | O81: FALSE | P81: FALSE | Q81: FALSE | R81: FALSE | S81: FALSE | T81: FALSE | U81: FALSE | V81: FALSE
A82: 31 | B82: Malawi | C82: MW | D82: Yes | E82: FALSE | F82: TRUE | G82: FALSE | H82: FALSE | I82: 43606 | J82: 43606 | K82: 6 | L82: As results from general election trickled in, numerous internet providers in the southeastern African state experienced service interruptions that lasted for up to six hours. | M82: Nationwide | N82: FALSE | O82: FALSE | P82: FALSE | Q82: FALSE | R82: FALSE | S82: FALSE | T82: FALSE | U82: FALSE | V82: FALSE | W82: QZ.com | X82: Netblocks
A83: 32 | B83: Mali | C83: ML | D83: Yes | E83: TRUE | F83: FALSE | G83: FALSE | H83: FALSE | I83: 44022 | J83: 44027 | K83: 120 | L83: Social media restricted in Mali amid protests against president. | M83: Nationwide | N83: TRUE | O83: TRUE | P83: TRUE | Q83: FALSE | R83: TRUE | S83: FALSE | T83: TRUE | U83: TRUE | V83: FALSE | W83: NetBlocks
E84: FALSE | F84: TRUE | G84: FALSE | H84: FALSE | I84: 43328 | J84: 43328 | K84: 6 | L84: Mali elections marred by internet disruptions | M84: Nationwide | N84: FALSE | O84: FALSE | P84: FALSE | Q84: FALSE | R84: FALSE | S84: FALSE | T84: FALSE | U84: FALSE | V84: FALSE | W84: NetBlocks
E85: FALSE | F85: TRUE | G85: FALSE | H85: FALSE | I85: 43310 | J85: 43310 | K85: 3 | L85: According to this data, WhatsApp and Twitter, among other apps and sites, were not available for several hours on election night. It was suspected that the sites were closed on the orders of the government. | M85: Nationwide | N85: TRUE | O85: FALSE | P85: TRUE | Q85: FALSE | R85: FALSE | S85: FALSE | T85: TRUE | U85: FALSE | V85: FALSE | W85: DW.com
E86: FALSE | F86: FALSE | G86: TRUE | H86: FALSE | I86: 42599 | J86: 42599 | K86: 24 | L86: Internet users in Bamako, Mali reported not being able to use Facebook and Twitter after protests against the detention of a popular radio host on Wednesday (Aug. 17) turned violent, resulting in three deaths. | M86: Nationwide | N86: TRUE | O86: TRUE | P86: TRUE | Q86: FALSE | R86: FALSE | S86: FALSE | T86: FALSE | U86: FALSE | V86: FALSE | W86: QZ
A87: 33 | B87: Mauritania | C87: MR | D87: Yes | E87: FALSE | F87: FALSE | G87: TRUE | H87: FALSE | I87: 42595 | J87: 42595 | K87: 6 | L87: Traffic data show a pattern of widescale internet disruptions in Mauritania during morning and afternoon national school exams; the incidents are consistent with blackouts reported in past years to prevent cheating and paper leaks | M87: Nationwide | N87: FALSE | O87: FALSE | P87: FALSE | Q87: FALSE | R87: FALSE | S87: FALSE | T87: FALSE | U87: FALSE | V87: FALSE | W87: Netblocks
E88: TRUE | F88: FALSE | G88: FALSE | H88: FALSE | I88: 45108 | J88: 45129 | K88: 528 | L88: Network traffic data show a major disruption to connectivity in #Mauritania from midnight, with mobile internet restricted amid protests rejecting the results of this weekend's presidential elections | M88: Nationwide | N88: FALSE | O88: FALSE | P88: FALSE | Q88: FALSE | R88: FALSE | S88: FALSE | T88: FALSE | U88: FALSE | V88: FALSE | W88: https://twitter.com/netblocks/status/1808190009008136209 | X88: BenjaminDada
E89: TRUE | F89: FALSE | G89: FALSE | H89: FALSE | I89: 45077 | J89: 45084 | K89: 168 | L89: Metrics show a significant decline in internet traffic in Mauritania amid protests after the death of an individual in police custody. | M89: Nationwide | N89: FALSE | O89: FALSE | P89: FALSE | Q89: FALSE | R89: FALSE | S89: FALSE | T89: FALSE | U89: FALSE | V89: FALSE | W89: NetBlocks | X89: IODA
E90: TRUE | F90: FALSE | G90: FALSE | H90: FALSE | I90: 44991 | J90: 44997 | K90: 144 | L90: A nationwide disruption to mobile internet traffic following a prison riot at the Nouakchott Civil Prison in the capital’s Tevragh Zeina district, which led to the killing of two guards and the escape of four prisoners. | M90: Nationwide | N90: FALSE | O90: FALSE | P90: FALSE | Q90: FALSE | R90: FALSE | S90: FALSE | T90: FALSE | U90: FALSE | V90: FALSE | W90: NetBlocks
E91: FALSE | F91: TRUE | G91: FALSE | H91: FALSE | I91: 43641 | J91: 43649 | K91: 192 | L91: The Mauritanian government interrupted internet services and blocked access to all social media platforms in the country for 10 hours, on 3 consecutive days, to prevent cheating during exams in 2019. | M91: Nationwide | N91: FALSE | O91: FALSE | P91: FALSE | Q91: FALSE | R91: FALSE | S91: FALSE | T91: FALSE | U91: FALSE | V91: FALSE | W91: IFEX | X91: Netblocks
A92: 34 | B92: Mauritius | C92: MU | D92: Yes | E92: FALSE | F92: TRUE | G92: FALSE | H92: FALSE | I92: 45600 | J92: 45601 | K92: 12 | L92: Metrics show multiple social media platforms have been restricted in Mauritius; the incident comes as authorities order ISPs to suspend access until after elections later this month, on grounds of national security after the leaking of "certain" audio clips | M92: Nationwide | N92: FALSE | O92: TRUE | P92: TRUE | Q92: TRUE | R92: FALSE | S92: FALSE | T92: FALSE | U92: TRUE | V92: FALSE | W92: NetBlocks
A93: 35 | B93: Morocco | C93: MA | D93: Yes | E93: FALSE | F93: FALSE | G93: FALSE | H93: TRUE | I93: 42370 | J93: 42668 | K93: 7800 | L93: Morocco banned Skype, Viber, WhatsApp and Facebook Messenger (VoIP). | M93: Nationwide | N93: TRUE | O93: FALSE | P93: FALSE | Q93: FALSE | R93: FALSE | S93: FALSE | T93: TRUE | U93: FALSE | V93: TRUE | W93: MiddleEastEye
A94: 36 | B94: Mozambique | C94: MZ | D94: Social media currently restricted | E94: TRUE | F94: FALSE | G94: FALSE | H94: FALSE | I94: 45603 | J94: 45604 | K94: 12 | L94: Metrics show internet has been cut in Mozambique for a 5th day as authorities crack down on the March on Maputo movement; a series of curfew-style internet shutdowns and social media restrictions have limited the visibility of opposition protests over election results | M94: Nationwide | N94: FALSE | O94: FALSE | P94: FALSE | Q94: FALSE | R94: FALSE | S94: FALSE | T94: FALSE | U94: FALSE | V94: FALSE | W94: NetBlocks
E95: TRUE | F95: FALSE | G95: FALSE | H95: FALSE | I95: 45602 | J95: 45603 | K95: 12 | L95: Traffic data indicate Mozambique is now in the fourth day of curfew-style mobile internet blackouts. The shutdown follows protests over disputed election results, and is the latest in a series of mass-censorship measures imposed by the government | M95: Nationwide | N95: FALSE | O95: FALSE | P95: FALSE | Q95: FALSE | R95: FALSE | S95: FALSE | T95: FALSE | U95: FALSE | V95: FALSE | W95: NetBlocks
E96: TRUE | F96: FALSE | G96: FALSE | H96: FALSE | I96: 45601 | J96: 45602 | K96: 12 | L96: Traffic data indicate Mozambique is now in the third day of curfew-style mobile internet blackouts. The shutdown follows protests over disputed election results, and is the latest in a series of mass-censorship measures imposed by the government | M96: Nationwide | N96: FALSE | O96: FALSE | P96: FALSE | Q96: FALSE | R96: FALSE | S96: FALSE | T96: FALSE | U96: FALSE | V96: FALSE | W96: NetBlocks
E97: TRUE | F97: FALSE | G97: FALSE | H97: FALSE | I97: 45600 | J97: 45601 | K97: 12 | L97: Traffic data indicate Mozambique is now in the second day of curfew-style mobile internet blackouts. The shutdown follows protests over disputed election results, and is the latest in a series of mass-censorship measures imposed by the government | M97: Nationwide | N97: FALSE | O97: FALSE | P97: FALSE | Q97: FALSE | R97: FALSE | S97: FALSE | T97: FALSE | U97: FALSE | V97: FALSE | W97: NetBlocks
E98: TRUE | F98: FALSE | G98: FALSE | H98: FALSE | I98: 45599 | J98: 45600 | K98: 12 | L98: Traffic data indicate Mozambique is now in the first day of curfew-style mobile internet blackouts. The shutdown follows protests over disputed election results, and is the latest in a series of mass-censorship measures imposed by the government | M98: Nationwide | N98: FALSE | O98: FALSE | P98: FALSE | Q98: FALSE | R98: FALSE | S98: FALSE | T98: FALSE | U98: FALSE | V98: FALSE | W98: NetBlocks
E99: TRUE | F99: FALSE | G99: FALSE | H99: FALSE | I99: 45599 | J99: Ongoing | K99: =(updateDate!B$1-date(year(I99),month(I99),day(I99)+1))*24 -> 1368 | L99: Live metrics show restrictions to social media and messaging platforms Facebook, Instagram and WhatsApp in #Mozambique; the incident follows mobile data disruptions last week and comes as protesters prepare to hit the streets over disputed election results | M99: Nationwide | N99: TRUE | O99: FALSE | P99: FALSE | Q99: TRUE | R99: FALSE | S99: TRUE | T99: FALSE | U99: TRUE | V99: FALSE | W99: Netblocks
E100: TRUE | F100: FALSE | G100: FALSE | H100: FALSE | I100: 45596 | J100: Ongoing | K100: =(updateDate!B$1-date(year(I100),month(I100),day(I100)+1))*24 -> 1440 | L100: Live metrics show restrictions to social media and messaging platforms Facebook, Instagram and WhatsApp in Mozambique; the incident follows mobile data disruptions last week and comes as protesters prepare to hit the streets over disputed election results | M100: Nationwide | N100: TRUE | O100: TRUE | P100: FALSE | Q100: FALSE | R100: TRUE | S100: FALSE | T100: TRUE | U100: FALSE | V100: FALSE | W100: Netblocks
...

Sheet internetshutdowns.in cases
B1: Country | C1: ISO-alpha2 Code | D1: Social media bans / heavy disruptions within the period of 2015 - present? | E1: Related w/ protests | F1: Related w/ elections | G1: Related w/ political turmoil | H1: Related w/ country’s internet law | I1: Start date | J1: End date | K1: Duration, h (Updates everyday) | L1: If yes, what was the context? | M1: Scope/population? | N1: Service based restriction | O1: Facebook | P1: Twitter | Q1: Youtube | R1: Instagram | S1: Telegram | T1: Whatsapp | U1: Other soc. media | V1: Other VoIP apps | W1: Source | Z1: Notes
A2: Social media blocked in the past
A3: No evidence
A4: Social media currently blocked
A5: Voice over IP (VoIP) apps currently blocked
A6: Social media and VoIP currently restricted
A7: ASIA

Sheet Other cases
A1: Country | B1: Affected service | C1: Date | D1: Description | E1: Sources
A2: Russia | B2: Navalny app | C2: 44456 | D2: Opposition election voting app Navalny removed from Apple App Store and Google Play Store in Russia. Removed from Apple App Store and Google Play Store on 9/17/2021. Reinstated by Google on 10/09/2021. Reinstated on Apple App Store on 4/5/2022. | E2: NetBlocks | F2: Apple Censorship | G2: https://russianfreepress.com/2021/10/09/google-restored-the-navalny-app-videos-and-smart-voting-documents/
A3: Slovakia | B3: Twitch | C3: 44371 | D3: One Slovakian ISP (O2) banned Twitch as a result of a streamer playing poker live. Other ISPs followed or were due to follow. Slovakia has strict laws surrounding gambling, as the streamer was "said to have broken laws around the operation of promotion of gambling by playing internet poker." | E3: Dexerto.com | F3: Guided.news
A4: U.K. | B4: Public Wi-Fi in London Underground | C4: 43572 | D4: UK police shut off Wi-Fi in London Tube stations to deter climate protestors. | E4: Independent
A5: Venezuela | B5: Wikipedia | C5: 43477 | D5: Wikipedia blocked by the largest telecommunications provider CANTV, following a bitter edit war where editors put forward conflicting views. | E5: NetBlocks | F5: VEsinFiltro | G5: OONI
A6: Spain | B6: Catalonian websites | C6: September - October 2017 | D6: During the days before the 2017 Catalan independence referendum, the Civil Guard closed the official website of the referendum. It also closed or blocked multiple alternative domains, official and non official. On 20 September the Civil Guard entered the headquarters of the Fundació puntCat, which administers the top-level domain .cat, and arrested the director of IT, Pep Masoliver. By 27 September, more than 140 websites related to the referendum were blocked. On 11 October, the official website of the Assemblea Nacional Catalana organization, assemblea.cat, was blocked. | E6: Wikipedia | F6: VentureBeat
A7: Philippines | B7: Mobile internet | C7: 2015 - 2018 | D7: The first known mobile network shutdown in the Philippines was during the Papal visit in 2015. Since then, signal jamming has been frequently used as a go-to security mechanism for large events, citing public safety as the main concern. | E7: Access Now | F7: Freedom House | G7: Inquirer.net
A8: Guyana | B8: VoIP services | C8: 12/2/2008 - ongoing | D8: Skype (and other VoIP services?) blocked nationwide. | E8: NordVPN blog | F8: VPN Overview | G8: freegyvoip.com
A9: Lebanon | B9: Internet service | C9: 44576 | D9: Loss of internet service in parts of Beirut, Lebanon, following an escalating pattern of destabilization of infrastructure as the country’s energy crisis deepens. | E9: NetBlocks
A10: Pakistan | B10: Slate Magazine website | C10: 43294 | D10: Slate Magazine blocked in Pakistan amid deteriorating conditions for online media freedom. | E10: https://netblocks.org/reports/slate-magazine-blocked-in-pakistan-qr8Vary5
A11: Pakistan | B11: Political party website | C11: 43254 | D11: Evidence of blocking of a political party website, operated by the Awami Workers Party, in the run up to general elections scheduled on the 25th of July 2018. | E11: https://netblocks.org/reports/study-reveals-extent-of-awami-workers-political-party-website-block-in-pakistan-zgBLrk84
A12: Venezuela | B12: Humanitarian aid volunteer web platform | C12: 43512 | D12: Volunteer registration web platform for Venezuela’s Coalition for Aid and Freedom blocked as members took to the streets, | E12: https://netblocks.org/reports/venezuela-humanitarian-aid-platform-blocked-GnAgJk8p
A13: Venezuela | B13: Wikipedia | C13: 43477 | D13: Wikipedia blocked in Venezuela as internet controls tighten. | E13: https://netblocks.org/reports/wikipedia-blocked-in-venezuela-as-internet-controls-tighten-XaAwR08M
A14: Russia | B14: Internet service | C14: 44265 | D14: Internet disrupted in Russia as regulator imposed new measures. | E14: https://netblocks.org/reports/internet-disrupted-in-russia-as-regulator-imposes-new-measures-l8WxaQAO
A15: Algeria | B15: Internet service | C15: 44087 | D15: Internet connectivity significantly disrupted for one hour during school exams. | E15: https://netblocks.org/reports/social-media-restricted-and-internet-cut-during-algeria-school-exams-xAGolxAz
A16: Algeria | B16: Facebook, Twitter, other social media | C16: 42541 | D16: Facebook, Twitter and other social networks blocked in an attempt to stop students from cheating during exams. | E16: The Independent
A17: Global | B17: Facebook, WhatsApp, Instagram, Messenger | C17: 43569 | D17: Several Facebook, WhatsApp, Instagram and Messenger servers showed signs of partial global outage, with availability falling to around 40% globally. | E17: https://netblocks.org/reports/facebook-whatsapp-instagram-messenger-down-globally-WJBZvWB6
A18: Iran | B18: Internet service | C18: 44020 | D18: Power-cut and outage in Armenia resulted in a knock-on loss of international connectivity in Iran. | E18: https://netblocks.org/reports/internet-in-iran-disrupted-knock-on-effect-of-power-cut-in-armenia-RyjPQ1Ag
A19: Egypt | B19: 34k domains | C19: 43570 | D19: Internet providers in Egypt blocked access to an estimated 34,000 internet domains in an apparent bid to stamp out an opposition campaign. Websites included prominent technology startups, self-help websites, celebrity homepages, dozens of Open Source technology projects, as well as Bahá’í, Jewish and Islamic faith group websites and NGOs. | E19: https://netblocks.org/reports/egypt-filters-34000-domains-in-bid-to-block-opposition-campaign-platform-7eA1blBp
A20: Egypt | B20: bit.ly | C20: 43573 | D20: Several Internet providers in Egypt restricted access to the bit.ly URL shortener service, breaking an estimated 37.5 billion web links. Reason for the 12-hour restrictions unknown. | E20: https://netblocks.org/reports/bitly-link-shortener-blocked-in-egypt-018lRLBa
... A39: Russia | B39: Amnesty International Eurasian website | C39: 44632 | D39: The Eurasia website of rights organization Amnesty International, which hosts a petition to end Russia's aggression against Ukraine, has been restricted in Russia. The measure follows social media and news site restrictions. | E39: NetBlocks
A40: Pakistan | B40: Wikipedia | C40: 02-03-2023 - 02-06-2023 | D40: Wikipedia restricted on multiple internet providers from Friday, February 3rd 2023 to Monday, February 6th 2023. The incident had come days after authorities threatened to ban the popular resource over the presence of “sacrilegious” content. Access was restored after an intervention by the Prime Minister. | E40: NetBlocks
A41: Italy | B41: ChatGPT | C41: 4/1/2023 - ongoing | D41: ChatGPT banned in Italy over privacy concerns, making Italy the first Western country to block the advanced chatbot. | E41: BBC

Sheet 2024
A1: Summary of 2024. Below the summary, there is a list of all the 2024 cases
A2: ISO-2 | B2: Countries restricting the internet in 2024 | C2: Newly imposed restrictions in 2024 Internet disruptions | D2: Affected people (if there were fer restrictions imposed in a country, biggest population sample is used); Data from UN, World Population Prospects 2022 | E2: Related w/ protests | F2: Related w/ elections | G2: Related w/ political turmoil | H2: Related w/ country’s internet law | I2: Soc media | J2: Local internet | K2: Nationwide internet | L2: Registered cases since 2015 | M2: Currently blocking | N2: Region
A3: BF | B3: Burkina Faso | C3: 0 | D3: 22959516 | E3: 0 | F3: 0 | G3: 0 | H3: 0 | I3: 0 | J3: 0 | K3: 0 | L3: 4 | M3: 1 | N3: Africa
A4: TD | B4: Chad | C4: 1 | D4: 17997367 | E4: 0 | F4: 0 | G4: 1 | H4: 0 | I4: 0 | J4: 0 | K4: 1 | L4: 7 | M4: 0 | N4: Africa
A5: KM | B5: Comoros | C5: 1 | D5: 844302 | E5: 1 | F5: 0 | G5: 0 | H5: 0 | I5: 0 | J5: 0 | K5: 1 | L5: 1 | M5: 0 | N5: Africa
A6: ER | B6: Eritrea | C6: 0 | D6: 3715522 | E6: 0 | F6: 0 | G6: 0 | H6: 0 | I6: 0 | J6: 0 | K6: 0 | L6: 2 | M6: 1 | N6: Africa
A7: ET | B7: Ethiopia | C7: 0 | D7: 124937259 | E7: 0 | F7: 0 | G7: 0 | H7: 0 | I7: 0 | J7: 0 | K7: 0 | L7: 12 | M7: 2 | N7: Africa
A8: GN | B8: Guinea | C8: 0 | D8: 14023588 | E8: 0 | F8: 0 | G8: 0 | H8: 0 | I8: 0 | J8: 0 | K8: 0 | L8: 5 | M8: 1 | N8: Africa
A9: KE | B9: Kenya | C9: 2 | D9: 54555095 | E9: 1 | F9: 0 | G9: 1 | H9: 0 | I9: 1 | J9: 0 | K9: 1 | L9: 2 | M9: 1 | N9: Africa
A10: MU | B10: Mauritius | C10: 1 | D10: 1299804 | E10: 0 | F10: 1 | G10: 0 | H10: 0 | I10: 0 | J10: 0 | K10: 1 | L10: 1 | M10: 0 | N10: Africa
A11: MZ | B11: Mozambique | C11: 8 | D11: 33420619 | E11: 8 | F11: 0 | G11: 0 | H11: 0 | I11: 2 | J11: 0 | K11: 6 | L11: 8 | M11: 2 | N11: Africa
A12: NG | B12: Nigeria | C12: 1 | D12: 221153992 | E12: 1 | F12: 0 | G12: 0 | H12: 0 | I12: 0 | J12: 0 | K12: 1 | L12: 2 | M12: 0 | N12: Africa
A13: SN | B13: Senegal | C13: 2 | D13: 17536231 | E13: 1 | F13: 1 | G13: 0 | H13: 0 | I13: 0 | J13: 1 | K13: 1 | L13: 8 | M13: 1 | N13: Africa
A14: SO | B14: Somalia | C14: 0 | D14: 17865030 | E14: 0 | F14: 0 | G14: 0 | H14: 0 | I14: 0 | J14: 0 | K14: 0 | L14: 4 | M14: 1 | N14: Africa
... A40: VE | B40: Venezuela | C40: 0 | D40: 28555733 | E40: 0 | F40: 0 | G40: 0 | H40: 0 | I40: 0 | J40: 0 | K40: 0 | L40: 36 | M40: 0 | N40: South America
A43: List of all restrictions in 2024
A44: Iso-2 array | B44: Start date | C44: End date | D44: Duration (until the end of 2022), h | E44: Related w/ protests | F44: Related w/ elections | G44: Related w/ political turmoil | H44: Related w/ country’s internet law | I44: Scope/ population | J44: Region | K44: Population; Data from UN, World Population Prospects 2022 | L44: Facebook | M44: Twitter | N44: Youtube | O44: Instagram | P44: Telegram | Q44: Whatsapp | R44: Other soc. media | S44: Other VoIP apps | T44: Cases that started and ended in chosen period | U44: Cases that started in chosen period and are still ongoing | V44: Cases that started earlier but ended in chosen period | W44: Cases that started earlier and are still ongoing | X44: Cases that started in this period
A45: AZ | B45: 45188 | D45: 11232 | E45: FALSE | F45: FALSE | G45: TRUE | H45: FALSE | I45: Nagorno-Karabakh | J45: Asia | K45: 120000 | L45: FALSE | M45: FALSE | N45: FALSE | O45: FALSE | P45: FALSE | Q45: FALSE | R45: FALSE | S45: FALSE | W45: Y
A46: BD | B46: 45509 | C46: 45509 | D46: 4 | E46: TRUE | F46: FALSE | G46: FALSE | H46: FALSE | I46: Nationwide | J46: Asia | K46: 172075151 | L46: FALSE | M46: FALSE | N46: FALSE | O46: FALSE | P46: FALSE | Q46: FALSE | R46: FALSE | S46: FALSE | T46: Y | X46: Y
A47: BD | B47: 45506 | D47: 3600 | E47: TRUE | F47: FALSE | G47: FALSE | H47: FALSE | I47: Nationwide | J47: Asia | K47: 172075151 | L47: TRUE | M47: FALSE | N47: FALSE | O47: FALSE | P47: FALSE | Q47: TRUE | R47: FALSE | S47: FALSE | U47: Y | X47: Y
A48: BD | B48: 45491 | C48: 45501 | D48: 264 | E48: TRUE | F48: FALSE | G48: FALSE | H48: FALSE | I48: Nationwide | J48: Asia | K48: 172075151 | L48: FALSE | M48: FALSE | N48: FALSE | O48: FALSE | P48: FALSE | Q48: FALSE | R48: FALSE | S48: FALSE | T48: Y | X48: Y
A49: BD | B49: 45489 | C49: 45504 | D49: 360 | E49: TRUE | F49: FALSE | G49: FALSE | H49: FALSE | I49: Nationwide | J49: Asia | K49: 172075151 | L49: TRUE | M49: FALSE | N49: FALSE | O49: FALSE | P49: FALSE | Q49: FALSE | R49: FALSE | S49: FALSE | T49: Y | X49: Y
A50: BF | B50: 44572 | D50: 26016 | E50: FALSE | F50: FALSE | G50: TRUE | H50: FALSE | I50: Nationwide | J50: Africa | K50: 22959516 | L50: TRUE | M50: FALSE | N50: FALSE | O50: FALSE | P50: FALSE | Q50: FALSE | R50: FALSE | S50: FALSE | W50: Y
A51: BR | B51: 45535 | C51: 45573 | D51: 912 | E51: FALSE | F51: FALSE | G51: FALSE | H51: TRUE | I51: Nationwide | J51: South America | K51: 215802222 | L51: FALSE | M51: TRUE | N51: FALSE | O51: FALSE | P51: FALSE | Q51: FALSE | R51: FALSE | S51: FALSE | T51: Y | X51: Y
A52: ET | B52: 44967 | D52: 16536 | E52: TRUE | F52: FALSE | G52: FALSE | H52: FALSE | I52: Nationwide | J52: Africa | K52: 124937259 | L52: FALSE | M52: FALSE | N52: TRUE | O52: FALSE | P52: FALSE | Q52: FALSE | R52: FALSE | S52: FALSE | W52: Y
A53: ET | B53: 44966 | D53: 16560 | E53: TRUE | F53: FALSE | G53: FALSE | H53: FALSE | I53: Nationwide | J53: Africa | K53: 124937259 | L53: TRUE | M53: FALSE | N53: FALSE | O53: FALSE | P53: TRUE | Q53: FALSE | R53: TRUE | S53: FALSE | W53: Y
A54: GN | B54: 45254 | D54: 9648 | E54: FALSE | F54: FALSE | G54: TRUE | H54: FALSE | I54: Nationwide | J54: Africa | K54: 14023588 | L54: TRUE | M54: FALSE | N54: FALSE | O54: FALSE | P54: TRUE | Q54: TRUE | R54: FALSE | S54: FALSE | W54: Y
A55: IN | B55: 45640 | C55: 45641 | D55: 24 | E55: TRUE | F55: FALSE | G55: FALSE | H55: FALSE | I55: Haryana | J55: Asia | K55: 30870000 | L55: FALSE | M55: FALSE | N55: FALSE | O55: FALSE | P55: FALSE | Q55: FALSE | R55: FALSE | S55: FALSE | T55: Y | X55: Y
A56: IN | B56: 45632 | C56: 45633 | D56: 24 | E56: TRUE | F56: FALSE | G56: FALSE | H56: FALSE | I56: Haryana | J56: Asia | K56: 30870000 | L56: FALSE | M56: FALSE | N56: FALSE | O56: FALSE | P56: FALSE | Q56: FALSE | R56: FALSE | S56: FALSE | T56: Y | X56: Y
A57: IN | B57: 45620 | C57: 45621 | D57: 24 | E57: FALSE | F57: FALSE | G57: TRUE | H57: FALSE | I57: Sambhal | J57: Asia | K57: 312000 | L57: FALSE | M57: FALSE | N57: FALSE | O57: FALSE | P57: FALSE | Q57: FALSE | R57: FALSE | S57: FALSE | T57: Y | X57: Y
A58: IN | B58: 45612 | C58: 45612 | D58: 24 | E58: FALSE | F58: FALSE | G58: TRUE | H58: FALSE | I58: Murshidabad | J58: Asia | K58: 44019 | L58: FALSE | M58: FALSE | N58: FALSE | O58: FALSE | P58: FALSE | Q58: FALSE | R58: FALSE | S58: FALSE | T58: Y | X58: Y
A59: IN | B59: 45612 | C59: 45633 | D59: 504 | E59: FALSE | F59: FALSE | G59: TRUE | H59: FALSE | I59: Manipur | J59: Asia | K59: 3436948 | L59: FALSE | M59: FALSE | N59: FALSE | O59: FALSE | P59: FALSE | Q59: FALSE | R59: FALSE | S59: FALSE | T59: Y | X59: Y
A60: IN | B60: 45608 | C60: 45495 | D60: 24 | E60: FALSE | F60: FALSE | G60: TRUE | H60: FALSE | I60: Dudyala, Kodangal, and Bonraspet | J60: Asia | K60: 24010 | L60: FALSE | M60: FALSE | N60: FALSE | O60: FALSE | P60: FALSE | Q60: FALSE | R60: FALSE | S60: FALSE | T60: Y | X60: Y
A61: IN | B61: 45580 | C61: 45583 | D61: 72 | E61: TRUE | F61: FALSE | G61: FALSE | H61: FALSE | I61: North Tripura | J61: Asia | K61: 693947 | L61: FALSE | M61: FALSE | N61: FALSE | O61: FALSE | P61: FALSE | Q61: FALSE | R61: FALSE | S61: FALSE | T61: Y | X61: Y
A62: IN | B62: 45579 | C62: 45579 | D62: 24 | E62: TRUE | F62: FALSE | G62: FALSE | H62: FALSE | I62: Bahraich | J62: Asia | K62: 3487731 | L62: FALSE | M62: FALSE | N62: FALSE | O62: FALSE | P62: FALSE | Q62: FALSE | R62: FALSE | S62: FALSE | T62: Y | X62: Y
A63: IN | B63: 45563 | C63: 45565 | D63: 48 | E63: TRUE | F63: FALSE | G63: FALSE | H63: FALSE | I63: Bhadrak | J63: Asia | K63: 1506337 | L63: FALSE | M63: FALSE | N63: FALSE | O63: FALSE | P63: FALSE | Q63: FALSE | R63: FALSE | S63: FALSE | T63: Y | X63: Y
A64: IN | B64: 45556 | C64: 45557 | D64: 6 | E64: FALSE | F64: FALSE | G64: TRUE | H64: FALSE | I64: Jharkhand | J64: Asia | K64: 32988134 | L64: FALSE | M64: FALSE | N64: FALSE | O64: FALSE | P64: FALSE | Q64: FALSE | R64: FALSE | S64: FALSE | T64: Y | X64: Y
A65: IN | B65: 45540 | C65: 45541 | D65: 24 | E65: FALSE | F65: FALSE | G65: TRUE | H65: FALSE | I65: Jainoor, Asifabad | J65: Asia | K65: 29401 | L65: FALSE | M65: FALSE | N65: FALSE | O65: FALSE | P65: FALSE | Q65: FALSE | R65: FALSE | S65: FALSE | T65: Y | X65: Y
A66: IN | B66: 45545 | C66: 45550 | D66: 120 | E66: TRUE | F66: FALSE | G66: FALSE | H66: FALSE | I66: Manipur | J66: Asia | K66: 3436948 | L66: FALSE | M66: FALSE | N66: FALSE | O66: FALSE | P66: FALSE | Q66: FALSE | R66: FALSE | S66: FALSE | T66: Y | X66: Y
... A71: IN | B71: 45461 | C71: 45465 | D71: 96 | E71: FALSE | F71: FALSE | G71: TRUE | H71: FALSE | I71: Balasore | J71: Asia | K71: 2680000 | L71: FALSE | M71: FALSE | N71: FALSE | O71: FALSE | P71: FALSE | Q71: FALSE | R71: FALSE | S71: FALSE | T71: Y | X71: Y
A72: IN | B72: 45433 | C72: 45435 | D72: 48 | E72: TRUE | F72: FALSE | G72: FALSE | H72: FALSE | I72: Saran | J72: Asia | K72: 25, 72,980 | L72: FALSE | M72: FALSE | N72: FALSE | O72: FALSE | P72: FALSE | Q72: FALSE | R72: FALSE | S72: FALSE | T72: Y | X72: Y
A73: IN | B73: 45426 | C73: 45428 | D73: 48 | E73: TRUE | F73: FALSE | G73: FALSE | H73: FALSE | I73: Saran | J73: Asia | K73: 25, 72,980 | L73: FALSE | M73: FALSE | N73: FALSE | O73: FALSE | P73: FALSE | Q73: FALSE | R73: FALSE | S73: FALSE | T73: Y | X73: Y
A74: IN | B74: 45388 | C74: 45389 | D74: 24 | E74: TRUE | F74: FALSE | G74: FALSE | H74: FALSE | I74: Leh | J74: Asia | K74: 133487 | L74: FALSE | M74: FALSE | N74: FALSE | O74: FALSE | P74: FALSE | Q74: FALSE | R74: FALSE | S74: FALSE | T74: Y | X74: Y
A75: IN | B75: 45338 | C75: 45353 | D75: 384 | E75: TRUE | F75: FALSE | G75: FALSE | H75: FALSE | I75: Manipur | J75: Asia | K75: 3436948 | L75: FALSE | M75: FALSE | N75: FALSE | O75: FALSE | P75: FALSE | Q75: FALSE | R75: FALSE | S75: FALSE | T75: Y | X75: Y
A76: IN | B76: 45333 | C76: 45351 | D76: 456 | E76: TRUE | F76: FALSE | G76: FALSE | H76: FALSE | I76: Haryana | J76: Asia | K76: 30870000 | L76: FALSE | M76: FALSE | N76: FALSE | O76: FALSE | P76: FALSE | Q76: FALSE | R76: FALSE | S76: FALSE | T76: Y | X76: Y
A77: IN | B77: 45332 | C77: 45346 | D77: 360 | E77: TRUE | F77: FALSE | G77: FALSE | H77: FALSE | I77: Punjab | J77: Asia | K77: 27700000 | L77: FALSE | M77: FALSE | N77: FALSE | O77: FALSE | P77: FALSE | Q77: FALSE | R77: FALSE | S77: FALSE | T77: Y | X77: Y
A78: IN | B78: 45049 | D78: 14568 | E78: TRUE | F78: FALSE | G78: FALSE | H78: FALSE | I78: Manipur | J78: Asia | K78: 3436948 | L78: FALSE | M78: FALSE | N78: FALSE | O78: FALSE | P78: FALSE | Q78: FALSE | R78: FALSE | S78: FALSE | W78: Y
A79: IN | B79: 45047 | D79: 14616 | E79: FALSE | F79: FALSE | G79: TRUE | H79: FALSE | I79: Nationwide | J79: Asia | K79: 1422026528 | L79: FALSE | M79: FALSE | N79: FALSE | O79: FALSE | P79: FALSE | Q79: FALSE | R79: FALSE | S79: TRUE | W79: Y
A80: IQ | B80: 45144 | D80: 12288 | E80: FALSE | F80: FALSE | G80: FALSE | H80: TRUE | I80: Nationwide | J80: Asia | K80: 44996074 | L80: FALSE | M80: FALSE | N80: FALSE | O80: FALSE | P80: TRUE | Q80: FALSE | R80: FALSE | S80: FALSE | W80: Y
A81: IR | B81: 45483 | C81: 45240 | D81: 3 | E81: FALSE | F81: FALSE | G81: TRUE | H81: FALSE | I81: Nationwide | J81: Asia | K81: 88844498 | L81: FALSE | M81: FALSE | N81: FALSE | O81: FALSE | P81: FALSE | Q81: FALSE | R81: FALSE | S81: FALSE | T81: Y | X81: Y
A82: IR | B82: 44828 | D82: 19872 | E82: TRUE | F82: FALSE | G82: FALSE | H82: FALSE | I82: Nationwide | J82: Asia | K82: 88844498 | L82: FALSE | M82: FALSE | N82: FALSE | O82: FALSE | P82: FALSE | Q82: FALSE | R82: FALSE | S82: TRUE | W82: Y
A83: IR | B83: 44825 | C83: 45651 | D83: 19800 | E83: TRUE | F83: FALSE | G83: FALSE | H83: FALSE | I83: Nationwide | J83: Asia | K83: 88844498 | L83: FALSE | M83: FALSE | N83: FALSE | O83: TRUE | P83: FALSE | Q83: TRUE | R83: FALSE | S83: FALSE | V83: Y
A84: J&K | B84: 45424 | C84: 45338 | D84: 112 | E84: TRUE | F84: FALSE | G84: FALSE | H84: FALSE | I84: Jammu and Kashmir | J84: Asia | K84: 13606320 | L84: FALSE | M84: FALSE | N84: FALSE | O84: FALSE | P84: FALSE | Q84: FALSE | R84: FALSE | S84: FALSE | T84: Y | X84: Y
A85: J&K | B85: 45329 | C85: 45330 | D85: 24 | E85: FALSE | F85: FALSE | G85: TRUE | H85: FALSE | I85: Jammu and Kashmir | J85: Asia | K85: 13606320 | L85: FALSE | M85: FALSE | N85: FALSE | O85: FALSE | P85: FALSE | Q85: FALSE | R85: FALSE | S85: FALSE | T85: Y | X85: Y
A86: JO | B86: 44911 | D86: 17880 | E86: TRUE | F86: FALSE | G86: FALSE | H86: FALSE | I86: Nationwide | J86: Asia | K86: 11315547 | L86: FALSE | M86: FALSE | N86: FALSE | O86: FALSE | P86: FALSE | Q86: FALSE | R86: TRUE | S86: FALSE | W86: Y
A87: KE | B87: 45604 | D87: 1248 | E87: FALSE | F87: FALSE | G87: TRUE | H87: FALSE | I87: Nationwide | J87: Africa | K87: 54555095 | L87: FALSE | M87: FALSE | N87: FALSE | O87: FALSE | P87: TRUE | Q87: FALSE | R87: FALSE | S87: FALSE | U87: Y | X87: Y
A88: KE | B88: 45468 | C88: 45468 | D88: 7 | E88: TRUE | F88: FALSE | G88: FALSE | H88: FALSE | I88: Nationwide | J88: Africa | K88: 54555095 | L88: FALSE | M88: FALSE | N88: FALSE | O88: FALSE | P88: FALSE | Q88: FALSE | R88: FALSE | S88: FALSE | T88: Y | X88: Y
A89: KM | B89: 45308 | C89: 45309 | D89: 24 | E89: TRUE | F89: FALSE | G89: FALSE | H89: FALSE | I89: Nationwide | J89: Africa | K89: 844302 | L89: FALSE | M89: FALSE | N89: FALSE | O89: FALSE | P89: FALSE | Q89: FALSE | R89: FALSE | S89: FALSE | T89: Y | X89: Y
A90: MU | B90: 45600 | C90: 45601 | D90: 12 | E90: FALSE | F90: TRUE | G90: FALSE | H90: FALSE | I90: Nationwide | J90: Africa | K90: 1299804 | L90: TRUE | M90: TRUE | N90: TRUE | O90: FALSE | P90: FALSE | Q90: FALSE | R90: TRUE | S90: FALSE | T90: Y | X90: Y
A91: MZ | B91: 45603 | C91: 45604 | D91: 12 | E91: TRUE | F91: FALSE | G91: FALSE | H91: FALSE | I91: Nationwide | J91: Africa | K91: 33420619 | L91: FALSE | M91: FALSE | N91: FALSE | O91: FALSE | P91: FALSE | Q91: FALSE | R91: FALSE | S91: FALSE | T91: Y | X91: Y
A92: MZ | B92: 45602 | C92: 45603 | D92: 12 | E92: TRUE | F92: FALSE | G92: FALSE | H92: FALSE | I92: Nationwide | J92: Africa | K92: 33420619 | L92: FALSE | M92: FALSE | N92: FALSE | O92: FALSE | P92: FALSE | Q92: FALSE | R92: FALSE | S92: FALSE | T92: Y | X92: Y
A93: MZ | B93: 45601 | C93: 45602 | D93: 12 | E93: TRUE | F93: FALSE | G93: FALSE | H93: FALSE | I93: Nationwide | J93: Africa | K93: 33420619 | L93: FALSE | M93: FALSE | N93: FALSE | O93: FALSE | P93: FALSE | Q93: FALSE | R93: FALSE | S93: FALSE | T93: Y | X93: Y
A94: MZ | B94: 45600 | C94: 45601 | D94: 12 | E94: TRUE | F94: FALSE | G94: FALSE | H94: FALSE | I94: Nationwide | J94: Africa | K94: 33420619 | L94: FALSE | M94: FALSE | N94: FALSE | O94: FALSE | P94: FALSE | Q94: FALSE | R94: FALSE | S94: FALSE | T94: Y | X94: Y
A95: MZ | B95: 45599 | C95: 45600 | D95: 12 | E95: TRUE | F95: FALSE | G95: FALSE | H95: FALSE | I95: Nationwide | J95: Africa | K95: 33420619 | L95: FALSE | M95: FALSE | N95: FALSE | O95: FALSE | P95: FALSE | Q95: FALSE | R95: FALSE | S95: FALSE | T95: Y | X95: Y
A96: MZ | B96: 45599 | D96: 1368 | E96: TRUE | F96: FALSE | G96: FALSE | H96: FALSE | I96: Nationwide | J96: Africa | K96: 33420619 | L96: FALSE | M96: FALSE | N96: TRUE | O96: FALSE | P96: TRUE | Q96: FALSE | R96: TRUE | S96: FALSE | U96: Y | X96: Y
A97: MZ | B97: 45596 | D97: 1440 | E97: TRUE | F97: FALSE | G97: FALSE | H97: FALSE | I97: Nationwide | J97: Africa | K97: 33420619 | L97: TRUE | M97: FALSE | N97: FALSE | O97: TRUE | P97: FALSE | Q97: TRUE | R97: FALSE | S97: FALSE | U97: Y | X97: Y
A98: MZ | B98: 45590 | C98: 45591 | D98: 24 | E98: TRUE | F98: FALSE | G98: FALSE | H98: FALSE | I98: Nationwide | J98: Africa | K98: 33420619 | L98: FALSE | M98: FALSE | N98: FALSE | O98: FALSE | P98: FALSE | Q98: FALSE | R98: FALSE | S98: FALSE | T98: Y | X98: Y
A99: NG | B99: 45505 | C99: 45506 | D99: 24 | E99: TRUE | F99: FALSE | G99: FALSE | H99: FALSE | I99: Nationwide | J99: Africa | K99: 221153992 | L99: FALSE | M99: FALSE | N99: FALSE | O99: FALSE | P99: FALSE | Q99: FALSE | R99: FALSE | S99: FALSE | T99: Y | X99: Y
A100: PK | B100: 45616 | D100: 960 | E100: FALSE | F100: FALSE | G100: FALSE | H100: TRUE | I100: Nationwide | J100: Asia | K100: 238126113 | L100: FALSE | M100: FALSE | N100: FALSE | O100: FALSE | P100: FALSE | Q100: FALSE | R100: TRUE | S100: FALSE | U100: Y | X100: Y
A101: PK | B101: 45571 | C101: 45571 | D101: 24 | E101: TRUE | F101: FALSE | G101: FALSE | H101: FALSE | I101: Khyber Pakhtunkhwa, Raw­al­pindi and Islamabad | J101: Asia | K101: 45354364 | L101: FALSE | M101: FALSE | N101: FALSE | O101: FALSE | P101: FALSE | Q101: FALSE | R101: FALSE | S101: FALSE | T101: Y | X101: Y
A102: PK | B102: 45490 | D102: 3984 | E102: FALSE | F102: FALSE | G102: TRUE | H102: FALSE | I102: Nationwide | J102: Asia | K102: 238126113 | L102: TRUE | M102: FALSE | N102: FALSE | O102: FALSE | P102: FALSE | Q102: FALSE | R102: FALSE | S102: FALSE | U102: Y | X102: Y
A103: PK | B103: 45339 | D103: 7608 | E103: FALSE | F103: TRUE | G103: FALSE | H103: FALSE | I103: Nationwide | J103: Asia | K103: 238126113 | L103: FALSE | M103: TRUE | N103: FALSE | O103: FALSE | P103: FALSE | Q103: FALSE | R103: FALSE | S103: FALSE | U103: Y | X103: Y
A104: PK | B104: 45332 | C104: 45333 | D104: 24 | E104: FALSE | F104: TRUE | G104: FALSE | H104: FALSE | I104: Nationwide | J104: Asia | K104: 238126113 | L104: FALSE | M104: TRUE | N104: FALSE | O104: FALSE | P104: FALSE | Q104: FALSE | R104: FALSE | S104: FALSE | T104: Y | X104: Y
A105: PK | B105: 45330 | C105: 45331 | D105: 36 | E105: FALSE | F105: TRUE | G105: FALSE | H105: FALSE | I105: Nationwide | J105: Asia | K105: 238126113 | L105: FALSE | M105: FALSE | N105: FALSE | O105: FALSE | P105: FALSE | Q105: FALSE | R105: FALSE | S105: FALSE | T105: Y | X105: Y
A106: PK | B106: 45311 | C106: 45312 | D106: 48 | E106: FALSE | F106: FALSE | G106: TRUE | H106: FALSE | I106: Nationwide | J106: Asia | K106: 238126113 | L106: TRUE | M106: TRUE | N106: TRUE | O106: TRUE | P106: FALSE | Q106: FALSE | R106: FALSE | S106: FALSE | T106: Y | X106: Y
A107: PK | B107: 45298 | C107: 45299 | D107: 12 | E107: FALSE | F107: FALSE | G107: TRUE | H107: FALSE | I107: Nationwide | J107: Asia | K107: 238126113 | L107: TRUE | M107: TRUE | N107: TRUE | O107: TRUE | P107: FALSE | Q107: FALSE | R107: FALSE | S107: FALSE | T107: Y | X107: Y
A108: PK | B108: 45056 | D108: 14400 | E108: FALSE | F108: FALSE | G108: TRUE | H108: FALSE | I108: Nationwide | J108: Asia | K108: 238126113 | L108: FALSE | M108: FALSE | N108: FALSE | O108: TRUE | P108: FALSE | Q108: FALSE | R108: FALSE | S108: FALSE | W108: Y
A109: RU | B109: 45573 | D109: 1992 | E109: FALSE | F109: FALSE | G109: FALSE | H109: TRUE | I109: Nationwide | J109: Europe | K109: 144694112 | L109: FALSE | M109: FALSE | N109: FALSE | O109: FALSE | P109: FALSE | Q109: FALSE | R109: FALSE | S109: TRUE | U109: Y | X109: Y
A110: RU | B110: 45513 | D110: 3432 | E110: FALSE | F110: FALSE | G110: TRUE | H110: FALSE | I110: Nationwide | J110: Europe | K110: 144694112 | L110: FALSE | M110: FALSE | N110: FALSE | O110: FALSE | P110: FALSE | Q110: FALSE | R110: FALSE | S110: TRUE | U110: Y | X110: Y
A111: RU | B111: 44633 | D111: 24552 | E111: FALSE | F111: FALSE | G111: TRUE | H111: FALSE | I111: Nationwide | J111: Europe | K111: 144694112 | L111: FALSE | M111: FALSE | N111: FALSE | O111: TRUE | P111: FALSE | Q111: FALSE | R111: FALSE | S111: FALSE | W111: Y
A112: RU | B112: 44619 | D112: 24888 | E112: FALSE | F112: FALSE | G112: TRUE | H112: FALSE | I112: Nationwide | J112: Europe | K112: 144694112 | L112: TRUE | M112: FALSE | N112: FALSE | O112: FALSE | P112: FALSE | Q112: FALSE | R112: FALSE | S112: FALSE | W112: Y
A113: RU | B113: 44618 | D113: 24912 | E113: FALSE | F113: FALSE | G113: TRUE | H113: FALSE | I113: Nationwide | J113: Europe | K113: 144694112 | L113: FALSE | M113: TRUE | N113: FALSE | O113: FALSE | P113: FALSE | Q113: FALSE | R113: FALSE | S113: FALSE | W113: Y
A114: SD | B114: 45329 | D114: 7848 | E114: FALSE | F114: FALSE | G114: TRUE | H114: FALSE | I114: Nationwide | J114: Africa | K114: 47486909 | L114: FALSE | M114: FALSE | N114: FALSE | O114: FALSE | P114: FALSE | Q114: FALSE | R114: FALSE | S114: FALSE | U114: Y | X114: Y
A115: SD | B115: 45031 | D115: 15000 | E115: FALSE | F115: FALSE | G115: TRUE | H115: FALSE | I115: Nationwide | J115: Africa | K115: 47486909 | L115: FALSE | M115: FALSE | N115: FALSE | O115: FALSE | P115: FALSE | Q115: FALSE | R115: FALSE | S115: FALSE | W115: Y
A116: SN | B116: 45332 | C116: 45335 | D116: 72 | E116: FALSE | F116: TRUE | G116: FALSE | H116: FALSE | I116: Nationwide | J116: Africa | K116: 17536231 | L116: FALSE | M116: FALSE | N116: FALSE | O116: FALSE | P116: FALSE | Q116: FALSE | R116: FALSE | S116: FALSE | T116: Y | X116: Y
A117: SN | B117: 45327 | C117: 45328 | D117: 48 | E117: TRUE | F117: FALSE | G117: FALSE | H117: FALSE | I117: Dakar | J117: Africa | K117: 3540462 | L117: FALSE | M117: FALSE | N117: FALSE | O117: FALSE | P117: FALSE | Q117: FALSE | R117: FALSE | S117: FALSE | T117: Y | X117: Y
A118: SN | B118: 45140 | D118: 12384 | E118: FALSE | F118: FALSE | G118: TRUE | H118: FALSE | I118: Nationwide | J118: Africa | K118: 17536231 | L118: FALSE | M118: FALSE | N118: FALSE | O118: FALSE | P118: FALSE | Q118: FALSE | R118: TRUE | S118: FALSE | W118: Y
A119: SO | B119: 45159 | D119: 11928 | E119: FALSE | F119: FALSE | G119: TRUE | H119: FALSE | I119: Nationwide | J119: Africa | K119: 17865030 | L119: FALSE | M119: FALSE | N119: FALSE | O119: FALSE | P119: TRUE | Q119: FALSE | R119: TRUE | S119: FALSE | W119: Y
A120: SV | B120: 45550 | C120: 45551 | D120: 24 | E120: FALSE | F120: FALSE | G120: TRUE | H120: FALSE | I120: Nationwide | J120: North America | K120: 6348989 | L120: FALSE | M120: FALSE | N120: FALSE | O120: FALSE | P120: TRUE | Q120: FALSE | R120: FALSE | S120: FALSE | T120: Y | X120: Y
A121: SV | B121: 45444 | C121: 45445 | D121: 24 | E121: FALSE | F121: FALSE | G121: TRUE | H121: FALSE | I121: Nationwide | J121: North America | K121: 6348989 | L121: FALSE | M121: FALSE | N121: FALSE | O121: FALSE | P121: TRUE | Q121: FALSE | R121: FALSE | S121: FALSE | T121: Y | X121: Y
A122: SY | B122: 45498 | C122: 45498 | D122: 4 | E122: FALSE | F122: FALSE | G122: TRUE | H122: FALSE | I122: Nationwide | J122: Asia | K122: 22660911 | L122: FALSE | M122: FALSE | N122: FALSE | O122: FALSE | P122: FALSE | Q122: FALSE | R122: FALSE | S122: FALSE | T122: Y | X122: Y
A123: TD | B123: 45350 | C123: 45358 | D123: 38 | E123: FALSE | F123: FALSE | G123: TRUE | H123: FALSE | I123: Nationwide | J123: Africa | K123: 17997367 | L123: FALSE | M123: FALSE | N123: FALSE | O123: FALSE | P123: FALSE | Q123: FALSE | R123: FALSE | S123: FALSE | T123: Y | X123: Y
A124: TR | B124: 45588 | C124: 45589 | D124: 24 | E124: FALSE | F124: FALSE | G124: TRUE | H124: FALSE | I124: Nationwide | J124: Asia | K124: 85590849 | L124: TRUE | M124: FALSE | N124: TRUE | O124: TRUE | P124: FALSE | Q124: FALSE | R124: TRUE | S124: FALSE | T124: Y | X124: Y
A125: TR | B125: 45574 | D125: 1968 | E125: FALSE | F125: FALSE | G125: TRUE | H125: FALSE | I125: Nationwide | J125: Asia | K125: 85590849 | L125: FALSE | M125: FALSE | N125: FALSE | O125: FALSE | P125: FALSE | Q125: FALSE | R125: FALSE | S125: TRUE | U125: Y | X125: Y
A126: TR | B126: 45506 | C126: 45514 | D126: 192 | E126: FALSE | F126: FALSE | G126: FALSE | H126: TRUE | I126: Nationwide | J126: Asia | K126: 85590849 | L126: FALSE | M126: FALSE | N126: FALSE | O126: TRUE | P126: FALSE | Q126: FALSE | R126: FALSE | S126: FALSE | T126: Y | X126: Y
A127: TR | B127: 45474 | C127: 45477 | D127: 72 | E127: TRUE | F127: FALSE | G127: FALSE | H127: FALSE | I127: Kayseri | J127: Asia | K127: 1025507 | L127: TRUE | M127: TRUE | N127: TRUE | O127: TRUE | P127: FALSE | Q127: FALSE | R127: FALSE | S127: FALSE | T127: Y | X127: Y
A128: TR | B128: 44978 | C128: 45313 | D128: 8050 | E128: FALSE | F128: TRUE | G128: FALSE | H128: FALSE | I128: Nationwide | J128: Asia | K128: 85590849 | L128: FALSE | M128: FALSE | N128: FALSE | O128: FALSE | P128: FALSE | Q128: FALSE | R128: TRUE | S128: FALSE | V128: Y
A129: VE | B129: 45513 | C129: 45523 | D129: 240 | E129: FALSE | F129: FALSE | G129: TRUE | H129: FALSE | I129: Nationwide | J129: South America | K129: 28555733 | L129: FALSE | M129: TRUE | N129: FALSE | O129: FALSE | P129: FALSE | Q129: FALSE | R129: FALSE | S129: FALSE | T129: Y | X129: Y
A130: YE | B130: 45195 | D130: 11064 | E130: FALSE | F130: FALSE | G130: TRUE | H130: FALSE | I130: Nationwide | J130: Asia | K130: 34070907 | L130: FALSE | M130: FALSE | N130: FALSE | O130: FALSE | P130: FALSE | Q130: FALSE | R130: FALSE | S130: TRUE | W130: Y
A131: YE | B131: 45229 | D131: 10248 | E131: FALSE | F131: FALSE | G131: TRUE | H131: FALSE | I131: Nationwide | J131: Asia | K131: 34070907 | L131: FALSE | M131: FALSE | N131: TRUE | O131: FALSE | P131: FALSE | Q131: FALSE | R131: TRUE | S131: FALSE | W131: Y

Sheet 2024 vs. 2023
A1: Summary of 2024 and 2023
A2: ISO-2 | B2: Countries restricting the internet in 2024 | C2: Newly imposed restrictions in 2024 Internet disruptions | D2: Affected people (if there were fer restrictions imposed in a country, biggest population sample is used); Data from UN, World Population Prospects 2022 | E2: Related w/ protests | F2: Related w/ elections | G2: Related w/ political turmoil | H2: Related w/ country’s internet law | I2: Soc media | J2: Local internet | K2: Nationwide internet | L2: Registered cases since 2015 | M2: Currently blocking | N2: Region
A3: BF | B3: Burkina Faso | C3: 0 | D3: 22959516 | E3: 0 | F3: 0 | G3: 0 | H3: 0 | I3: 0 | J3: 0 | K3: 0 | L3: 4 | M3: 1 | N3: Africa
A4: TD | B4: Chad | C4: 1 | D4: 17997367 | E4: 0 | F4: 0 | G4: 1 | H4: 0 | I4: 0 | J4: 0 | K4: 1 | L4: 7 | M4: 0 | N4: Africa
A5: KM | B5: Comoros | C5: 1 | D5: 844302 | E5: 1 | F5: 0 | G5: 0 | H5: 0 | I5: 0 | J5: 0 | K5: 1 | L5: 1 | M5: 0 | N5: Africa
A6: ER | B6: Eritrea | C6: 0 | D6: 3715522 | E6: 0 | F6: 0 | G6: 0 | H6: 0 | I6: 0 | J6: 0 | K6: 0 | L6: 2 | M6: 1 | N6: Africa
A7: ET | B7: Ethiopia | C7: 0 | D7: 124937259 | E7: 0 | F7: 0 | G7: 0 | H7: 0 | I7: 0 | J7: 0 | K7: 0 | L7: 12 | M7: 2 | N7: Africa
A8: GN | B8: Guinea | C8: 0 | D8: 14023588 | E8: 0 | F8: 0 | G8: 0 | H8: 0 | I8: 0 | J8: 0 | K8: 0 | L8: 5 | M8: 1 | N8: Africa
A9: KE | B9: Kenya | C9: 2 | D9: 54555095 | E9: 1 | F9: 0 | G9: 1 | H9: 0 | I9: 1 | J9: 0 | K9: 1 | L9: 2 | M9: 1 | N9: Africa
A10: MU | B10: Mauritius | C10: 1 | D10: 1299804 | E10: 0 | F10: 1 | G10: 0 | H10: 0 | I10: 0 | J10: 0 | K10: 1 | L10: 1 | M10: 0 | N10: Africa
A11: MZ | B11: Mozambique | C11: 8 | D11: 33420619 | E11: 8 | F11: 0 | G11: 0 | H11: 0 | I11: 2 | J11: 0 | K11: 6 | L11: 8 | M11: 2 | N11: Africa
A12: NG | B12: Nigeria | C12: 1 | D12: 221153992 | E12: 1 | F12: 0 | G12: 0 | H12: 0 | I12: 0 | J12: 0 | K12: 1 | L12: 2 | M12: 0 | N12: Africa
A13: SN | B13: Senegal | C13: 2 | D13: 17536231 | E13: 1 | F13: 1 | G13: 0 | H13: 0 | I13: 0 | J13: 1 | K13: 1 | L13: 8 | M13: 1 | N13: Africa
A14: SO | B14: Somalia | C14: 0 | D14: 17865030 | E14: 0 | F14: 0 | G14: 0 | H14: 0 | I14: 0 | J14: 0 | K14: 0 | L14: 4 | M14: 1 | N14: Africa
... A40: VE | B40: Venezuela | C40: 0 | D40: 28555733 | E40: 0 | F40: 0 | G40: 0 | H40: 0 | I40: 0 | J40: 0 | K40: 0 | L40: 36 | M40: 0 | N40: South America
A45: 2023
B46: Countries restricting the internet in 2023'H1 | C46: Newly imposed restrictions in 2023'H1 Internet disruptions | D46: Affected people (if there were fer restrictions imposed in a country, biggest population sample is used); Data from UN, World Population Prospects 2022 | E46: Related w/ protests | F46: Related w/ elections | G46: Related w/ political turmoil | H46: Related w/ country’s internet law | I46: Soc media | J46: Local internet | K46: Nationwide internet | L46: Registered cases since 2015 | M46: Currently blocking | N46: Region
A47: BF | B47: Burkina Faso | C47: 0 | D47: 22959516 | E47: 0 | F47: 0 | G47: 0 | H47: 0 | I47: 0 | J47: 0 | K47: 0 | L47: 4 | M47: 1 | N47: Africa
A48: ER | B48: Eritrea | C48: 0 | D48: 3715522 | E48: 0 | F48: 0 | G48: 0 | H48: 0 | I48: 0 | J48: 0 | K48: 0 | L48: 2 | M48: 1 | N48: Africa
A49: ET | B49: Ethiopia | C49: 2 | D49: 124937259 | E49: 2 | F49: 0 | G49: 0 | H49: 0 | I49: 2 | J49: 0 | K49: 0 | L49: 12 | M49: 3 | N49: Africa
A50: GN | B50: Guinea | C50: 1 | D50: 14023588 | E50: 1 | F50: 0 | G50: 0 | H50: 0 | I50: 1 | J50: 0 | K50: 0 | L50: 4 | M50: 1 | N50: Africa
A51: MR | B51: Mauritania | C51: 2 | D51: 4798604 | E51: 2 | F51: 0 | G51: 0 | H51: 0 | I51: 0 | J51: 0 | K51: 2 | L51: 3 | M51: 0 | N51: Africa
A52: SN | B52: Senegal | C52: 2 | D52: 17536231 | E52: 0 | F52: 0 | G52: 2 | H52: 0 | I52: 1 | J52: 0 | K52: 1 | L52: 3 | M52: 0 | N52: Africa
A53: SD | B53: Sudan | C53: 1 | D53: 47486909 | E53: 0 | F53: 0 | G53: 1 | H53: 0 | I53: 0 | J53: 0 | K53: 1 | L53: 12 | M53: 1 | N53: Africa
A54: TZ | B54: Tanzania | C54: 1 | D54: 66455898 | E54: 0 | F54: 0 | G54: 1 | H54: 0 | I54: 1 | J54: 0 | K54: 0 | L54: 2 | M54: 0 | N54: Africa
A55: CN | B55: China | C55: 0 | D55: 1425849288 | E55: 0 | F55: 0 | G55: 0 | H55: 0 | I55: 0 | J55: 0 | K55: 0 | L55: 4 | M55: 4 | N55: Asia
A56: KP | B56: North Korea | C56: 0 | D56: 26116716 | E56: 0 | F56: 0 | G56: 0 | H56: 0 | I56: 0 | J56: 0 | K56: 0 | L56: 3 | M56: 3 | N56: Asia
A57: IN | B57: India | C57: 9 | D57: 1422026528 | E57: 7 | F57: 0 | G57: 2 | H57: 0 | I57: 1 | J57: 8 | K57: 0 | L57: 111 | M57: 3 | N57: Asia
A58: IR | B58: Iran | C58: 14 | D58: 88844498 | E58: 14 | F58: 0 | G58: 0 | H58: 0 | I58: 0 | J58: 14 | K58: 0 | L58: 41 | M58: 5 | N58: Asia
... A75: J&K | B75: Jammu and Kashmir | C75: 2 | D75: 13606320 | E75: 0 | F75: 0 | G75: 2 | H75: 0 | I75: 0 | J75: 2 | K75: 0 | L75: 326 | M75: 0 | N75: Asia

Sheet 2023
A1: Summary of 2023. Below the summary, there is a list of all the 2023 cases
A2: ISO-2 | B2: Countries restricting the internet in 2023 | C2: Newly imposed restrictions in 2023 Internet disruptions | D2: Affected people (if there were fer restrictions imposed in a country, biggest population sample is used); Data from UN, World Population Prospects 2022 | E2: Related w/ protests | F2: Related w/ elections | G2: Related w/ political turmoil | H2: Related w/ country’s internet law | I2: Soc media | J2: Local internet | K2: Nationwide internet | L2: Registered cases since 2015 | M2: Currently blocking | N2: Region
A3: BF | B3: Burkina Faso | C3: 0 | D3: 22959516 | E3: 0 | F3: 0 | G3: 0 | H3: 0 | I3: 0 | J3: 0 | K3: 0 | L3: 4 | M3: 1 | N3: Africa
A4: TD | B4: Chad | C4: 1 | D4: 17997367 | E4: 0 | F4: 1 | G4: 0 | H4: 0 | I4: 0 | J4: 0 | K4: 1 | L4: 6 | M4: 0 | N4: Africa
A5: ER | B5: Eritrea | C5: 0 | D5: 3715522 | E5: 0 | F5: 0 | G5: 0 | H5: 0 | I5: 0 | J5: 0 | K5: 0 | L5: 2 | M5: 1 | N5: Africa
A6: ET | B6: Ethiopia | C6: 2 | D6: 124937259 | E6: 2 | F6: 0 | G6: 0 | H6: 0 | I6: 2 | J6: 0 | K6: 0 | L6: 12 | M6: 2 | N6: Africa
A7: GA | B7: Gabon | C7: 1 | D7: 2412778 | E7: 0 | F7: 1 | G7: 0 | H7: 0 | I7: 0 | J7: 0 | K7: 1 | L7: 3 | M7: 0 | N7: Africa
A8: GN | B8: Guinea | C8: 2 | D8: 14023588 | E8: 1 | F8: 0 | G8: 1 | H8: 0 | I8: 2 | J8: 0 | K8: 0 | L8: 5 | M8: 2 | N8: Africa
A9: MR | B9: Mauritania | C9: 2 | D9: 4798604 | E9: 2 | F9: 0 | G9: 0 | H9: 0 | I9: 0 | J9: 0 | K9: 2 | L9: 3 | M9: 0 | N9: Africa
A10: SN | B10: Senegal | C10: 5 | D10: 17536231 | E10: 3 | F10: 0 | G10: 2 | H10: 0 | I10: 3 | J10: 0 | K10: 2 | L10: 6 | M10: 1 | N10: Africa
A11: SO | B11: Somalia | C11: 1 | D11: 17865030 | E11: 0 | F11: 0 | G11: 1 | H11: 0 | I11: 1 | J11: 0 | K11: 0 | L11: 4 | M11: 1 | N11: Africa
A12: SD | B12: Sudan | C12: 1 | D12: 47486909 | E12: 0 | F12: 0 | G12: 1 | H12: 0 | I12: 0 | J12: 0 | K12: 1 | L12: 12 | M12: 0 | N12: Africa
A13: TZ | B13: Tanzania | C13: 1 | D13: 66455898 | E13: 0 | F13: 0 | G13: 1 | H13: 0 | I13: 1 | J13: 0 | K13: 0 | L13: 2 | M13: 0 | N13: Africa
A14: ZW | B14: Zimbabwe | C14: 1 | D14: 16488132 | E14: 0 | F14: 1 | G14: 0 | H14: 0 | I14: 1 | J14: 0 | K14: 0 | L14: 7 | M14: 0 | N14: Africa
... A38: VE | B38: Venezuela | C38: 1 | D38: 28555733 | E38: 0 | F38: 1 | G38: 0 | H38: 0 | I38: 0 | J38: 0 | K38: 1 | L38: 35 | M38: 0 | N38: South America
A43: List of all restrictions in 2023
A44: Iso-2 array | B44: Start date | C44: End date | D44: Duration (until the end of 2022), h | E44: Related w/ protests | F44: Related w/ elections | G44: Related w/ political turmoil | H44: Related w/ country’s internet law | I44: Scope/ population | J44: Region | K44: Population; Data from UN, World Population Prospects 2022 | L44: Facebook | M44: Twitter | N44: Youtube | O44: Instagram | P44: Telegram | Q44: Whatsapp | R44: Other soc. media | S44: Other VoIP apps | T44: Service based restriction | U44: Cases that started and ended in chosen period | V44: Cases that started in chosen period and are still ongoing | W44: Cases that started earlier but ended in chosen period | X44: Cases that started earlier and are still ongoing | Y44: Cases that started in this period
A45: BF | B45: 44572 | D45: 17256 | E45: FALSE | F45: FALSE | G45: TRUE | H45: FALSE | I45: Nationwide | J45: Africa | K45: 22959516 | L45: TRUE | M45: FALSE | N45: FALSE | O45: FALSE | P45: FALSE | Q45: FALSE | R45: FALSE | S45: FALSE | T45: TRUE | X45: Y
A46: TD | B46: 45267 | C46: 45268 | D46: 14 | E46: FALSE | F46: TRUE | G46: FALSE | H46: FALSE | I46: Nationwide | J46: Africa | K46: 17997367 | L46: FALSE | M46: FALSE | N46: FALSE | O46: FALSE | P46: FALSE | Q46: FALSE | R46: FALSE | S46: FALSE | T46: FALSE | U46: Y | Y46: Y
A47: ER | B47: 40544 | D47: 113928 | E47: FALSE | F47: FALSE | G47: TRUE | H47: FALSE | I47: Nationwide | J47: Africa | K47: 3715522 | L47: FALSE | M47: FALSE | N47: TRUE | O47: FALSE | P47: FALSE | Q47: FALSE | R47: FALSE | S47: FALSE | T47: TRUE | X47: Y
A48: ET | B48: 44967 | D48: 7776 | E48: TRUE | F48: FALSE | G48: FALSE | H48: FALSE | I48: Nationwide | J48: Africa | K48: 124937259 | L48: FALSE | M48: FALSE | N48: TRUE | O48: FALSE | P48: FALSE | Q48: FALSE | R48: FALSE | S48: FALSE | T48: TRUE | V48: Y | Y48: Y
A49: ET | B49: 44966 | D49: 7800 | E49: TRUE | F49: FALSE | G49: FALSE | H49: FALSE | I49: Nationwide | J49: Africa | K49: 124937259 | L49: TRUE | M49: FALSE | N49: FALSE | O49: FALSE | P49: TRUE | Q49: FALSE | R49: TRUE | S49: FALSE | T49: TRUE | V49: Y | Y49: Y
A50: ET | B50: 44139 | D50: 27648 | E50: FALSE | F50: FALSE | G50: TRUE | H50: FALSE | I50: Tigray region | J50: Africa | K50: 5443000 | L50: FALSE | M50: FALSE | N50: FALSE | O50: FALSE | P50: FALSE | Q50: FALSE | R50: FALSE | S50: FALSE | T50: FALSE | X50: Y
A51: GA | B51: 45164 | C51: 45168 | D51: 96 | E51: FALSE | F51: TRUE | G51: FALSE | H51: FALSE | I51: Nationwide | J51: Africa | K51: 2412778 | L51: FALSE | M51: FALSE | N51: FALSE | O51: FALSE | P51: FALSE | Q51: FALSE | R51: FALSE | S51: FALSE | T51: FALSE | U51: Y | Y51: Y
A52: GN | B52: 45254 | D52: 888 | E52: FALSE | F52: FALSE | G52: TRUE | H52: FALSE | I52: Nationwide | J52: Africa | K52: 14023588 | L52: TRUE | M52: FALSE | N52: FALSE | O52: FALSE | P52: TRUE | Q52: TRUE | R52: FALSE | S52: FALSE | T52: TRUE | V52: Y | Y52: Y
A53: GN | B53: 45063 | D53: 5472 | E53: TRUE | F53: FALSE | G53: FALSE | H53: FALSE | I53: Nationwide | J53: Africa | K53: 14023588 | L53: TRUE | M53: FALSE | N53: TRUE | O53: TRUE | P53: TRUE | Q53: TRUE | R53: TRUE | S53: TRUE | T53: TRUE | V53: Y | Y53: Y
A54: MR | B54: 45077 | C54: 45084 | D54: 168 | E54: TRUE | F54: FALSE | G54: FALSE | H54: FALSE | I54: Nationwide | J54: Africa | K54: 4798604 | L54: FALSE | M54: FALSE | N54: FALSE | O54: FALSE | P54: FALSE | Q54: FALSE | R54: FALSE | S54: FALSE | T54: FALSE | U54: Y | Y54: Y
A55: MR | B55: 44991 | C55: 44997 | D55: 144 | E55: TRUE | F55: FALSE | G55: FALSE | H55: FALSE | I55: Nationwide | J55: Africa | K55: 4798604 | L55: FALSE | M55: FALSE | N55: FALSE | O55: FALSE | P55: FALSE | Q55: FALSE | R55: FALSE | S55: FALSE | T55: FALSE | U55: Y | Y55: Y
A56: SN | B56: 45140 | D56: 3624 | E56: FALSE | F56: FALSE | G56: TRUE | H56: FALSE | I56: Nationwide | J56: Africa | K56: 17536231 | L56: FALSE | M56: FALSE | N56: FALSE | O56: FALSE | P56: FALSE | Q56: FALSE | R56: TRUE | S56: FALSE | T56: TRUE | V56: Y | Y56: Y
A57: SN | B57: 45138 | C57: 45145 | D57: 144 | E57: FALSE | F57: FALSE | G57: TRUE | H57: FALSE | I57: Nationwide | J57: Africa | K57: 17536231 | L57: FALSE | M57: FALSE | N57: FALSE | O57: FALSE | P57: FALSE | Q57: FALSE | R57: FALSE | S57: FALSE | T57: FALSE | U57: Y | Y57: Y
A58: SN | B58: 45081 | C58: 45084 | D58: 84 | E58: TRUE | F58: FALSE | G58: FALSE | H58: FALSE | I58: Nationwide | J58: Africa | K58: 17536231 | L58: FALSE | M58: FALSE | N58: FALSE | O58: FALSE | P58: FALSE | Q58: FALSE | R58: FALSE | S58: FALSE | T58: FALSE | U58: Y | Y58: Y
A59: SN | B59: 45078 | C59: 45144 | D59: 1584 | E59: TRUE | F59: FALSE | G59: FALSE | H59: FALSE | I59: Nationwide | J59: Africa | K59: 17536231 | L59: FALSE | M59: FALSE | N59: FALSE | O59: FALSE | P59: TRUE | Q59: FALSE | R59: FALSE | S59: FALSE | T59: TRUE | U59: Y | Y59: Y
A60: SN | B60: 45078 | C60: 45084 | D60: 180 | E60: TRUE | F60: FALSE | G60: FALSE | H60: FALSE | I60: Nationwide | J60: Africa | K60: 17536231 | L60: TRUE | M60: TRUE | N60: TRUE | O60: TRUE | P60: FALSE | Q60: TRUE | R60: FALSE | S60: FALSE | T60: TRUE | U60: Y | Y60: Y
A61: SO | B61: 45159 | D61: 3168 | E61: FALSE | F61: FALSE | G61: TRUE | H61: FALSE | I61: Nationwide | J61: Africa | K61: 17865030 | L61: FALSE | M61: FALSE | N61: FALSE | O61: FALSE | P61: TRUE | Q61: FALSE | R61: TRUE | S61: FALSE | T61: TRUE | V61: Y | Y61: Y
A62: SD | B62: 45031 | D62: 6240 | E62: FALSE | F62: FALSE | G62: TRUE | H62: FALSE | I62: Nationwide | J62: Africa | K62: 47486909 | L62: FALSE | M62: FALSE | N62: FALSE | O62: FALSE | P62: FALSE | Q62: FALSE | R62: FALSE | S62: FALSE | T62: FALSE | V62: Y | Y62: Y
A63: TZ | B63: 44972 | C63: 44973 | D63: 24 | E63: FALSE | F63: FALSE | G63: TRUE | H63: FALSE | I63: Nationwide | J63: Africa | K63: 66455898 | L63: FALSE | M63: FALSE | N63: FALSE | O63: FALSE | P63: FALSE | Q63: FALSE | R63: FALSE | S63: TRUE | T63: TRUE | U63: Y | Y63: Y
A64: ZW | B64: 45161 | C64: 45161 | D64: 8 | E64: FALSE | F64: TRUE | G64: FALSE | H64: FALSE | I64: Nationwide | J64: Africa | K64: 16488132 | L64: TRUE | M64: TRUE | N64: TRUE | O64: TRUE | P64: TRUE | Q64: FALSE | R64: FALSE | S64: FALSE | T64: TRUE | U64: Y | Y64: Y
A65: AZ | B65: 45188 | D65: 2472 | E65: FALSE | F65: FALSE | G65: TRUE | H65: FALSE | I65: Nagorno-Karabakh | J65: Asia | K65: 120000 | L65: FALSE | M65: FALSE | N65: FALSE | O65: FALSE | P65: FALSE | Q65: FALSE | R65: FALSE | S65: FALSE | T65: FALSE | V65: Y | Y65: Y
A66: CN | B66: 39995 | D66: 127104 | E66: FALSE | F66: FALSE | G66: TRUE | H66: FALSE | I66: Nationwide | J66: Asia | K66: 1425849288 | L66: TRUE | M66: TRUE | N66: TRUE | O66: FALSE | P66: FALSE | Q66: FALSE | R66: FALSE | S66: FALSE | T66: TRUE | X66: Y
A67: CN | B67: 42642 | D67: 63576 | E67: TRUE | F67: FALSE | G67: FALSE | H67: FALSE | I67: Nationwide | J67: Asia | K67: 1425849288 | L67: FALSE | M67: FALSE | N67: FALSE | O67: TRUE | P67: FALSE | Q67: FALSE | R67: FALSE | S67: FALSE | T67: TRUE | X67: Y
A68: CN | B68: 42564 | D68: 65448 | E68: FALSE | F68: FALSE | G68: TRUE | H68: FALSE | I68: Nationwide | J68: Asia | K68: 1425849288 | L68: FALSE | M68: FALSE | N68: FALSE | O68: FALSE | P68: TRUE | Q68: FALSE | R68: FALSE | S68: FALSE | T68: TRUE | X68: Y
A69: CN | B69: 42979 | D69: 55488 | E69: FALSE | F69: FALSE | G69: TRUE | H69: FALSE | I69: Nationwide | J69: Asia | K69: 1425849288 | L69: FALSE | M69: FALSE | N69: FALSE | O69: FALSE | P69: FALSE | Q69: TRUE | R69: FALSE | S69: FALSE | T69: TRUE | X69: Y
A70: KP | B70: 43084 | D70: 52968 | E70: FALSE | F70: FALSE | G70: TRUE | H70: FALSE | I70: Nationwide | J70: Asia | K70: 26116716 | L70: FALSE | M70: FALSE | N70: FALSE | O70: FALSE | P70: FALSE | Q70: TRUE | R70: FALSE | S70: FALSE | T70: TRUE | X70: Y
A71: KP | B71: 42461 | D71: 67920 | E71: FALSE | F71: FALSE | G71: TRUE | H71: FALSE | I71: Nationwide | J71: Asia | K71: 26116716 | L71: TRUE | M71: TRUE | N71: TRUE | O71: FALSE | P71: FALSE | Q71: FALSE | R71: FALSE | S71: FALSE | T71: TRUE | X71: Y
A72: KP | B72: 42177 | D72: 74736 | E72: FALSE | F72: FALSE | G72: TRUE | H72: FALSE | I72: Nationwide | J72: Asia | K72: 26116716 | L72: FALSE | M72: FALSE | N72: FALSE | O72: TRUE | P72: FALSE | Q72: FALSE | R72: FALSE | S72: FALSE | T72: TRUE | X72: Y
A73: IN | B73: 45049 | D73: 5808 | E73: TRUE | F73: FALSE | G73: FALSE | H73: FALSE | I73: Manipur | J73: Asia | K73: 3436948 | L73: FALSE | M73: FALSE | N73: FALSE | O73: FALSE | P73: FALSE | Q73: FALSE | R73: FALSE | S73: FALSE | T73: FALSE | V73: Y | Y73: Y
A74: IN | B74: 45047 | D74: 5856 | E74: FALSE | F74: FALSE | G74: TRUE | H74: FALSE | I74: Nationwide | J74: Asia | K74: 1422026528 | L74: FALSE | M74: FALSE | N74: FALSE | O74: FALSE | P74: FALSE | Q74: FALSE | R74: FALSE | S74: TRUE | T74: TRUE | V74: Y | Y74: Y
A75: IN | B75: 43984 | D75: 31368 | E75: FALSE | F75: FALSE | G75: FALSE | H75: TRUE | I75: Nationwide | J75: Asia | K75: 1422026528 | L75: FALSE | M75: FALSE | N75: FALSE | O75: FALSE | P75: FALSE | Q75: FALSE | R75: TRUE | S75: TRUE | T75: TRUE | X75: Y
A76: IN | B76: 45231 | C76: 45233 | D76: 48 | E76: TRUE | F76: FALSE | G76: FALSE | H76: FALSE | I76: Various regions in India | J76: Asia | K76: 1422026528 | L76: FALSE | M76: FALSE | N76: FALSE | O76: FALSE | P76: FALSE | Q76: FALSE | R76: FALSE | S76: FALSE | T76: FALSE | U76: Y | Y76: Y
A77: IN | B77: 45164 | C77: 45166 | D77: 72 | E77: FALSE | F77: FALSE | G77: TRUE | H77: FALSE | I77: Various regions in India | J77: Asia | K77: 1422026528 | L77: FALSE | M77: FALSE | N77: FALSE | O77: FALSE | P77: FALSE | Q77: FALSE | R77: FALSE | S77: FALSE | T77: FALSE | U77: Y | Y77: Y
A78: IN | B78: 45084 | C78: 45085 | D78: 24 | E78: TRUE | F78: FALSE | G78: FALSE | H78: FALSE | I78: Various regions in India | J78: Asia | K78: 1422026528 | L78: FALSE | M78: FALSE | N78: FALSE | O78: FALSE | P78: FALSE | Q78: FALSE | R78: FALSE | S78: FALSE | T78: FALSE | U78: Y | Y78: Y
A79: IN | B79: 45055 | C79: 45058 | D79: 72 | E79: TRUE | F79: FALSE | G79: FALSE | H79: FALSE | I79: Various regions in India | J79: Asia | K79: 1422026528 | L79: FALSE | M79: FALSE | N79: FALSE | O79: FALSE | P79: FALSE | Q79: FALSE | R79: FALSE | S79: FALSE | T79: FALSE | U79: Y | Y79: Y
A80: IN | B80: 45043 | C80: 45048 | D80: 120 | E80: TRUE | F80: FALSE | G80: FALSE | H80: FALSE | I80: Various regions in India | J80: Asia | K80: 1422026528 | L80: FALSE | M80: FALSE | N80: FALSE | O80: FALSE | P80: FALSE | Q80: FALSE | R80: FALSE | S80: FALSE | T80: FALSE | U80: Y | Y80: Y
A81: IN | B81: 45038 | C81: 45040 | D81: 48 | E81: TRUE | F81: FALSE | G81: FALSE | H81: FALSE | I81: Various regions in India | J81: Asia | K81: 1422026528 | L81: FALSE | M81: FALSE | N81: FALSE | O81: FALSE | P81: FALSE | Q81: FALSE | R81: FALSE | S81: FALSE | T81: FALSE | U81: Y | Y81: Y
A82: IN | B82: 45003 | C82: 45008 | D82: 120 | E82: FALSE | F82: FALSE | G82: TRUE | H82: FALSE | I82: Various regions in India | J82: Asia | K82: 1422026528 | L82: FALSE | M82: FALSE | N82: FALSE | O82: FALSE | P82: FALSE | Q82: FALSE | R82: FALSE | S82: FALSE | T82: FALSE | U82: Y | Y82: Y
A83: IN | B83: 44983 | C83: 44985 | D83: 62 | E83: TRUE | F83: FALSE | G83: FALSE | H83: FALSE | I83: Various regions in India | J83: Asia | K83: 1422026528 | L83: FALSE | M83: FALSE | N83: FALSE | O83: FALSE | P83: FALSE | Q83: FALSE | R83: FALSE | S83: FALSE | T83: FALSE | U83: Y | Y83: Y
A84: IN | B84: 44974 | C84: 44976 | D84: 47 | E84: TRUE | F84: FALSE | G84: FALSE | H84: FALSE | I84: Various regions in India | J84: Asia | K84: 1422026528 | L84: FALSE | M84: FALSE | N84: FALSE | O84: FALSE | P84: FALSE | Q84: FALSE | R84: FALSE | S84: FALSE | T84: FALSE | U84: Y | Y84: Y
A85: IR | B85: 45240 | C85: 45240 | D85: 2 | E85: TRUE | F85: FALSE | G85: FALSE | H85: FALSE | I85: Zahedan | J85: Asia | K85: 551980 | L85: FALSE | M85: FALSE | N85: FALSE | O85: FALSE | P85: FALSE | Q85: FALSE | R85: FALSE | S85: FALSE | T85: FALSE | U85: Y | Y85: Y
A86: IR | B86: 45233 | C86: 45233 | D86: 2 | E86: TRUE | F86: FALSE | G86: FALSE | H86: FALSE | I86: Zahedan | J86: Asia | K86: 551980 | L86: FALSE | M86: FALSE | N86: FALSE | O86: FALSE | P86: FALSE | Q86: FALSE | R86: FALSE | S86: FALSE | T86: FALSE | U86: Y | Y86: Y
A87: IR | B87: 45226 | C87: 45226 | D87: 2 | E87: TRUE | F87: FALSE | G87: FALSE | H87: FALSE | I87: Zahedan | J87: Asia | K87: 551980 | L87: FALSE | M87: FALSE | N87: FALSE | O87: FALSE | P87: FALSE | Q87: FALSE | R87: FALSE | S87: FALSE | T87: FALSE | U87: Y | Y87: Y
... A113: IR | B113: 44981 | C113: 44981 | D113: 3 | E113: TRUE | F113: FALSE | G113: FALSE | H113: FALSE | I113: Zahedan | J113: Asia | K113: 551980 | L113: FALSE | M113: FALSE | N113: FALSE | O113: FALSE | P113: FALSE | Q113: FALSE | R113: FALSE | S113: FALSE | T113: FALSE | U113: Y | Y113: Y
A114: IR | B114: 44912 | C114: 44931 | D114: 9096 | E114: TRUE | F114: FALSE | G114: FALSE | H114: FALSE | I114: Sanandaj | J114: Asia | K114: 349176 | L114: FALSE | M114: FALSE | N114: FALSE | O114: FALSE | P114: FALSE | Q114: FALSE | R114: FALSE | S114: FALSE | T114: FALSE | W114: Y
A115: IR | B115: 39957 | D115: 128016 | E115: FALSE | F115: TRUE | G115: FALSE | H115: FALSE | I115: Nationwide | J115: Asia | K115: 88844498 | L115: TRUE | M115: TRUE | N115: FALSE | O115: FALSE | P115: FALSE | Q115: FALSE | R115: FALSE | S115: FALSE | T115: TRUE | X115: Y
A116: IR | B116: 39977 | D116: 127536 | E116: FALSE | F116: TRUE | G116: FALSE | H116: FALSE | I116: Nationwide | J116: Asia | K116: 88844498 | L116: FALSE | M116: FALSE | N116: TRUE | O116: FALSE | P116: FALSE | Q116: FALSE | R116: FALSE | S116: FALSE | T116: TRUE | X116: Y
A117: IR | B117: 44828 | D117: 11112 | E117: TRUE | F117: FALSE | G117: FALSE | H117: FALSE | I117: Nationwide | J117: Asia | K117: 88844498 | L117: FALSE | M117: FALSE | N117: FALSE | O117: FALSE | P117: FALSE | Q117: FALSE | R117: FALSE | S117: TRUE | T117: TRUE | X117: Y
A118: IR | B118: 44825 | D118: 11184 | E118: TRUE | F118: FALSE | G118: FALSE | H118: FALSE | I118: Nationwide | J118: Asia | K118: 88844498 | L118: FALSE | M118: FALSE | N118: FALSE | O118: TRUE | P118: FALSE | Q118: TRUE | R118: FALSE | S118: FALSE | T118: TRUE | X118: Y
A119: IR | B119: 43220 | D119: 49704 | E119: FALSE | F119: FALSE | G119: TRUE | H119: FALSE | I119: Nationwide | J119: Asia | K119: 88844498 | L119: FALSE | M119: FALSE | N119: FALSE | O119: FALSE | P119: TRUE | Q119: FALSE | R119: FALSE | S119: FALSE | T119: TRUE | X119: Y
A120: IQ | B120: 45144 | D120: 3528 | E120: FALSE | F120: FALSE | G120: FALSE | H120: TRUE | I120: Nationwide | J120: Asia | K120: 44996074 | L120: FALSE | M120: FALSE | N120: FALSE | O120: FALSE | P120: TRUE | Q120: FALSE | R120: FALSE | S120: FALSE | T120: TRUE | V120: Y | Y120: Y
A121: J&K | B121: 45235 | C121: 45239 | D121: 96 | E121: FALSE | F121: FALSE | G121: TRUE | H121: FALSE | I121: Jammu and Kashmir | J121: Asia | K121: 13606320 | L121: FALSE | M121: FALSE | N121: FALSE | O121: FALSE | P121: FALSE | Q121: FALSE | R121: FALSE | S121: FALSE | T121: FALSE | U121: Y | Y121: Y
A122: J&K | B122: 45283 | C122: 45284 | D122: 24 | E122: FALSE | F122: FALSE | G122: TRUE | H122: FALSE | I122: Jammu and Kashmir | J122: Asia | K122: 13606320 | L122: FALSE | M122: FALSE | N122: FALSE | O122: FALSE | P122: FALSE | Q122: FALSE | R122: FALSE | S122: FALSE | T122: FALSE | U122: Y | Y122: Y
A123: J&K | B123: 45051 | C123: 45051 | D123: 2 | E123: FALSE | F123: FALSE | G123: TRUE | H123: FALSE | I123: Jammu and Kashmir | J123: Asia | K123: 13606320 | L123: FALSE | M123: FALSE | N123: FALSE | O123: FALSE | P123: FALSE | Q123: FALSE | R123: FALSE | S123: FALSE | T123: FALSE | U123: Y | Y123: Y
A124: J&K | B124: 45038 | C124: 45038 | D124: 7 | E124: FALSE | F124: FALSE | G124: TRUE | H124: FALSE | I124: Jammu and Kashmir | J124: Asia | K124: 13606320 | L124: FALSE | M124: FALSE | N124: FALSE | O124: FALSE | P124: FALSE | Q124: FALSE | R124: FALSE | S124: FALSE | T124: FALSE | U124: Y | Y124: Y
A125: JO | B125: 44911 | D125: 9120 | E125: TRUE | F125: FALSE | G125: FALSE | H125: FALSE | I125: Nationwide | J125: Asia | K125: 11315547 | L125: FALSE | M125: FALSE | N125: FALSE | O125: FALSE | P125: FALSE | Q125: FALSE | R125: TRUE | S125: FALSE | T125: TRUE | X125: Y
A126: MM | B126: 44232 | D126: 25416 | E126: FALSE | F126: FALSE | G126: TRUE | H126: FALSE | I126: Nationwide | J126: Asia | K126: 54380868 | L126: FALSE | M126: TRUE | N126: FALSE | O126: FALSE | P126: FALSE | Q126: FALSE | R126: FALSE | S126: FALSE | T126: TRUE | X126: Y
A127: MM | B127: 44230 | D127: 25464 | E127: FALSE | F127: FALSE | G127: TRUE | H127: FALSE | I127: Nationwide | J127: Asia | K127: 54380868 | L127: TRUE | M127: FALSE | N127: FALSE | O127: TRUE | P127: FALSE | Q127: TRUE | R127: FALSE | S127: FALSE | T127: TRUE | X127: Y
A128: OM | B128: 44269 | D128: 24528 | E128: FALSE | F128: FALSE | G128: FALSE | H128: TRUE | I128: Nationwide | J128: Asia | K128: 4609315 | L128: FALSE | M128: FALSE | N128: FALSE | O128: FALSE | P128: FALSE | Q128: FALSE | R128: FALSE | S128: TRUE | T128: TRUE | X128: Y
A129: OM | B129: 41500 | D129: 90984 | E129: FALSE | F129: FALSE | G129: FALSE | H129: TRUE | I129: Nationwide | J129: Asia | K129: 4609315 | L129: FALSE | M129: FALSE | N129: FALSE | O129: FALSE | P129: TRUE | Q129: FALSE | R129: FALSE | S129: FALSE | T129: TRUE | X129: Y
A130: OM | B130: 39868 | D130: 130152 | E130: FALSE | F130: FALSE | G130: FALSE | H130: TRUE | I130: Nationwide | J130: Asia | K130: 4609315 | L130: FALSE | M130: FALSE | N130: FALSE | O130: FALSE | P130: FALSE | Q130: TRUE | R130: FALSE | S130: FALSE | T130: TRUE | X130: Y
A131: PK | B131: 45277 | C131: 45277 | D131: 7 | E131: FALSE | F131: FALSE | G131: TRUE | H131: FALSE | I131: Nationwide | J131: Asia | K131: 238126113 | L131: TRUE | M131: TRUE | N131: TRUE | O131: TRUE | P131: FALSE | Q131: FALSE | R131: TRUE | S131: FALSE | T131: TRUE | U131: Y | Y131: Y
A132: PK | B132: 45056 | D132: 5640 | E132: FALSE | F132: FALSE | G132: TRUE | H132: FALSE | I132: Nationwide | J132: Asia | K132: 238126113 | L132: FALSE | M132: FALSE | N132: FALSE | O132: TRUE | P132: FALSE | Q132: FALSE | R132: FALSE | S132: FALSE | T132: TRUE | V132: Y | Y132: Y
A133: PK | B133: 45055 | C133: 45058 | D133: 3 | E133: FALSE | F133: FALSE | G133: TRUE | H133: FALSE | I133: Nationwide | J133: Asia | K133: 238126113 | L133: FALSE | M133: FALSE | N133: FALSE | O133: FALSE | P133: FALSE | Q133: FALSE | R133: FALSE | S133: FALSE | T133: FALSE | U133: Y | Y133: Y
A134: PK | B134: 45055 | D134: 5664 | E134: FALSE | F134: FALSE | G134: TRUE | H134: FALSE | I134: Nationwide | J134: Asia | K134: 238126113 | L134: TRUE | M134: TRUE | N134: TRUE | O134: FALSE | P134: FALSE | Q134: FALSE | R134: FALSE | S134: FALSE | T134: TRUE | V134: Y | Y134: Y
A135: QA | B135: 43018 | D135: 54552 | E135: FALSE | F135: FALSE | G135: FALSE | H135: TRUE | I135: Nationwide | J135: Asia | K135: 2705914 | L135: FALSE | M135: FALSE | N135: FALSE | O135: FALSE | P135: FALSE | Q135: TRUE | R135: FALSE | S135: TRUE | T135: TRUE | X135: Y
A136: TH | B136: 44123 | D136: 28032 | E136: TRUE | F136: FALSE | G136: FALSE | H136: FALSE | I136: Nationwide | J136: Asia | K136: 71753808 | L136: FALSE | M136: FALSE | N136: FALSE | O136: FALSE | P136: TRUE | Q136: FALSE | R136: FALSE | S136: FALSE | T136: TRUE | X136: Y
A137: TR | B137: 44978 | D137: 7512 | E137: FALSE | F137: TRUE | G137: FALSE | H137: FALSE | I137: Nationwide | J137: Asia | K137: 85590849 | L137: FALSE | M137: FALSE | N137: FALSE | O137: FALSE | P137: FALSE | Q137: FALSE | R137: TRUE | S137: FALSE | T137: TRUE | V137: Y | Y137: Y
A138: TR | B138: 44965 | C138: 44966 | D138: 12 | E138: FALSE | F138: FALSE | G138: TRUE | H138: FALSE | I138: Nationwide | J138: Asia | K138: 85590849 | L138: FALSE | M138: TRUE | N138: FALSE | O138: FALSE | P138: FALSE | Q138: FALSE | R138: FALSE | S138: FALSE | T138: TRUE | U138: Y | Y138: Y
A139: TM | B139: 43101 | D139: 52560 | E139: FALSE | F139: FALSE | G139: TRUE | H139: FALSE | I139: Nationwide | J139: Asia | K139: 6474341 | L139: FALSE | M139: TRUE | N139: FALSE | O139: FALSE | P139: FALSE | Q139: FALSE | R139: FALSE | S139: FALSE | T139: TRUE | X139: Y
A140: TM | B140: 40422 | D140: 116856 | E140: FALSE | F140: FALSE | G140: TRUE | H140: FALSE | I140: Nationwide | J140: Asia | K140: 6474341 | L140: TRUE | M140: FALSE | N140: FALSE | O140: TRUE | P140: FALSE | Q140: FALSE | R140: FALSE | S140: FALSE | T140: TRUE | X140: Y
A141: TM | B141: 40148 | D141: 123432 | E141: FALSE | F141: FALSE | G141: TRUE | H141: FALSE | I141: Nationwide | J141: Asia | K141: 6474341 | L141: FALSE | M141: FALSE | N141: TRUE | O141: FALSE | P141: FALSE | Q141: FALSE | R141: FALSE | S141: FALSE | T141: TRUE | X141: Y
A142: TM | B142: 42005 | D142: 78864 | E142: FALSE | F142: FALSE | G142: TRUE | H142: FALSE | I142: Nationwide | J142: Asia | K142: 6474341 | L142: FALSE | M142: FALSE | N142: FALSE | O142: FALSE | P142: TRUE | Q142: TRUE | R142: FALSE | S142: FALSE | T142: TRUE | X142: Y
A143: AE | B143: 42096 | D143: 76680 | E143: FALSE | F143: FALSE | G143: FALSE | H143: TRUE | I143: Nationwide | J143: Asia | K143: 9478996 | L143: FALSE | M143: FALSE | N143: FALSE | O143: FALSE | P143: FALSE | Q143: TRUE | R143: FALSE | S143: TRUE | T143: TRUE | X143: Y
A144: AE | B144: 43221 | D144: 49680 | E144: FALSE | F144: FALSE | G144: FALSE | H144: TRUE | I144: Nationwide | J144: Asia | K144: 9478996 | L144: FALSE | M144: FALSE | N144: FALSE | O144: FALSE | P144: TRUE | Q144: FALSE | R144: FALSE | S144: FALSE | T144: TRUE | X144: Y
A145: UZ | B145: 44503 | D145: 18912 | E145: FALSE | F145: FALSE | G145: FALSE | H145: TRUE | I145: Nationwide | J145: Asia | K145: 34902257 | L145: TRUE | M145: FALSE | N145: TRUE | O145: TRUE | P145: FALSE | Q145: FALSE | R145: TRUE | S145: FALSE | T145: TRUE | X145: Y
A146: UZ | B146: 44378 | D146: 21912 | E146: FALSE | F146: FALSE | G146: FALSE | H146: TRUE | I146: Nationwide | J146: Asia | K146: 34902257 | L146: FALSE | M146: FALSE | N146: FALSE | O146: FALSE | P146: FALSE | Q146: FALSE | R146: TRUE | S146: FALSE | T146: TRUE | X146: Y
A147: UZ | B147: 44503 | D147: 18912 | E147: FALSE | F147: FALSE | G147: FALSE | H147: TRUE | I147: Nationwide | J147: Asia | K147: 34902257 | L147: FALSE | M147: FALSE | N147: FALSE | O147: FALSE | P147: TRUE | Q147: FALSE | R147: FALSE | S147: TRUE | T147: TRUE | X147: Y
A148: YE | B148: 45195 | D148: 2304 | E148: FALSE | F148: FALSE | G148: TRUE | H148: FALSE | I148: Nationwide | J148: Asia | K148: 34070907 | L148: FALSE | M148: FALSE | N148: FALSE | O148: FALSE | P148: FALSE | Q148: FALSE | R148: FALSE | S148: TRUE | T148: TRUE | V148: Y | Y148: Y
A149: YE | B149: 45240 | C149: 45240 | D149: 6 | E149: FALSE | F149: FALSE | G149: TRUE | H149: FALSE | I149: Nationwide | J149: Asia | K149: 34070907 | L149: FALSE | M149: FALSE | N149: FALSE | O149: FALSE | P149: FALSE | Q149: FALSE | R149: FALSE | S149: FALSE | T149: FALSE | U149: Y | Y149: Y
A150: YE | B150: 45229 | D150: 1488 | E150: FALSE | F150: FALSE | G150: TRUE | H150: FALSE | I150: Nationwide | J150: Asia | K150: 34070907 | L150: FALSE | M150: FALSE | N150: TRUE | O150: FALSE | P150: FALSE | Q150: FALSE | R150: TRUE | S150: FALSE | T150: TRUE | V150: Y | Y150: Y
A151: YE | B151: 43077 | D151: 53136 | E151: FALSE | F151: FALSE | G151: FALSE | H151: TRUE | I151: Nationwide | J151: Asia | K151: 34070907 | L151: FALSE | M151: FALSE | N151: FALSE | O151: FALSE | P151: FALSE | Q151: FALSE | R151: FALSE | S151: TRUE | T151: TRUE | X151: Y
A152: RU | B152: 44633 | D152: 15792 | E152: FALSE | F152: FALSE | G152: TRUE | H152: FALSE | I152: Nationwide | J152: Europe | K152: 144694112 | L152: FALSE | M152: FALSE | N152: FALSE | O152: TRUE | P152: FALSE | Q152: FALSE | R152: FALSE | S152: FALSE | T152: TRUE | X152: Y
...

Sheet 2023H1 vs. 2022H1
A1: Summary of 2023'H1 and 2022'H1
B2: Countries restricting the internet in 2023'H1 | C2: Newly imposed restrictions in 2023'H1 Internet disruptions | D2: Affected people (if there were fer restrictions imposed in a country, biggest population sample is used); Data from UN, World Population Prospects 2022 | E2: Related w/ protests | F2: Related w/ elections | G2: Related w/ political turmoil | H2: Related w/ country’s internet law | I2: Soc media | J2: Local internet | K2: Nationwide internet | L2: Registered cases since 2015 | M2: Currently blocking | N2: Region
A3: BF | B3: Burkina Faso | C3: 0 | D3: 22959516 | E3: 0 | F3: 0 | G3: 0 | H3: 0 | I3: 0 | J3: 0 | K3: 0 | L3: 4 | M3: 1 | N3: Africa
A4: ER | B4: Eritrea | C4: 0 | D4: 3715522 | E4: 0 | F4: 0 | G4: 0 | H4: 0 | I4: 0 | J4: 0 | K4: 0 | L4: 2 | M4: 1 | N4: Africa
A5: ET | B5: Ethiopia | C5: 2 | D5: 124937259 | E5: 2 | F5: 0 | G5: 0 | H5: 0 | I5: 2 | J5: 0 | K5: 0 | L5: 12 | M5: 3 | N5: Africa
A6: GN | B6: Guinea | C6: 1 | D6: 14023588 | E6: 1 | F6: 0 | G6: 0 | H6: 0 | I6: 1 | J6: 0 | K6: 0 | L6: 4 | M6: 1 | N6: Africa
A7: MR | B7: Mauritania | C7: 2 | D7: 4798604 | E7: 2 | F7: 0 | G7: 0 | H7: 0 | I7: 0 | J7: 0 | K7: 2 | L7: 3 | M7: 0 | N7: Africa
A8: SN | B8: Senegal | C8: 2 | D8: 17536231 | E8: 0 | F8: 0 | G8: 2 | H8: 0 | I8: 1 | J8: 0 | K8: 1 | L8: 3 | M8: 0 | N8: Africa
A9: SD | B9: Sudan | C9: 1 | D9: 47486909 | E9: 0 | F9: 0 | G9: 1 | H9: 0 | I9: 0 | J9: 0 | K9: 1 | L9: 12 | M9: 1 | N9: Africa
A10: TZ | B10: Tanzania | C10: 1 | D10: 66455898 | E10: 0 | F10: 0 | G10: 1 | H10: 0 | I10: 1 | J10: 0 | K10: 0 | L10: 2 | M10: 0 | N10: Africa
A11: CN | B11: China | C11: 0 | D11: 1425849288 | E11: 0 | F11: 0 | G11: 0 | H11: 0 | I11: 0 | J11: 0 | K11: 0 | L11: 4 | M11: 4 | N11: Asia
A12: KP | B12: North Korea | C12: 0 | D12: 26116716 | E12: 0 | F12: 0 | G12: 0 | H12: 0 | I12: 0 | J12: 0 | K12: 0 | L12: 3 | M12: 3 | N12: Asia
A13: IN | B13: India | C13: 9 | D13: 1422026528 | E13: 7 | F13: 0 | G13: 2 | H13: 0 | I13: 1 | J13: 8 | K13: 0 | L13: 111 | M13: 3 | N13: Asia
A14: IR | B14: Iran | C14: 14 | D14: 88844498 | E14: 14 | F14: 0 | G14: 0 | H14: 0 | I14: 0 | J14: 14 | K14: 0 | L14: 41 | M14: 5 | N14: Asia
... A31: J&K | B31: Jammu and Kashmir | C31: 2 | D31: 13606320 | E31: 0 | F31: 0 | G31: 2 | H31: 0 | I31: 0 | J31: 2 | K31: 0 | L31: 326 | M31: 0 | N31: Asia
A34: 2022'H1
B35: Countries restricting the internet in 2022'H1 | C35: Newly imposed restrictions in 2022'H1 Internet disruptions | D35: Affected people (if there were fer restrictions imposed in a country, biggest population sample is used); Data from UN, World Population Prospects 2022 | E35: Related w/ protests | F35: Related w/ elections | G35: Related w/ political turmoil | H35: Related w/ country’s internet law | I35: Soc media | J35: Local internet | K35: Nationwide internet | L35: Registered cases since 2015 | M35: Currently blocking | N35: Region
A36: BF | B36: Burkina Faso | C36: 3 | D36: 22959516 | E36: 0 | F36: 0 | G36: 3 | H36: 0 | I36: 1 | J36: 0 | K36: 2 | L36: 4 | M36: 1 | N36: Africa
A37: ER | B37: Eritrea | C37: 0 | D37: 3715522 | E37: 0 | F37: 0 | G37: 0 | H37: 0 | I37: 0 | J37: 0 | K37: 0 | L37: 2 | M37: 1 | N37: Africa
A38: ET | B38: Ethiopia | C38: 0 | D38: 5443000 | E38: 0 | F38: 0 | G38: 0 | H38: 0 | I38: 0 | J38: 0 | K38: 0 | L38: 12 | M38: 1 | N38: Africa
A39: NG | B39: Nigeria | C39: 0 | D39: 221153992 | E39: 0 | F39: 0 | G39: 0 | H39: 0 | I39: 0 | J39: 0 | K39: 0 | L39: 1 | M39: 0 | N39: Africa
A40: SD | B40: Sudan | C40: 3 | D40: 47486909 | E40: 3 | F40: 0 | G40: 0 | H40: 0 | I40: 0 | J40: 0 | K40: 3 | L40: 12 | M40: 0 | N40: Africa
A41: ZW | B41: Zimbabwe | C41: 3 | D41: 16488132 | E41: 3 | F41: 0 | G41: 0 | H41: 0 | I41: 0 | J41: 0 | K41: 3 | L41: 6 | M41: 0 | N41: Africa
A42: CN | B42: China | C42: 0 | D42: 1425849288 | E42: 0 | F42: 0 | G42: 0 | H42: 0 | I42: 0 | J42: 0 | K42: 0 | L42: 4 | M42: 4 | N42: Asia
A43: KP | B43: North Korea | C43: 0 | D43: 26116716 | E43: 0 | F43: 0 | G43: 0 | H43: 0 | I43: 0 | J43: 0 | K43: 0 | L43: 3 | M43: 3 | N43: Asia
A44: IN | B44: India | C44: 6 | D44: 1422026528 | E44: 6 | F44: 0 | G44: 0 | H44: 0 | I44: 0 | J44: 6 | K44: 0 | L44: 111 | M44: 1 | N44: Asia
A45: IR | B45: Iran | C45: 1 | D45: 88844498 | E45: 1 | F45: 0 | G45: 0 | H45: 0 | I45: 0 | J45: 0 | K45: 1 | L45: 41 | M45: 3 | N45: Asia
A46: JO | B46: Jordan | C46: 1 | D46: 11315547 | E46: 0 | F46: 0 | G46: 1 | H46: 0 | I46: 1 | J46: 0 | K46: 0 | L46: 5 | M46: 0 | N46: Asia
A47: KZ | B47: Kazakhstan | C47: 1 | D47: 19500494 | E47: 1 | F47: 0 | G47: 0 | H47: 0 | I47: 0 | J47: 0 | K47: 1 | L47: 8 | M47: 0 | N47: Asia
... A61: J&K | B61: Jammu and Kashmir | C61: 35 | D61: 13606320 | E61: 1 | F61: 0 | G61: 34 | H61: 0 | I61: 0 | J61: 35 | K61: 0 | L61: 326 | M61: 0 | N61: Asia

Sheet 2022
A1: Summary of 2022. Below the summary, there is a list of all the 2022 cases
B2: Countries restricting the internet in 2022 | C2: Newly imposed restrictions in 2022 Internet disruptions | D2: Affected people (if there were fer restrictions imposed in a country, biggest population sample is used); Data from UN, World Population Prospects 2021 | E2: Related w/ protests | F2: Related w/ elections | G2: Related w/ political turmoil | H2: Related w/ country’s internet law | I2: Soc media | J2: Local internet | K2: Nationwide internet | L2: Registered cases since 2015 | M2: Currently blocking | N2: Region
A3: BF | B3: Burkina Faso | C3: 3 | D3: 20903273 | E3: 0 | F3: 0 | G3: 3 | H3: 0 | I3: 1 | J3: 0 | K3: 2 | L3: 4 | M3: Y | N3: Africa
A4: ER | B4: Eritrea | C4: 0 | D4: 3546421 | E4: 0 | F4: 0 | G4: 0 | H4: 0 | I4: 0 | J4: 0 | K4: 0 | L4: 2 | M4: Y | N4: Africa
A5: ET | B5: Ethiopia | C5: 0 | D5: 5443000 | E5: 0 | F5: 0 | G5: 0 | H5: 0 | I5: 0 | J5: 0 | K5: 0 | L5: 10 | M5: Y | N5: Africa
A6: NG | B6: Nigeria | C6: 0 | D6: 206139589 | E6: 0 | F6: 0 | G6: 0 | H6: 0 | I6: 0 | J6: 0 | K6: 0 | L6: 1 | N6: Africa
A7: SL | B7: Sierra Leone | C7: 2 | D7: 7976983 | E7: 2 | F7: 0 | G7: 0 | H7: 0 | I7: 0 | J7: 0 | K7: 2 | L7: 3 | N7: Africa
A8: SO | B8: Somalia | C8: 1 | D8: 477876 | E8: 1 | F8: 0 | G8: 0 | H8: 0 | I8: 0 | J8: 1 | K8: 0 | L8: 3 | N8: Africa
A9: SD | B9: Sudan | C9: 4 | D9: 43849260 | E9: 4 | F9: 0 | G9: 0 | H9: 0 | I9: 0 | J9: 0 | K9: 4 | L9: 11 | N9: Africa
A10: ZW | B10: Zimbabwe | C10: 3 | D10: 14862924 | E10: 3 | F10: 0 | G10: 0 | H10: 0 | I10: 0 | J10: 0 | K10: 3 | L10: 6 | N10: Africa
A11: AF | B11: Afghanistan | C11: 1 | D11: 38928346 | E11: 0 | F11: 0 | G11: 1 | H11: 0 | I11: 0 | J11: 0 | K11: 1 | L11: 2 | N11: Asia
A12: AM | B12: Armenia | C12: 1 | D12: 2963243 | E12: 0 | F12: 0 | G12: 1 | H12: 0 | I12: 1 | J12: 0 | K12: 0 | L12: 3 | N12: Asia
A13: AZ | B13: Azerbaijan | C13: 1 | D13: 10139177 | E13: 0 | F13: 0 | G13: 1 | H13: 0 | I13: 1 | J13: 0 | K13: 0 | L13: 2 | M13: Y | N13: Asia
A14: CN | B14: China | C14: 0 | D14: 1439323776 | E14: 0 | F14: 0 | G14: 0 | H14: 0 | I14: 0 | J14: 0 | K14: 0 | L14: 4 | M14: Y | N14: Asia
A15: KP | B15: North Korea | C15: 0 | D15: 25778816 | E15: 0 | F15: 0 | G15: 0 | H15: 0 | I15: 0 | J15: 0 | K15: 0 | L15: 3 | M15: Y | N15: Asia
A16: IN | B16: India | C16: 10 | D16: 1380004385 | E16: 9 | F16: 0 | G16: 1 | H16: 0 | I16: 0 | J16: 10 | K16: 0 | L16: 102 | M16: Y | N16: Asia
A17: IR | B17: Iran | C17: 11 | D17: 83992949 | E17: 10 | F17: 0 | G17: 1 | H17: 0 | I17: 2 | J17: 4 | K17: 5 | L17: 27 | M17: Y | N17: Asia
A18: JO | B18: Jordan | C18: 2 | D18: 10203134 | E18: 1 | F18: 0 | G18: 1 | H18: 0 | I18: 2 | J18: 0 | K18: 0 | L18: 5 | M18: Y | N18: Asia
A19: KZ | B19: Kazakhstan | C19: 2 | D19: 18776707 | E19: 2 | F19: 0 | G19: 0 | H19: 0 | I19: 0 | J19: 1 | K19: 1 | L19: 8 | N19: Asia
A20: MM | B20: Myanmar | C20: 0 | D20: 54409800 | E20: 0 | F20: 0 | G20: 0 | H20: 0 | I20: 0 | J20: 0 | K20: 0 | L20: 6 | M20: Y | N20: Asia
A21: OM | B21: Oman | C21: 0 | D21: 5106626 | E21: 0 | F21: 0 | G21: 0 | H21: 0 | I21: 0 | J21: 0 | K21: 0 | L21: 3 | M21: Y | N21: Asia
A22: PK | B22: Pakistan | C22: 3 | D22: 220892340 | E22: 1 | F22: 0 | G22: 2 | H22: 0 | I22: 2 | J22: 1 | K22: 0 | L22: 12 | N22: Asia
A23: QA | B23: Qatar | C23: 0 | D23: 2881053 | E23: 0 | F23: 0 | G23: 0 | H23: 0 | I23: 0 | J23: 0 | K23: 0 | L23: 1 | M23: Y | N23: Asia
A24: LK | B24: Sri Lanka | C24: 2 | D24: 21413249 | E24: 2 | F24: 0 | G24: 0 | H24: 0 | I24: 1 | J24: 0 | K24: 1 | L24: 5 | N24: Asia
A25: TH | B25: Thailand | C25: 0 | D25: 69799978 | E25: 0 | F25: 0 | G25: 0 | H25: 0 | I25: 0 | J25: 0 | K25: 0 | L25: 1 | M25: Y | N25: Asia
A26: TM | B26: Turkmenistan | C26: 0 | D26: 6031200 | E26: 0 | F26: 0 | G26: 0 | H26: 0 | I26: 0 | J26: 0 | K26: 0 | L26: 4 | M26: Y | N26: Asia
A27: AE | B27: U.A.E. | C27: 0 | D27: 9890402 | E27: 0 | F27: 0 | G27: 0 | H27: 0 | I27: 0 | J27: 0 | K27: 0 | L27: 2 | M27: Y | N27: Asia
A28: UZ | B28: Uzbekistan | C28: 1 | D28: 33469203 | E28: 1 | F28: 0 | G28: 0 | H28: 0 | I28: 0 | J28: 0 | K28: 1 | L28: 6 | M28: Y | N28: Asia
A29: YE | B29: Yemen | C29: 0 | D29: 29825964 | E29: 0 | F29: 0 | G29: 0 | H29: 0 | I29: 0 | J29: 0 | K29: 0 | L29: 3 | M29: Y | N29: Asia
A30: RU | B30: Russia | C30: 3 | D30: 145934462 | E30: 0 | F30: 0 | G30: 3 | H30: 0 | I30: 3 | J30: 0 | K30: 0 | L30: 9 | M30: Y | N30: Europe
A31: UA | B31: Ukraine | C31: 0 | D31: 43733762 | E31: 0 | F31: 0 | G31: 0 | H31: 0 | I31: 0 | J31: 0 | K31: 0 | L31: 1 | M31: Y | N31: Europe
A32: CU | B32: Cuba | C32: 3 | D32: 11326616 | E32: 3 | F32: 0 | G32: 0 | H32: 0 | I32: 0 | J32: 0 | K32: 3 | L32: 7 | N32: North America
A33: BR | B33: Brazil | C33: 1 | D33: 212559417 | E33: 0 | F33: 0 | G33: 1 | H33: 0 | I33: 1 | J33: 0 | K33: 0 | L33: 4 | N33: South America
A34: J&K | B34: Jammu and Kashmir | C34: 24 | D34: 13606320 | E34: 0 | F34: 0 | G34: 24 | H34: 0 | I34: 0 | J34: 24 | K34: 0 | L34: 306 | N34: Asia
A40: List of all restrictions in 2022
A41: Iso-2 array | B41: Start date | C41: End date | D41: Duration (until the end of 2022), h | E41: If yes, what was the context? | F41: Related w/ protests | G41: Related w/ elections | H41: Related w/ political turmoil | I41: Related w/ country’s internet law | J41: Scope/population? | K41: Region | L41: Population; Data from UN, World Population Prospects 2021 | M41: Facebook | N41: Twitter | O41: Youtube | P41: Instagram | Q41: Telegram | R41: Whatsapp | S41: Other soc. media | T41: Other VoIP apps | U41: Service based restriction | V41: Cases that started and ended in chosen period | W41: Cases that started in chosen period and are still ongoing | X41: Cases that started earlier but ended in chosen period | Y41: Cases that started earlier and are still ongoing | Z41: Cases that started in this period
A42: BF | B42: 44584 | C42: 44585 | D42: 35 | E42: Internet disrupted in Burkina Faso amid military uprising | F42: FALSE | G42: FALSE | H42: TRUE | I42: FALSE | J42: Nationwide | K42: Africa | L42: 20903273 | M42: FALSE | N42: FALSE | O42: FALSE | P42: FALSE | Q42: FALSE | R42: FALSE | S42: FALSE | T42: FALSE | U42: FALSE | V42: Y | Z42: Y
A43: BF | B43: 44572 | D43: 8496 | E43: On 19 January 2022, authorities admitted that they restricted access to Facebook services citing security concern. Restrictions started on 11 January. | F43: FALSE | G43: FALSE | H43: TRUE | I43: FALSE | J43: Nationwide | K43: Africa | L43: 20903273 | M43: TRUE | N43: FALSE | O43: FALSE | P43: FALSE | Q43: FALSE | R43: FALSE | S43: FALSE | T43: FALSE | U43: TRUE | W43: Y | Z43: Y
A44: BF | B44: 44571 | C44: 44572 | D44: 15 | E44: Internet disruptions observed in Burkina Faso amid coup plot arrests. | F44: FALSE | G44: FALSE | H44: TRUE | I44: FALSE | J44: Nationwide | K44: Africa | L44: 20903273 | M44: FALSE | N44: FALSE | O44: FALSE | P44: FALSE | Q44: FALSE | R44: FALSE | S44: FALSE | T44: FALSE | U44: FALSE | V44: Y | Z44: Y
A45: ER | B45: 40544 | D45: 105168 | E45: According to Freedom House, Eritrea has one of the worst infrastructures in Africa, it is possible that some ISPs deliberately block services, but the government’s poor human rights record indicates that the inaccessibility of YouTube could be related to censorship. | F45: FALSE | G45: FALSE | H45: TRUE | I45: FALSE | J45: Nationwide | K45: Africa | L45: 3546421 | M45: FALSE | N45: FALSE | O45: TRUE | P45: FALSE | Q45: FALSE | R45: FALSE | S45: FALSE | T45: FALSE | U45: TRUE | Y45: Y
A46: ET | B46: 44139 | D46: 18888 | E46: Tigray has been mostly without internet, telecommunications and banking since war broke out between federal government troops and forces led by the Tigray People’s Liberation Front (TPLF) in November 2020. A ceasefire deal between the warring sides was signed in South Africa in November of 2022. It commits Ethiopia’s government to restoring Tigray’s basic services, but the communications blackout has not yet been lifted. | F46: FALSE | G46: FALSE | H46: TRUE | I46: FALSE | J46: Tigray region | K46: Africa | L46: 5443000 | M46: FALSE | N46: FALSE | O46: FALSE | P46: FALSE | Q46: FALSE | R46: FALSE | S46: FALSE | T46: FALSE | U46: FALSE | Y46: Y
A47: NG | B47: 44352 | C47: 44574 | D47: 13776 | E47: Nigeria banned Twitter after the social media site removed a post by President Muhammadu Buhari threatening secessionists. | F47: FALSE | G47: FALSE | H47: TRUE | I47: FALSE | J47: Nationwide | K47: Africa | L47: 206139589 | M47: FALSE | N47: TRUE | O47: FALSE | P47: FALSE | Q47: FALSE | R47: FALSE | S47: FALSE | T47: FALSE | U47: TRUE | X47: Y
A48: SL | B48: 44784 | C48: 44784 | D48: 8 | E48: An overnight internet blackout, the second registered amid anti-government protests. | F48: TRUE | G48: FALSE | H48: FALSE | I48: FALSE | J48: Nationwide | K48: Africa | L48: 7976983 | M48: FALSE | N48: FALSE | O48: FALSE | P48: FALSE | Q48: FALSE | R48: FALSE | S48: FALSE | T48: FALSE | U48: FALSE | V48: Y | Z48: Y
A49: SL | B49: 44783 | C49: 44783 | D49: 2 | E49: The internet was disrupted on multiple providers nationwide in Sierra Leone. National connectivity was observed at just 5% of ordinary levels for two hours. The incident came amid protests in the capital city Freetown and other areas. | F49: TRUE | G49: FALSE | H49: FALSE | I49: FALSE | J49: Nationwide | K49: Africa | L49: 7976983 | M49: FALSE | N49: FALSE | O49: FALSE | P49: FALSE | Q49: FALSE | R49: FALSE | S49: FALSE | T49: FALSE | U49: FALSE | V49: Y | Z49: Y
A50: SO | B50: 44784 | C50: 44784 | D50: 4 | E50: Multiple providers in Somaliland experienced major internet disruptions on Thursday, August 11, 2022. The incident happened just before planned protests over the postponement of elections. | F50: TRUE | G50: FALSE | H50: FALSE | I50: FALSE | J50: Hargeysa | K50: Africa | L50: 477876 | M50: FALSE | N50: FALSE | O50: FALSE | P50: FALSE | Q50: FALSE | R50: FALSE | S50: FALSE | T50: FALSE | U50: FALSE | V50: Y | Z50: Y
A51: SD | B51: 44859 | C51: 44859 | D51: 8 | E51: A significant internet disruption affected cellular and fixed-line connectivity on multiple providers for around 8 hours. The incident comes ahead of planned pro-democracy protests to mark the first anniversary of the 2021 Sudanese military coup. Internet shutdowns were then imposed to silence public dissent. | F51: TRUE | G51: FALSE | H51: FALSE | I51: FALSE | J51: Nationwide | K51: Africa | L51: 43849260 | M51: FALSE | N51: FALSE | O51: FALSE | P51: FALSE | Q51: FALSE | R51: FALSE | S51: FALSE | T51: FALSE | U51: FALSE | V51: Y | Z51: Y
A52: SD | B52: 44742 | C52: 44742 | D52: 18 | E52: Internet service disruption was recorded on multiple mobile and fixed-line internet providers across Sudan amid protests against the military junta. | F52: TRUE | G52: FALSE | H52: FALSE | I52: FALSE | J52: Nationwide | K52: Africa | L52: 43849260 | M52: FALSE | N52: FALSE | O52: FALSE | P52: FALSE | Q52: FALSE | R52: FALSE | S52: FALSE | T52: FALSE | U52: FALSE | V52: Y | Z52: Y
A53: SD | B53: 44567 | C53: 44567 | D53: 10 | E53: Mobile internet disrupted ahead of planned mass-protests against the October 25 military coup. | F53: TRUE | G53: FALSE | H53: FALSE | I53: FALSE | J53: Nationwide | K53: Africa | L53: 43849260 | M53: FALSE | N53: FALSE | O53: FALSE | P53: FALSE | Q53: FALSE | R53: FALSE | S53: FALSE | T53: FALSE | U53: FALSE | V53: Y | Z53: Y
A54: SD | B54: 44563 | C54: 44563 | D54: 10 | E54: Mobile data service was again cut for some 10 hours during protests against military violence following the coup. | F54: TRUE | G54: FALSE | H54: FALSE | I54: FALSE | J54: Nationwide | K54: Africa | L54: 43849260 | M54: FALSE | N54: FALSE | O54: FALSE | P54: FALSE | Q54: FALSE | R54: FALSE | S54: FALSE | T54: FALSE | U54: FALSE | V54: Y | Z54: Y
A55: ZW | B55: 44633 | C55: 44633 | D55: 12 | E55: A new series of disruptions was registered amid further opposition demonstrations. | F55: TRUE | G55: FALSE | H55: FALSE | I55: FALSE | J55: Nationwide | K55: Africa | L55: 14862924 | M55: FALSE | N55: FALSE | O55: FALSE | P55: FALSE | Q55: FALSE | R55: FALSE | S55: FALSE | T55: FALSE | U55: FALSE | V55: Y | Z55: Y
A56: ZW | B56: 44612 | C56: 44614 | D56: 20 | E56: Significant slowing of internet service for many users in Zimbabwe as a major political opposition rally is held in Harare. | F56: TRUE | G56: FALSE | H56: FALSE | I56: FALSE | J56: Nationwide | K56: Africa | L56: 14862924 | M56: FALSE | N56: FALSE | O56: FALSE | P56: FALSE | Q56: FALSE | R56: FALSE | S56: FALSE | T56: FALSE | U56: FALSE | V56: Y | Z56: Y
A57: ZW | B57: 44593 | C57: 44594 | D57: 5 | E57: Internet slowdown limits coverage of Zimbabwe opposition rally | F57: TRUE | G57: FALSE | H57: FALSE | I57: FALSE | J57: Nationwide | K57: Africa | L57: 14862924 | M57: FALSE | N57: FALSE | O57: FALSE | P57: FALSE | Q57: FALSE | R57: FALSE | S57: FALSE | T57: FALSE | U57: FALSE | V57: Y | Z57: Y
A58: AF | B58: 44781 | C58: 44781 | D58: 4 | E58: Internet disruption in Afghanistan with high impact to Kabul affecting multiple providers, for fear of militant bombings as Shiite Muslims in the Middle East mark the holy day of Ashoura. | F58: FALSE | G58: FALSE | H58: TRUE | I58: FALSE | J58: Nationwide | K58: Asia | L58: 38928346 | M58: FALSE | N58: FALSE | O58: FALSE | P58: FALSE | Q58: FALSE | R58: FALSE | S58: FALSE | T58: FALSE | U58: FALSE | V58: Y | Z58: Y
A59: AM | B59: 44818 | C59: 44826 | D59: 192 | E59: TikTok restricted on multiple internet providers in Armenia and Azerbaijan amid deadly clashes between the countries over the Nagorno-Karabakh region. OONI data suggests that TikTok has been unblocked in Armenia but remains restricted in Azerbaijan. | F59: FALSE | G59: FALSE | H59: TRUE | I59: FALSE | J59: Nationwide | K59: Asia | L59: 2963243 | M59: FALSE | N59: FALSE | O59: FALSE | P59: FALSE | Q59: FALSE | R59: FALSE | S59: TRUE | T59: FALSE | U59: TRUE | V59: Y | Z59: Y
A60: AZ | B60: 44818 | D60: 2592 | E60: TikTok restricted on multiple internet providers in Armenia and Azerbaijan amid deadly clashes between the countries over the Nagorno-Karabakh region. OONI data suggests that TikTok has been unblocked in Armenia but remains restricted in Azerbaijan. | F60: FALSE | G60: FALSE | H60: TRUE | I60: FALSE | J60: Nationwide | K60: Asia | L60: 10139177 | M60: FALSE | N60: FALSE | O60: FALSE | P60: FALSE | Q60: FALSE | R60: FALSE | S60: TRUE | T60: FALSE | U60: TRUE | W60: Y | Z60: Y
A61: CN | B61: 39995 | D61: 118344 | E61: Foreign social media platforms such as Twitter, Facebook, and YouTube are currently banned in China. | F61: FALSE | G61: FALSE | H61: TRUE | I61: FALSE | J61: Nationwide | K61: Asia | L61: 1439323776 | M61: TRUE | N61: TRUE | O61: TRUE | P61: FALSE | Q61: FALSE | R61: FALSE | S61: FALSE | T61: FALSE | U61: TRUE | Y61: Y
A62: CN | B62: 42642 | D62: 54816 | E62: Instagram blocked in China as protests sweep Hong Kong. | F62: TRUE | G62: FALSE | H62: FALSE | I62: FALSE | J62: Nationwide | K62: Asia | L62: 1439323776 | M62: FALSE | N62: FALSE | O62: FALSE | P62: TRUE | Q62: FALSE | R62: FALSE | S62: FALSE | T62: FALSE | U62: TRUE | Y62: Y
A63: CN | B63: 42564 | D63: 56688 | E63: China blocks Telegram messenger, blamed for aiding human rights lawyers. | F63: FALSE | G63: FALSE | H63: TRUE | I63: FALSE | J63: Nationwide | K63: Asia | L63: 1439323776 | M63: FALSE | N63: FALSE | O63: FALSE | P63: FALSE | Q63: TRUE | R63: FALSE | S63: FALSE | T63: FALSE | U63: TRUE | Y63: Y
A64: CN | B64: 42979 | D64: 46728 | E64: China Blocks WhatsApp, broadening online censorship. | F64: FALSE | G64: FALSE | H64: TRUE | I64: FALSE | J64: Nationwide | K64: Asia | L64: 1439323776 | M64: FALSE | N64: FALSE | O64: FALSE | P64: FALSE | Q64: FALSE | R64: TRUE | S64: FALSE | T64: FALSE | U64: TRUE | Y64: Y
A65: KP | B65: 43084 | D65: 44208 | E65: WhatsApp messaging service blocked in North Korea | F65: FALSE | G65: FALSE | H65: TRUE | I65: FALSE | J65: Nationwide | K65: Asia | L65: 25778816 | M65: FALSE | N65: FALSE | O65: FALSE | P65: FALSE | Q65: FALSE | R65: TRUE | S65: FALSE | T65: FALSE | U65: TRUE | Y65: Y
A66: KP | B66: 42981 | D66: 46680 | E66: North Korea started blocking, Facebook, YouTube, Twitter and South Korean websites in April 2016. | F66: FALSE | G66: FALSE | H66: TRUE | I66: FALSE | J66: Nationwide | K66: Asia | L66: 25778816 | M66: TRUE | N66: TRUE | O66: TRUE | P66: FALSE | Q66: FALSE | R66: FALSE | S66: FALSE | T66: FALSE | U66: TRUE | Y66: Y
A67: KP | B67: 42177 | D67: 65976 | E67: North Korea blocks access to Instagram | F67: FALSE | G67: FALSE | H67: TRUE | I67: FALSE | J67: Nationwide | K67: Asia | L67: 25778816 | M67: FALSE | N67: FALSE | O67: FALSE | P67: TRUE | Q67: FALSE | R67: FALSE | S67: FALSE | T67: FALSE | U67: TRUE | Y67: Y
A68: IN | B68: 44729 | C68: 44733 | D68: 84 | E68: A significant disruption to fixed-line and mobile internet connectivity on multiple providers occurred in Bihar, eastern India, on June 17, 2022. The incident is ongoing at the time of writing and comes as the government imposes telecommunications restrictions to counter protests over a new military recruitment plan. | F68: TRUE | G68: FALSE | H68: FALSE | I68: FALSE | J68: Bihar | K68: Asia | L68: 128300000 | M68: FALSE | N68: FALSE | O68: FALSE | P68: FALSE | Q68: FALSE | R68: FALSE | S68: FALSE | T68: FALSE | U68: FALSE | V68: Y | Z68: Y
A69: IN | B69: 43984 | D69: 22608 | E69: TikTok + 59 Chinese apps' ban. | F69: FALSE | G69: FALSE | H69: FALSE | I69: TRUE | J69: Nationwide | K69: Asia | L69: 1380004385 | M69: FALSE | N69: FALSE | O69: FALSE | P69: FALSE | Q69: FALSE | R69: FALSE | S69: TRUE | T69: TRUE | U69: TRUE | Y69: Y
A70: IR | B70: 44912 | D70: 336 | E70: Internet connectivity has been disrupted in and around Sanandaj, Kurdistan Province, corroborating user reports of curfew-style cuts during strikes over the death of Mahsa Amini. | F70: TRUE | G70: FALSE | H70: FALSE | I70: FALSE | J70: Sanandaj | K70: Asia | L70: 349176 | M70: FALSE | N70: FALSE | O70: FALSE | P70: FALSE | Q70: FALSE | R70: FALSE | S70: FALSE | T70: FALSE | U70: FALSE | W70: Y | Z70: Y
A71: IR | B71: 44907 | C71: 44907 | D71: 1 | E71: Abnormal drop in internet connectivity around the time of the execution of Majidreza Rahnavard. | F71: FALSE | G71: FALSE | H71: TRUE | I71: FALSE | J71: Nationwide | K71: Asia | L71: 83992949 | M71: FALSE | N71: FALSE | O71: FALSE | P71: FALSE | Q71: FALSE | R71: FALSE | S71: FALSE | T71: FALSE | U71: FALSE | V71: Y | Z71: Y
A72: IR | B72: 44903 | C72: 44903 | D72: 7 | E72: Disruption to internet connectivity in and around Sanandaj, Kurdistan Province, after the killing of Houman Abdollahi and amid protests over the execution of Mohsen Shekari. | F72: TRUE | G72: FALSE | H72: FALSE | I72: FALSE | J72: Sanandaj | K72: Asia | L72: 349176 | M72: FALSE | N72: FALSE | O72: FALSE | P72: FALSE | Q72: FALSE | R72: FALSE | S72: FALSE | T72: FALSE | U72: FALSE | V72: Y | Z72: Y
A73: IR | B73: 44886 | C73: 44886 | D73: 4 | E73: Mobile internet cut off for many users amid a wave of new protests over the death of Mahsa Amini and reports of casualties, just as the Iranian World Cup team refused to sing the national anthem and backed the protest movement. | F73: TRUE | G73: FALSE | H73: FALSE | I73: FALSE | J73: Nationwide | K73: Asia | L73: 83992949 | M73: FALSE | N73: FALSE | O73: FALSE | P73: FALSE | Q73: FALSE | R73: FALSE | S73: FALSE | T73: FALSE | U73: FALSE | V73: Y | Z73: Y
A74: IR | B74: 44829 | C74: 44862 | D74: 330 | E74: Recurring disruptions to internet service amid protests over Mahsa Amini's death. Some disruptions nationwide, some localized (Zahedan, West Azerbaijan province, Kurdistan province, Sanandaj, South Iran, Amirkabir University). | F74: TRUE | G74: FALSE | H74: FALSE | I74: FALSE | J74: Nationwide | K74: Asia | L74: 83992949 | M74: FALSE | N74: FALSE | O74: FALSE | P74: FALSE | Q74: FALSE | R74: FALSE | S74: FALSE | T74: FALSE | U74: FALSE | V74: Y | Z74: Y
A75: IR | B75: 44825 | C75: 44827 | D75: 24 | E75: Mobile networks disrupted leaving many internet users completely offline. These mobile disruptions continued daily in a curfew-style rolling manner through to Friday. | F75: TRUE | G75: FALSE | H75: FALSE | I75: FALSE | J75: Nationwide | K75: Asia | L75: 83992949 | M75: FALSE | N75: FALSE | O75: FALSE | P75: FALSE | Q75: FALSE | R75: FALSE | S75: FALSE | T75: FALSE | U75: FALSE | V75: Y | Z75: Y
A76: IR | B76: 44823 | C76: 44823 | D76: 4 | E76: Near-total disruption to internet connectivity in Sanandaj, the capital of Kurdistan province, amid widening protests over the death of Mahsa Amini. | F76: TRUE | G76: FALSE | H76: FALSE | I76: FALSE | J76: Sanandaj | K76: Asia | L76: 349176 | M76: FALSE | N76: FALSE | O76: FALSE | P76: FALSE | Q76: FALSE | R76: FALSE | S76: FALSE | T76: FALSE | U76: FALSE | V76: Y | Z76: Y
A77: IR | B77: 44820 | C77: 44820 | D77: 48 | E77: A significant internet outage has been registered in Tehran, with real time network data showing connectivity at 67% of ordinary levels; the incident comes amid protests over the death of Mahsa Amini. | F77: TRUE | G77: FALSE | H77: FALSE | I77: FALSE | J77: Tehran | K77: Asia | L77: 7153309 | M77: FALSE | N77: FALSE | O77: FALSE | P77: FALSE | Q77: FALSE | R77: FALSE | S77: FALSE | T77: FALSE | U77: FALSE | V77: Y | Z77: Y
A78: IR | B78: 44692 | C78: 44692 | D78: 3 | E78: An internet disruption has been registered in Iran with high impact to provider MobinNet; the incident comes amid ongoing protests. | F78: TRUE | G78: FALSE | H78: FALSE | I78: FALSE | J78: Nationwide | K78: Asia | L78: 83992949 | M78: FALSE | N78: FALSE | O78: FALSE | P78: FALSE | Q78: FALSE | R78: FALSE | S78: FALSE | T78: FALSE | U78: FALSE | V78: Y | Z78: Y
A79: IR | B79: 39957 | D79: 119256 | E79: Iranian government blocks Facebook access. Opposition parties accuse President Mahmoud Ahmadinejad of trying to curb support for rivals before elections | F79: FALSE | G79: TRUE | H79: FALSE | I79: FALSE | J79: Nationwide | K79: Asia | L79: 83992949 | M79: TRUE | N79: TRUE | O79: FALSE | P79: FALSE | Q79: FALSE | R79: FALSE | S79: FALSE | T79: FALSE | U79: TRUE | Y79: Y
A80: IR | B80: 39977 | D80: 118776 | E80: The main mobile telephone network in Iran was cut in the capital Tehran evening while popular Internet websites Facebook and YouTube also appeared to be blocked | F80: FALSE | G80: TRUE | H80: FALSE | I80: FALSE | J80: Nationwide | K80: Asia | L80: 83992949 | M80: FALSE | N80: FALSE | O80: TRUE | P80: FALSE | Q80: FALSE | R80: FALSE | S80: FALSE | T80: FALSE | U80: TRUE | Y80: Y
A81: IR | B81: 44828 | D81: 2352 | E81: Access to Skype restricted across all major ISPs amid protests over Mahsa Amini's death. | F81: TRUE | G81: FALSE | H81: FALSE | I81: FALSE | J81: Nationwide | K81: Asia | L81: 83992949 | M81: FALSE | N81: FALSE | O81: FALSE | P81: FALSE | Q81: FALSE | R81: FALSE | S81: FALSE | T81: TRUE | U81: TRUE | W81: Y | Z81: Y
A82: IR | B82: 44825 | D82: 2424 | E82: Access to WhatsApp and Instagram restricted across all major ISPs amid protests over Mahsa Amini's death. | F82: TRUE | G82: FALSE | H82: FALSE | I82: FALSE | J82: Nationwide | K82: Asia | L82: 83992949 | M82: FALSE | N82: FALSE | O82: FALSE | P82: TRUE | Q82: FALSE | R82: TRUE | S82: FALSE | T82: FALSE | U82: TRUE | W82: Y | Z82: Y
A83: IR | B83: 43220 | D83: 40944 | E83: Iran blocks Telegram, claiming the app endangers national security. | F83: FALSE | G83: FALSE | H83: TRUE | I83: FALSE | J83: Nationwide | K83: Asia | L83: 83992949 | M83: FALSE | N83: FALSE | O83: FALSE | P83: FALSE | Q83: TRUE | R83: FALSE | S83: FALSE | T83: FALSE | U83: TRUE | Y83: Y
A84: JO | B84: 44911 | D84: 360 | E84: TikTok restricted on multiple internet providers amid protests over high fuel prices that have spread to several cities across the kingdom. | F84: TRUE | G84: FALSE | H84: FALSE | I84: FALSE | J84: Nationwide | K84: Asia | L84: 10203134 | M84: FALSE | N84: FALSE | O84: FALSE | P84: FALSE | Q84: FALSE | R84: FALSE | S84: TRUE | T84: FALSE | U84: TRUE | W84: Y | Z84: Y
A85: JO | B85: 44700 | C85: 44700 | D85: 3 | E85: Facebook CDN servers disrupted on multiple networks as King Abdullah II approves measures to formally detain former Crown Prince Hamzah and impacts internet users' ability to stream content online. | F85: FALSE | G85: FALSE | H85: TRUE | I85: FALSE | J85: Nationwide | K85: Asia | L85: 10203134 | M85: TRUE | N85: FALSE | O85: FALSE | P85: FALSE | Q85: FALSE | R85: FALSE | S85: FALSE | T85: FALSE | U85: TRUE | V85: Y | Z85: Y
A86: KZ | B86: 44891 | C86: 44891 | D86: 2 | E86: The people of Astana, Kazakhstan experienced an internet disruption as a rally formed in the capital city on 26 Nov to demonstrate against inauguration. Officials have claimed the Internet outage was due to equipment failure. | F86: TRUE | G86: FALSE | H86: FALSE | I86: FALSE | J86: Astana | K86: Asia | M86: FALSE | N86: FALSE | O86: FALSE | P86: FALSE | Q86: FALSE | R86: FALSE | S86: FALSE | T86: FALSE | U86: FALSE | V86: Y | Z86: Y
A87: KZ | B87: 44566 | C87: 44572 | D87: 139 | E87: Internet disrupted in Kazakhstan amid energy price protests | F87: TRUE | G87: FALSE | H87: FALSE | I87: FALSE | J87: Nationwide | K87: Asia | L87: 18776707 | M87: FALSE | N87: FALSE | O87: FALSE | P87: FALSE | Q87: FALSE | R87: FALSE | S87: FALSE | T87: FALSE | U87: FALSE | V87: Y | Z87: Y
A88: MM | B88: 44232 | D88: 16656 | E88: Network data confirm the restriction of Twitter on Myanmar’s leading network operators, following the blocking of other social media platforms. | F88: FALSE | G88: FALSE | H88: TRUE | I88: FALSE | J88: Nationwide | K88: Asia | L88: 54409800 | M88: FALSE | N88: TRUE | O88: FALSE | P88: FALSE | Q88: FALSE | R88: FALSE | S88: FALSE | T88: FALSE | U88: TRUE | Y88: Y
A89: MM | B89: 44230 | D89: 16704 | E89: The military ordered telecos to block Facebook, Instagram, WhatsApp and Messenger amid military coup. | F89: FALSE | G89: FALSE | H89: TRUE | I89: FALSE | J89: Nationwide | K89: Asia | L89: 54409800 | M89: TRUE | N89: FALSE | O89: FALSE | P89: TRUE | Q89: FALSE | R89: TRUE | S89: FALSE | T89: FALSE | U89: TRUE | Y89: Y
A90: OM | B90: 44269 | D90: 15768 | E90: Clubhouse blocked on the grounds of not being licensed to operate. But some activists described the move as further erosion of freedom of expression. | F90: FALSE | G90: FALSE | H90: FALSE | I90: TRUE | J90: Nationwide | K90: Asia | L90: 5106626 | M90: FALSE | N90: FALSE | O90: FALSE | P90: FALSE | Q90: FALSE | R90: FALSE | S90: FALSE | T90: TRUE | U90: TRUE | Y90: Y
A91: OM | B91: 41500 | D91: 82224 | E91: VoIP as a service was banned in Oman on 09/12/2007. Telegram launched on 08/14/2013. Some VoIP services were unblocked in 2020 in light of the pandemic, but Telegram not listed as unblocked. | F91: FALSE | G91: FALSE | H91: FALSE | I91: TRUE | J91: Nationwide | K91: Asia | L91: 5106626 | M91: FALSE | N91: FALSE | O91: FALSE | P91: FALSE | Q91: TRUE | R91: FALSE | S91: FALSE | T91: FALSE | U91: TRUE | Y91: Y
A92: OM | B92: 39868 | D92: 121392 | E92: VoIP as a service was banned in Oman on 09/12/2007. WhatsApp launched on 02/24/2009. Some VoIP services were unblocked in 2020 in light of the pandemic, but WhatsApp listed as still blocked. | F92: FALSE | G92: FALSE | H92: FALSE | I92: TRUE | J92: Nationwide | K92: Asia | L92: 5106626 | M92: FALSE | N92: FALSE | O92: FALSE | P92: FALSE | Q92: FALSE | R92: TRUE | S92: FALSE | T92: FALSE | U92: TRUE | Y92: Y
A93: PK | B93: 44810 | C93: 44810 | D93: 1 | E93: Access to YouTube has again been disrupted on as Khan appears on screen to give a live speech at the Peshawar Jalsa. | F93: FALSE | G93: FALSE | H93: TRUE | I93: FALSE | J93: Nationwide | K93: Asia | L93: 220892340 | M93: FALSE | N93: FALSE | O93: TRUE | P93: FALSE | Q93: FALSE | R93: FALSE | S93: FALSE | T93: FALSE | U93: TRUE | V93: Y | Z93: Y
A94: PK | B94: 44794 | C94: 44794 | D94: 1 | E94: A YouTube disruption was recorded on multiple mobile and fixed-line internet providers in Pakistan on Sunday, August 21, 2022. The disruption happened during a live broadcast of the former Prime Minister Imran Khan’s speech. Access was restored after the speech concluded. | F94: FALSE | G94: FALSE | H94: TRUE | I94: FALSE | J94: Nationwide | K94: Asia | L94: 220892340 | M94: FALSE | N94: FALSE | O94: TRUE | P94: FALSE | Q94: FALSE | R94: FALSE | S94: FALSE | T94: FALSE | U94: TRUE | V94: Y | Z94: Y
A95: PK | B95: 44706 | C95: 44706 | D95: 2 | E95: Internet was disrupted for a couple of hours on multiple providers across Pakistan on May 25, 2022. The incident came as the government moved to ban rallies and a march to the capital organized by ousted Prime Minister Imran Khan. | F95: TRUE | G95: FALSE | H95: FALSE | I95: FALSE | J95: Karachi, Lahore and Islamabad | K95: Asia | L95: 18536707 | M95: FALSE | N95: FALSE | O95: FALSE | P95: FALSE | Q95: FALSE | R95: FALSE | S95: FALSE | T95: FALSE | U95: FALSE | V95: Y | Z95: Y
A96: QA | B96: 43018 | D96: 45792 | E96: Popular Voice over IP (VoIP) apps such as Skype, Facetime, Duo, Viber, and WhatsApp were blocked in 2017, October. At the time of conducting the study, Voice Over IP (VoIP) platforms remain blocked. | F96: FALSE | G96: FALSE | H96: FALSE | I96: TRUE | J96: Nationwide | K96: Asia | L96: 2881053 | M96: FALSE | N96: FALSE | O96: FALSE | P96: FALSE | Q96: FALSE | R96: TRUE | S96: FALSE | T96: TRUE | U96: TRUE | Y96: Y
A97: LK | B97: 44654 | C97: 44654 | D97: 16 | E97: Multiple social media platforms, including Facebook, Twitter, WhatsApp, Viber, and YouTube, were restricted in Sri Lanka. The government declares a state of emergency, imposing curfews to counter widespread protests over the economic crisis. | F97: TRUE | G97: FALSE | H97: FALSE | I97: FALSE | J97: Nationwide | K97: Asia | L97: 21413249 | M97: TRUE | N97: TRUE | O97: TRUE | P97: TRUE | Q97: FALSE | R97: TRUE | S97: TRUE | T97: FALSE | U97: TRUE | V97: Y | Z97: Y
A98: LK | B98: 44649 | C98: 44653 | D98: 96 | E98: Significant decline in connectivity levels on internet provider Dialog from 29 March coinciding with the onset of protests. | F98: TRUE | G98: FALSE | H98: FALSE | I98: FALSE | J98: Nationwide | K98: Asia | L98: 21413249 | M98: FALSE | N98: FALSE | O98: FALSE | P98: FALSE | Q98: FALSE | R98: FALSE | S98: FALSE | T98: FALSE | U98: FALSE | V98: Y | Z98: Y
A99: TH | B99: 44123 | D99: 19272 | E99: Thai authorities are reported to have ordered internet providers to block the Telegram messaging app, which has been used by anti-government protesters. | F99: TRUE | G99: FALSE | H99: FALSE | I99: FALSE | J99: Nationwide | K99: Asia | L99: 69799978 | M99: FALSE | N99: FALSE | O99: FALSE | P99: FALSE | Q99: TRUE | R99: FALSE | S99: FALSE | T99: FALSE | U99: TRUE | Y99: Y
A100: TM | B100: 43101 | D100: 43800 | E100: As of 2018, foreign news, opposition websites and international social networks such as Twitter are "often inaccessible". | F100: FALSE | G100: FALSE | H100: TRUE | I100: FALSE | J100: Nationwide | K100: Asia | L100: 6031200 | M100: FALSE | N100: TRUE | O100: FALSE | P100: FALSE | Q100: FALSE | R100: FALSE | S100: FALSE | T100: FALSE | U100: TRUE | Y100: Y
A101: TM | B101: 40422 | D101: 108096 | E101: In September 2010, Facebook was already banned in Turkmenistan. | F101: FALSE | G101: FALSE | H101: TRUE | I101: FALSE | J101: Nationwide | K101: Asia | L101: 6031200 | M101: TRUE | N101: FALSE | O101: FALSE | P101: TRUE | Q101: FALSE | R101: FALSE | S101: FALSE | T101: FALSE | U101: TRUE | Y101: Y
A102: TM | B102: 40148 | D102: 114672 | E102: YouTube was blocked by its only ISP in December 2009, and the ban has been in place in Turkmenistan ever since. | F102: FALSE | G102: FALSE | H102: TRUE | I102: FALSE | J102: Nationwide | K102: Asia | L102: 6031200 | M102: FALSE | N102: FALSE | O102: TRUE | P102: FALSE | Q102: FALSE | R102: FALSE | S102: FALSE | T102: FALSE | U102: TRUE | Y102: Y
A103: TM | B103: 42005 | D103: 70104 | E103: Most social networks are blocked, including WhatsApp and Telegram (Turkmens use Imo). It is not clear when they were blocked. WhatsApp might have been blocked as early as 2012. | F103: FALSE | G103: FALSE | H103: TRUE | I103: FALSE | J103: Nationwide | K103: Asia | L103: 6031200 | M103: FALSE | N103: FALSE | O103: FALSE | P103: FALSE | Q103: TRUE | R103: TRUE | S103: FALSE | T103: FALSE | U103: TRUE | Y103: Y
A104: AE | B104: 42096 | D104: 67920 | E104: Most Voice over Internet Protocol (VoIP) services – including Skype, FaceTime and WhatsApp – which enable free voice and video calls via the internet, are illegal in the UAE. | F104: FALSE | G104: FALSE | H104: FALSE | I104: TRUE | J104: Nationwide | K104: Asia | L104: 9890402 | M104: FALSE | N104: FALSE | O104: FALSE | P104: FALSE | Q104: FALSE | R104: TRUE | S104: FALSE | T104: TRUE | U104: TRUE | Y104: Y
A105: AE | B105: 43221 | D105: 40920 | E105: While progress is apparently being made by big-name app brands in the UAE on service expansion, rival Telegram’s regulatory issues appeared to worsen. | F105: FALSE | G105: FALSE | H105: FALSE | I105: TRUE | J105: Nationwide | K105: Asia | L105: 9890402 | M105: FALSE | N105: FALSE | O105: FALSE | P105: FALSE | Q105: TRUE | R105: FALSE | S105: FALSE | T105: FALSE | U105: TRUE | Y105: Y
...

Sheet 2021
A1: Summary of 2021. Below the summary, there is a list of all the 2021 cases
B2: Countries restricting the internet in 2021 | C2: Newly imposed restrictions in 2021 Internet disruptions | D2: Affected people (if there were fer restrictions imposed in a country, biggest population sample is used); Data from UN, World Population Prospects 2021 | E2: Related w/ protests | F2: Related w/ elections | G2: Related w/ political turmoil | H2: Related w/ country’s internet law | I2: Soc media | J2: Local internet | K2: Nationwide internet | L2: Registered cases since 2015 | M2: Currently blocking | N2: Region
A3: BF | B3: Burkina Faso | C3: 1 | D3: 20903273 | E3: 1 | F3: 0 | G3: 0 | H3: 0 | I3: 0 | J3: 0 | K3: 1 | L3: 4 | N3: Africa
A4: TD | B4: Chad | C4: 1 | D4: 16425864 | E4: 0 | F4: 0 | G4: 1 | H4: 0 | I4: 0 | J4: 0 | K4: 1 | L4: 5 | N4: Africa
A5: CG | B5: Congo | C5: 1 | D5: 5518087 | E5: 0 | F5: 1 | G5: 0 | H5: 0 | I5: 0 | J5: 0 | K5: 1 | L5: 3 | N5: Africa
A6: ER | B6: Eritrea | C6: 0 | D6: 3546421 | E6: 0 | F6: 0 | G6: 0 | H6: 0 | I6: 0 | J6: 0 | K6: 0 | L6: 2 | M6: Y | N6: Africa
A7: SZ | B7: Eswatini | C7: 2 | D7: 1160164 | E7: 2 | F7: 0 | G7: 0 | H7: 0 | I7: 1 | J7: 0 | K7: 1 | L7: 2 | N7: Africa
A8: ET | B8: Ethiopia | C8: 0 | D8: 5443000 | E8: 0 | F8: 0 | G8: 0 | H8: 0 | I8: 0 | J8: 0 | K8: 0 | L8: 10 | M8: Y | N8: Africa
A9: NE | B9: Niger | C9: 1 | D9: 24206644 | E9: 1 | F9: 0 | G9: 0 | H9: 0 | I9: 0 | J9: 0 | K9: 1 | L9: 2 | N9: Africa
A10: NG | B10: Nigeria | C10: 1 | D10: 206139589 | E10: 0 | F10: 0 | G10: 1 | H10: 0 | I10: 1 | J10: 0 | K10: 0 | L10: 1 | M10: Y | N10: Africa
A11: SS | B11: South Sudan | C11: 1 | D11: 11193725 | E11: 1 | F11: 0 | G11: 0 | H11: 0 | I11: 0 | J11: 0 | K11: 1 | L11: 1 | N11: Africa
A12: SN | B12: Senegal | C12: 1 | D12: 16743927 | E12: 1 | F12: 0 | G12: 0 | H12: 0 | I12: 1 | J12: 0 | K12: 0 | L12: 1 | N12: Africa
A13: SD | B13: Sudan | C13: 4 | D13: 43849260 | E13: 2 | F13: 0 | G13: 2 | H13: 0 | I13: 1 | J13: 0 | K13: 3 | L13: 11 | N13: Africa
A14: UG | B14: Uganda | C14: 3 | D14: 45741007 | E14: 0 | F14: 3 | G14: 0 | H14: 0 | I14: 2 | J14: 0 | K14: 1 | L14: 5 | N14: Africa
A15: ZM | B15: Zambia | C15: 1 | D15: 18383955 | E15: 0 | F15: 1 | G15: 0 | H15: 0 | I15: 1 | J15: 0 | K15: 0 | L15: 1 | N15: Africa
A16: AM | B16: Armenia | C16: 1 | D16: 2963243 | E16: 0 | F16: 0 | G16: 1 | H16: 0 | I16: 0 | J16: 0 | K16: 1 | L16: 3 | N16: Asia
A17: BH | B17: Bahrain | C17: 0 | D17: 1701575 | E17: 0 | F17: 0 | G17: 0 | H17: 0 | I17: 0 | J17: 0 | K17: 0 | L17: 1 | N17: Asia
A18: BD | B18: Bangladesh | C18: 1 | D18: 164689383 | E18: 1 | F18: 0 | G18: 0 | H18: 0 | I18: 1 | J18: 0 | K18: 0 | L18: 6 | N18: Asia
A19: CN | B19: China | C19: 0 | D19: 1439323776 | E19: 0 | F19: 0 | G19: 0 | H19: 0 | I19: 0 | J19: 0 | K19: 0 | L19: 4 | M19: Y | N19: Asia
A20: KP | B20: North Korea | C20: 0 | D20: 25778816 | E20: 0 | F20: 0 | G20: 0 | H20: 0 | I20: 0 | J20: 0 | K20: 0 | L20: 3 | M20: Y | N20: Asia
A21: IN | B21: India | C21: 7 | D21: 1380004385 | E21: 7 | F21: 0 | G21: 0 | H21: 0 | I21: 0 | J21: 7 | K21: 0 | L21: 102 | M21: Y | N21: Asia
A22: ID | B22: Indonesia | C22: 1 | D22: 327000 | E22: 0 | F22: 0 | G22: 1 | H22: 0 | I22: 0 | J22: 1 | K22: 0 | L22: 3 | N22: Asia
A23: IR | B23: Iran | C23: 5 | D23: 83992949 | E23: 4 | F23: 1 | G23: 0 | H23: 0 | I23: 0 | J23: 5 | K23: 0 | L23: 27 | M23: Y | N23: Asia
A24: JO | B24: Jordan | C24: 1 | D24: 1356046 | E24: 0 | F24: 0 | G24: 1 | H24: 0 | I24: 0 | J24: 1 | K24: 0 | L24: 5 | N24: Asia
A25: KZ | B25: Kazakhstan | C25: 1 | D25: 2346504 | E25: 1 | F25: 0 | G25: 0 | H25: 0 | I25: 0 | J25: 1 | K25: 0 | L25: 8 | N25: Asia
A26: MM | B26: Myanmar | C26: 5 | D26: 54409800 | E26: 1 | F26: 0 | G26: 4 | H26: 0 | I26: 2 | J26: 1 | K26: 2 | L26: 6 | M26: Y | N26: Asia
A27: OM | B27: Oman | C27: 1 | D27: 5106626 | E27: 0 | F27: 0 | G27: 0 | H27: 1 | I27: 1 | J27: 0 | K27: 0 | L27: 3 | M27: Y | N27: Asia
A28: PK | B28: Pakistan | C28: 1 | D28: 220892340 | E28: 1 | F28: 0 | G28: 0 | H28: 0 | I28: 1 | J28: 0 | K28: 0 | L28: 12 | N28: Asia
A29: QA | B29: Qatar | C29: 0 | D29: 2881053 | E29: 0 | F29: 0 | G29: 0 | H29: 0 | I29: 0 | J29: 0 | K29: 0 | L29: 1 | M29: Y | N29: Asia
A30: TJ | B30: Tajikistan | C30: 1 | D30: 9537645 | E30: 0 | F30: 0 | G30: 1 | H30: 0 | I30: 1 | J30: 0 | K30: 0 | L30: 4 | N30: Asia
A31: TH | B31: Thailand | C31: 0 | D31: 69799978 | E31: 0 | F31: 0 | G31: 0 | H31: 0 | I31: 0 | J31: 0 | K31: 0 | L31: 1 | M31: Y | N31: Asia
A32: TM | B32: Turkmenistan | C32: 0 | D32: 6031200 | E32: 0 | F32: 0 | G32: 0 | H32: 0 | I32: 0 | J32: 0 | K32: 0 | L32: 4 | M32: Y | N32: Asia
A33: AE | B33: U.A.E. | C33: 0 | D33: 9890402 | E33: 0 | F33: 0 | G33: 0 | H33: 0 | I33: 0 | J33: 0 | K33: 0 | L33: 2 | M33: Y | N33: Asia
A34: UZ | B34: Uzbekistan | C34: 4 | D34: 33469203 | E34: 0 | F34: 0 | G34: 0 | H34: 4 | I34: 4 | J34: 0 | K34: 0 | L34: 6 | M34: Y | N34: Asia
A35: YE | B35: Yemen | C35: 0 | D35: 29825964 | E35: 0 | F35: 0 | G35: 0 | H35: 0 | I35: 0 | J35: 0 | K35: 0 | L35: 3 | M35: Y | N35: Asia
A36: RU | B36: Russia | C36: 1 | D36: 145934462 | E36: 1 | F36: 0 | G36: 0 | H36: 0 | I36: 0 | J36: 1 | K36: 0 | L36: 9 | M36: Y | N36: Europe
A37: UA | B37: Ukraine | C37: 0 | D37: 43733762 | E37: 0 | F37: 0 | G37: 0 | H37: 0 | I37: 0 | J37: 0 | K37: 0 | L37: 1 | M37: Y | N37: Europe
A38: CU | B38: Cuba | C38: 3 | D38: 11326616 | E38: 3 | F38: 0 | G38: 0 | H38: 0 | I38: 1 | J38: 0 | K38: 2 | L38: 7 | N38: North America
A39: CO | B39: Colombia | C39: 1 | D39: 2392877 | E39: 1 | F39: 0 | G39: 0 | H39: 0 | I39: 0 | J39: 1 | K39: 0 | L39: 1 | N39: South America
A40: J&K | B40: Jammu and Kashmir | C40: 80 | D40: 13606320 | E40: 2 | F40: 0 | G40: 78 | H40: 0 | I40: 0 | J40: 80 | K40: 0 | L40: 306 | N40: Asia
A45: List of all restrictions in 2021
A46: Iso-2 array | B46: Start date | C46: End date | D46: Duration (until the end of 2021), h | E46: If yes, what was the context? | F46: Related w/ protests | G46: Related w/ elections | H46: Related w/ political turmoil | I46: Related w/ country’s internet law | J46: Scope/population? | L46: Population; Data from UN, World Population Prospects 2021 | M46: Facebook | N46: Twitter | O46: Youtube | P46: Instagram | Q46: Telegram | R46: Whatsapp | S46: Other soc. media | T46: Other VoIP apps | U46: Service based restriction | V46: Cases that started and ended in chosen period | W46: Cases that started in chosen period and are still ongoing | X46: Cases that started earlier but ended in chosen period | Y46: Cases that started earlier and are still ongoing | Z46: Cases that started in this period
A47: BF | B47: 44520 | C47: 44528 | D47: 193 | E47: Mobile internet disrupted in Burkina Faso after shooting of protesters | F47: TRUE | G47: FALSE | H47: FALSE | I47: FALSE | J47: Nationwide | K47: Africa | L47: 20903273 | M47: FALSE | N47: FALSE | O47: FALSE | P47: FALSE | Q47: FALSE | R47: FALSE | S47: FALSE | T47: FALSE | U47: FALSE | V47: Y | Z47: Y
A48: TD | B48: 44255 | C48: 44256 | D48: 32 | E48: Internet connectivity has been severely disrupted in Chad since the morning of Sunday 28 February 2021 amid reports of a deadly armed raid at the house of opposition candidate Yaya Dillo. | F48: FALSE | G48: FALSE | H48: TRUE | I48: FALSE | J48: Nationwide | K48: Africa | L48: 16425864 | M48: FALSE | N48: FALSE | O48: FALSE | P48: FALSE | Q48: FALSE | R48: FALSE | S48: FALSE | T48: FALSE | U48: FALSE | V48: Y | Z48: Y
A49: CG | B49: 44276 | C49: 44278 | D49: 72 | E49: Republic of the Congo shut down the internet amid the presidential election. | F49: FALSE | G49: TRUE | H49: FALSE | I49: FALSE | J49: Nationwide | K49: Africa | L49: 5518087 | M49: FALSE | N49: FALSE | O49: FALSE | P49: FALSE | Q49: FALSE | R49: FALSE | S49: FALSE | T49: FALSE | U49: FALSE | V49: Y | Z49: Y
A50: ER | B50: 40544 | D50: 96408 | E50: According to Freedom House, Eritrea has one of the worst infrastructures in Africa, it is possible that some ISPs deliberately block services, but the government’s poor human rights record indicates that the inaccessibility of YouTube could be related to censorship. | F50: FALSE | G50: FALSE | H50: TRUE | I50: FALSE | J50: Nationwide | K50: Africa | L50: 3546421 | M50: FALSE | N50: FALSE | O50: TRUE | P50: FALSE | Q50: FALSE | R50: FALSE | S50: FALSE | T50: FALSE | U50: TRUE | Y50: Y
A51: SZ | B51: 44484 | C51: 44484 | D51: 2 | E51: Authorities in Eswatini have again disrupted access to the internet and social media platforms in response to Ongoing pro-democracy protests. The government shut down social media platforms including Facebook, WhatsApp, and Twitter for approximately two hours. | F51: TRUE | G51: FALSE | H51: FALSE | I51: FALSE | J51: Nationwide | K51: Africa | L51: 1160164 | M51: TRUE | N51: TRUE | O51: FALSE | P51: FALSE | Q51: FALSE | R51: TRUE | S51: FALSE | T51: FALSE | U51: TRUE | V51: Y | Z51: Y
A52: SZ | B52: 44376 | C52: 44380 | D52: 89 | E52: Authorities shut internet down on June 29, in response to large-scale pro-democracy protests. | F52: TRUE | G52: FALSE | H52: FALSE | I52: FALSE | J52: Nationwide | K52: Africa | L52: 1160164 | M52: FALSE | N52: FALSE | O52: FALSE | P52: FALSE | Q52: FALSE | R52: FALSE | S52: FALSE | T52: FALSE | U52: FALSE | V52: Y | Z52: Y
A53: ET | B53: 44139 | D53: 10128 | E53: Tigray has been mostly without internet, telecommunications and banking since war broke out between federal government troops and forces led by the Tigray People’s Liberation Front (TPLF) in November 2020. A ceasefire deal between the warring sides was signed in South Africa in November of 2022. It commits Ethiopia’s government to restoring Tigray’s basic services, but the communications blackout has not yet been lifted. | F53: FALSE | G53: FALSE | H53: TRUE | I53: FALSE | J53: Tigray region | K53: Africa | L53: 5443000 | M53: FALSE | N53: FALSE | O53: FALSE | P53: FALSE | Q53: FALSE | R53: FALSE | S53: FALSE | T53: FALSE | U53: FALSE | Y53: Y
A54: NE | B54: 44251 | C54: 44260 | D54: 240 | E54: Three days later after presidential elections, as protesters gathered on the streets of Niamey and other regions following the official announcement of election results, major internet service providers (ISPs) in the country disrupted mobile internet. | F54: TRUE | G54: FALSE | H54: FALSE | I54: FALSE | J54: Nationwide | K54: Africa | L54: 24206644 | M54: FALSE | N54: FALSE | O54: FALSE | P54: FALSE | Q54: FALSE | R54: FALSE | S54: FALSE | T54: FALSE | U54: FALSE | V54: Y | Z54: Y
A55: NG | B55: 44352 | C55: 44574 | D55: 5016 | E55: Nigeria banned Twitter after the social media site removed a post by President Muhammadu Buhari threatening secessionists. | F55: FALSE | G55: FALSE | H55: TRUE | I55: FALSE | J55: Nationwide | K55: Africa | L55: 206139589 | M55: FALSE | N55: TRUE | O55: FALSE | P55: FALSE | Q55: FALSE | R55: FALSE | S55: FALSE | T55: FALSE | U55: TRUE | W55: Y | Z55: Y
A56: SS | B56: 44437 | C56: 44438 | D56: 12 | E56: Internet disrupted in South Sudan amid anti-government protests | F56: TRUE | G56: FALSE | H56: FALSE | I56: FALSE | J56: Nationwide | K56: Africa | L56: 11193725 | M56: FALSE | N56: FALSE | O56: FALSE | P56: FALSE | Q56: FALSE | R56: FALSE | S56: FALSE | T56: FALSE | U56: FALSE | V56: Y | Z56: Y
A57: SN | B57: 44260 | C57: 44260 | D57: 8 | E57: The online service restrictions come amid intensifying clashes between protesters and anti-riot police in Dakar after the second day of demonstrations following the arrest of opposition leader Ousmane Sonko. | F57: TRUE | G57: FALSE | H57: FALSE | I57: FALSE | J57: Nationwide | K57: Africa | L57: 16743927 | M57: TRUE | N57: FALSE | O57: TRUE | P57: FALSE | Q57: TRUE | R57: TRUE | S57: FALSE | T57: FALSE | U57: TRUE | V57: Y | Z57: Y
A58: SD | B58: 44560 | C58: 44560 | D58: 10 | E58: Internet service cut again for many users as protesters gathered for a new round of anti-coup protests. | F58: TRUE | G58: FALSE | H58: FALSE | I58: FALSE | J58: Nationwide | K58: Africa | L58: 43849260 | M58: FALSE | N58: FALSE | O58: FALSE | P58: FALSE | Q58: FALSE | R58: FALSE | S58: FALSE | T58: FALSE | U58: FALSE | V58: Y | Z58: Y
A59: SD | B59: 44555 | C59: 44555 | D59: 16 | E59: Mobile internet disrupted exactly two months after the coup, ahead of planned demonstrations. | F59: TRUE | G59: FALSE | H59: FALSE | I59: FALSE | J59: Nationwide | K59: Africa | L59: 43849260 | M59: FALSE | N59: FALSE | O59: FALSE | P59: FALSE | Q59: FALSE | R59: FALSE | S59: FALSE | T59: FALSE | U59: FALSE | V59: Y | Z59: Y
A60: SD | B60: 44494 | C60: 44524 | D60: 720 | E60: Social media and messaging platforms restricted amid an apparent military coup. | F60: FALSE | G60: FALSE | H60: TRUE | I60: FALSE | J60: Nationwide | K60: Africa | L60: 43849260 | M60: TRUE | N60: TRUE | O60: FALSE | P60: TRUE | Q60: TRUE | R60: TRUE | S60: FALSE | T60: FALSE | U60: TRUE | V60: Y | Z60: Y
A61: SD | B61: 44494 | C61: 44518 | D61: 576 | E61: Significant disruption to internet service, affecting cellular and some fixed-line connectivity on multiple providers, amid reports that senior government officials were detained in an apparent military coup. | F61: FALSE | G61: FALSE | H61: TRUE | I61: FALSE | J61: Nationwide | K61: Africa | L61: 43849260 | M61: FALSE | N61: FALSE | O61: FALSE | P61: FALSE | Q61: FALSE | R61: FALSE | S61: FALSE | T61: FALSE | U61: FALSE | V61: Y | Z61: Y
A62: UG | B62: 44209 | C62: 44214 | D62: 120 | E62: Internet blackout in the midst of presidential election. | F62: FALSE | G62: TRUE | H62: FALSE | I62: FALSE | J62: Nationwide | K62: Africa | L62: 45741007 | M62: FALSE | N62: FALSE | O62: FALSE | P62: FALSE | Q62: FALSE | R62: FALSE | S62: FALSE | T62: FALSE | U62: FALSE | V62: Y | Z62: Y
A63: UG | B63: 44208 | C63: 44369 | D63: 3864 | E63: Social media and messaging services restricted as authorities impose internet gag order before presidential election. | F63: FALSE | G63: TRUE | H63: FALSE | I63: FALSE | J63: Nationwide | K63: Africa | L63: 45741007 | M63: TRUE | N63: FALSE | O63: FALSE | P63: FALSE | Q63: FALSE | R63: FALSE | S63: FALSE | T63: FALSE | U63: TRUE | V63: Y | Z63: Y
A64: UG | B64: 44208 | C64: 44237 | D64: 696 | E64: Social media and messaging services restricted as authorities impose internet gag order before presidential election. | F64: FALSE | G64: TRUE | H64: FALSE | I64: FALSE | J64: Nationwide | K64: Africa | L64: 45741007 | M64: FALSE | N64: TRUE | O64: FALSE | P64: TRUE | Q64: TRUE | R64: TRUE | S64: TRUE | T64: TRUE | U64: TRUE | V64: Y | Z64: Y
A65: ZM | B65: 44420 | C65: 44421 | D65: 48 | E65: Social media and messaging apps restricted in Zambia on election day. | F65: FALSE | G65: TRUE | H65: FALSE | I65: FALSE | J65: Nationwide | K65: Africa | L65: 18383955 | M65: TRUE | N65: TRUE | O65: FALSE | P65: TRUE | Q65: FALSE | R65: TRUE | S65: FALSE | T65: FALSE | U65: TRUE | V65: Y | Z65: Y
A66: AM | B66: 44252 | C66: 44252 | D66: 7 | E66: Internet disrupted in Armenia amid political turmoil and alleged coup attempt. | F66: FALSE | G66: FALSE | H66: TRUE | I66: FALSE | J66: Nationwide | K66: Asia | L66: 2963243 | M66: FALSE | N66: FALSE | O66: FALSE | P66: FALSE | Q66: FALSE | R66: FALSE | S66: FALSE | T66: FALSE | U66: FALSE | V66: Y | Z66: Y
A67: BH | B67: 42522 | C67: 44348 | D67: 48936 | E67: Authorities blocked the communications app Telegram, which was popular among independent media, members of the political opposition, and protest groups in Bahrain. | F67: FALSE | G67: FALSE | H67: TRUE | I67: FALSE | J67: Nationwide | K67: Asia | L67: 1701575 | M67: FALSE | N67: FALSE | O67: FALSE | P67: FALSE | Q67: TRUE | R67: FALSE | S67: FALSE | T67: FALSE | U67: TRUE | X67: Y
A68: BD | B68: 44281 | C68: 44284 | D68: 72 | E68: Facebook and Messenger restricted in Bangladesh amid Indian Prime Minister Narendra Modi’s visit to the capital city of Bangladesh, Dhaka. | F68: TRUE | G68: FALSE | H68: FALSE | I68: FALSE | J68: Nationwide | K68: Asia | L68: 164689383 | M68: TRUE | N68: FALSE | O68: FALSE | P68: FALSE | Q68: FALSE | R68: FALSE | S68: FALSE | T68: FALSE | U68: TRUE | V68: Y | Z68: Y
A69: CN | B69: 39995 | D69: 109584 | E69: Foreign social media platforms such as Twitter, Facebook, and YouTube are currently banned in China. | F69: FALSE | G69: FALSE | H69: TRUE | I69: FALSE | J69: Nationwide | K69: Asia | L69: 1439323776 | M69: TRUE | N69: TRUE | O69: TRUE | P69: FALSE | Q69: FALSE | R69: FALSE | S69: FALSE | T69: FALSE | U69: TRUE | Y69: Y
A70: CN | B70: 42642 | D70: 46056 | E70: Instagram blocked in China as protests sweep Hong Kong. | F70: TRUE | G70: FALSE | H70: FALSE | I70: FALSE | J70: Nationwide | K70: Asia | L70: 1439323776 | M70: FALSE | N70: FALSE | O70: FALSE | P70: TRUE | Q70: FALSE | R70: FALSE | S70: FALSE | T70: FALSE | U70: TRUE | Y70: Y
A71: CN | B71: 42564 | D71: 47928 | E71: China blocks Telegram messenger, blamed for aiding human rights lawyers. | F71: FALSE | G71: FALSE | H71: TRUE | I71: FALSE | J71: Nationwide | K71: Asia | L71: 1439323776 | M71: FALSE | N71: FALSE | O71: FALSE | P71: FALSE | Q71: TRUE | R71: FALSE | S71: FALSE | T71: FALSE | U71: TRUE | Y71: Y
A72: CN | B72: 42979 | D72: 37968 | E72: China Blocks WhatsApp, broadening online censorship. | F72: FALSE | G72: FALSE | H72: TRUE | I72: FALSE | J72: Nationwide | K72: Asia | L72: 1439323776 | M72: FALSE | N72: FALSE | O72: FALSE | P72: FALSE | Q72: FALSE | R72: TRUE | S72: FALSE | T72: FALSE | U72: TRUE | Y72: Y
A73: KP | B73: 43084 | D73: 35448 | E73: WhatsApp messaging service blocked in North Korea | F73: FALSE | G73: FALSE | H73: TRUE | I73: FALSE | J73: Nationwide | K73: Asia | L73: 25778816 | M73: FALSE | N73: FALSE | O73: FALSE | P73: FALSE | Q73: FALSE | R73: TRUE | S73: FALSE | T73: FALSE | U73: TRUE | Y73: Y
A74: KP | B74: 42981 | D74: 37920 | E74: North Korea started blocking, Facebook, YouTube, Twitter and South Korean websites in April 2016. | F74: FALSE | G74: FALSE | H74: TRUE | I74: FALSE | J74: Nationwide | K74: Asia | L74: 25778816 | M74: TRUE | N74: TRUE | O74: TRUE | P74: FALSE | Q74: FALSE | R74: FALSE | S74: FALSE | T74: FALSE | U74: TRUE | Y74: Y
A75: KP | B75: 42177 | D75: 57216 | E75: North Korea blocks access to Instagram | F75: FALSE | G75: FALSE | H75: TRUE | I75: FALSE | J75: Nationwide | K75: Asia | L75: 25778816 | M75: FALSE | N75: FALSE | O75: FALSE | P75: TRUE | Q75: FALSE | R75: FALSE | S75: FALSE | T75: FALSE | U75: TRUE | Y75: Y
A76: IN | B76: 43984 | D76: 13848 | E76: TikTok + 59 Chinese apps' ban. | F76: FALSE | G76: FALSE | H76: FALSE | I76: TRUE | J76: Nationwide | K76: Asia | L76: 1380004385 | M76: FALSE | N76: FALSE | O76: FALSE | P76: FALSE | Q76: FALSE | R76: FALSE | S76: TRUE | T76: TRUE | U76: TRUE | Y76: Y
A77: ID | B77: 44433 | C77: 44433 | D77: 3 | E77: Internet blackout in Jayapura for around three hours. State-owned ISP said the disruption was caused by broken fiber optic cable. Rights watchdog says it should be seen within context of the August 26th trial of Victor Yeimo, spokesman for the pro-independence West Papua National Committee (KNPB), charged with treason and incitement. | F77: FALSE | G77: FALSE | H77: TRUE | I77: FALSE | J77: Jayapura | K77: Asia | L77: 327000 | M77: FALSE | N77: FALSE | O77: FALSE | P77: FALSE | Q77: FALSE | R77: FALSE | S77: FALSE | T77: FALSE | U77: FALSE | V77: Y | Z77: Y
A78: IR | B78: 44525 | C78: 44527 | D78: 48 | E78: Internet disruption registered in Iran amid protests against government water management policies. | F78: TRUE | G78: FALSE | H78: FALSE | I78: FALSE | J78: Ahvaz and Isfahan | K78: Asia | L78: 2388309 | M78: FALSE | N78: FALSE | O78: FALSE | P78: FALSE | Q78: FALSE | R78: FALSE | S78: FALSE | T78: FALSE | U78: FALSE | V78: Y | Z78: Y
A79: IR | B79: 44392 | C79: 44398 | D79: 144 | E79: Mobile internet disrupted in Iran amid Khuzestan water protests | F79: TRUE | G79: FALSE | H79: FALSE | I79: FALSE | J79: Khuzestan | K79: Asia | L79: 4710509 | M79: FALSE | N79: FALSE | O79: FALSE | P79: FALSE | Q79: FALSE | R79: FALSE | S79: FALSE | T79: FALSE | U79: FALSE | V79: Y | Z79: Y
A80: IR | B80: 44367 | C80: 44368 | D80: 24 | E80: Mobile internet cut off in response to protests against the result of city council elections. | F80: FALSE | G80: TRUE | H80: FALSE | I80: FALSE | J80: Yasuj | K80: Asia | L80: 134532 | M80: FALSE | N80: FALSE | O80: FALSE | P80: FALSE | Q80: FALSE | R80: FALSE | S80: FALSE | T80: FALSE | U80: FALSE | V80: Y | Z80: Y
A81: IR | B81: 44254 | C81: 44254 | D81: 2 | E81: Disruption to internet connectivity, following four days of localized regional network disruptions reported in the Sistan and Baluchestan region amid deadly protests. | F81: TRUE | G81: FALSE | H81: FALSE | I81: FALSE | J81: Sistan and Baluchestan | K81: Asia | L81: 2775014 | M81: FALSE | N81: FALSE | O81: FALSE | P81: FALSE | Q81: FALSE | R81: FALSE | S81: FALSE | T81: FALSE | U81: FALSE | V81: Y | Z81: Y
A82: IR | B82: 44251 | C82: 44255 | D82: 96 | E82: Disruptions of internet services in the southeast as unrest gripped the remote province after fatal border shootings. Rights groups called the disruptions a “tool to conceal” the government’s harsh crackdown on protests convulsing the area. | F82: TRUE | G82: FALSE | H82: FALSE | I82: FALSE | J82: Sistan and Baluchestan | K82: Asia | L82: 2775014 | M82: FALSE | N82: FALSE | O82: FALSE | P82: FALSE | Q82: FALSE | R82: FALSE | S82: FALSE | T82: FALSE | U82: FALSE | V82: Y | Z82: Y
A83: IR | B83: 39957 | D83: 110496 | E83: Iranian government blocks Facebook access. Opposition parties accuse President Mahmoud Ahmadinejad of trying to curb support for rivals before elections | F83: FALSE | G83: TRUE | H83: FALSE | I83: FALSE | J83: Nationwide | K83: Asia | L83: 83992949 | M83: TRUE | N83: TRUE | O83: FALSE | P83: FALSE | Q83: FALSE | R83: FALSE | S83: FALSE | T83: FALSE | U83: TRUE | Y83: Y
A84: IR | B84: 39977 | D84: 110016 | E84: The main mobile telephone network in Iran was cut in the capital Tehran evening while popular Internet websites Facebook and YouTube also appeared to be blocked | F84: FALSE | G84: TRUE | H84: FALSE | I84: FALSE | J84: Nationwide | K84: Asia | L84: 83992949 | M84: FALSE | N84: FALSE | O84: TRUE | P84: FALSE | Q84: FALSE | R84: FALSE | S84: FALSE | T84: FALSE | U84: TRUE | Y84: Y
A85: IR | B85: 43220 | D85: 32184 | E85: Iran blocks Telegram, claiming the app endangers national security. | F85: FALSE | G85: FALSE | H85: TRUE | I85: FALSE | J85: Nationwide | K85: Asia | L85: 83992949 | M85: FALSE | N85: FALSE | O85: FALSE | P85: FALSE | Q85: TRUE | R85: FALSE | S85: FALSE | T85: FALSE | U85: TRUE | Y85: Y
A86: JO | B86: 44289 | C86: 44291 | D86: 48 | E86: In the aftermath of the alleged coup attempt linked to Prince Hamzah, a two-day internet shutdown impacted parts of western Amman. | F86: FALSE | G86: FALSE | H86: TRUE | I86: FALSE | J86: Amman and Al-Salt | K86: Asia | L86: 1356046 | M86: FALSE | N86: FALSE | O86: FALSE | P86: FALSE | Q86: FALSE | R86: FALSE | S86: FALSE | T86: FALSE | U86: FALSE | V86: Y | Z86: Y
A87: KZ | B87: 44283 | C87: 44283 | D87: 3 | E87: Internet shutdown coinciding with anti-government protests in several Kazakh cities calling for the release of political prisoners, following a resolution passed by the European Parliament on human rights in the country. | F87: TRUE | G87: FALSE | H87: FALSE | I87: FALSE | J87: Almaty and Nur-Sultan | K87: Asia | L87: 2346504 | M87: FALSE | N87: FALSE | O87: FALSE | P87: FALSE | Q87: FALSE | R87: FALSE | S87: FALSE | T87: FALSE | U87: FALSE | V87: Y | Z87: Y
A88: MM | B88: 44453 | C88: 44467 | D88: 336 | E88: Mobile internet access cut off in townships that have seen widespread anti-junta protests since the military seized power. More townships affected later. | F88: TRUE | G88: FALSE | H88: FALSE | I88: FALSE | J88: Chin, Kachin, Magway, Mandalay, Sagaing | K88: Asia | L88: 3552034 | M88: FALSE | N88: FALSE | O88: FALSE | P88: FALSE | Q88: FALSE | R88: FALSE | S88: FALSE | T88: FALSE | U88: FALSE | V88: Y | Z88: Y
A89: MM | B89: 44351 | C89: 44351 | D89: 1 | E89: One hour-long internet shutdown coinciding with the NUG’s press conference. | F89: FALSE | G89: FALSE | H89: TRUE | I89: FALSE | J89: Nationwide | K89: Asia | L89: 54409800 | M89: FALSE | N89: FALSE | O89: FALSE | P89: FALSE | Q89: FALSE | R89: FALSE | S89: FALSE | T89: FALSE | U89: FALSE | V89: Y | Z89: Y
A90: MM | B90: 44232 | D90: 7896 | E90: Network data confirm the restriction of Twitter on Myanmar’s leading network operators, following the blocking of other social media platforms. | F90: FALSE | G90: FALSE | H90: TRUE | I90: FALSE | J90: Nationwide | K90: Asia | L90: 54409800 | M90: FALSE | N90: TRUE | O90: FALSE | P90: FALSE | Q90: FALSE | R90: FALSE | S90: FALSE | T90: FALSE | U90: TRUE | W90: Y | Z90: Y
A91: MM | B91: 44230 | D91: 7944 | E91: The military ordered telecos to block Facebook, Instagram, WhatsApp and Messenger amid military coup. | F91: FALSE | G91: FALSE | H91: TRUE | I91: FALSE | J91: Nationwide | K91: Asia | L91: 54409800 | M91: TRUE | N91: FALSE | O91: FALSE | P91: TRUE | Q91: FALSE | R91: TRUE | S91: FALSE | T91: FALSE | U91: TRUE | W91: Y | Z91: Y
A92: MM | B92: 44228 | C92: 44313 | D92: 767 | E92: Internet disrupted in Myanmar amid military uprising. Two major disruptions on Februarry 1st and 6th followed by periodical shutdown starting on February 15th (approximately 10 hours each day) until April 27th. | F92: FALSE | G92: FALSE | H92: TRUE | I92: FALSE | J92: Nationwide | K92: Asia | L92: 54409800 | M92: FALSE | N92: FALSE | O92: FALSE | P92: FALSE | Q92: FALSE | R92: FALSE | S92: FALSE | T92: FALSE | U92: FALSE | V92: Y | Z92: Y
A93: MM | B93: 44003 | C93: 44228 | D93: 13392 | E93: Myanmar authorities ordered the shutdown in the armed-conflict areas of Rakhine and Chin states. More than a million people living in these war-torn zones lost their right to access information they need to stay safe, such as news about the COVID-19 pandemic. | F93: FALSE | G93: FALSE | H93: TRUE | I93: FALSE | J93: Rakhine, Chin | K93: Asia | L93: 3667608 | M93: FALSE | N93: FALSE | O93: FALSE | P93: FALSE | Q93: FALSE | R93: FALSE | S93: FALSE | T93: FALSE | U93: FALSE | X93: Y
A94: OM | B94: 44269 | D94: 7008 | E94: Clubhouse blocked on the grounds of not being licensed to operate. But some activists described the move as further erosion of freedom of expression. | F94: FALSE | G94: FALSE | H94: FALSE | I94: TRUE | J94: Nationwide | K94: Asia | L94: 5106626 | M94: FALSE | N94: FALSE | O94: FALSE | P94: FALSE | Q94: FALSE | R94: FALSE | S94: FALSE | T94: TRUE | U94: TRUE | W94: Y | Z94: Y
A95: OM | B95: 41500 | D95: 73464 | E95: VoIP as a service was banned in Oman on 09/12/2007. Telegram launched on 08/14/2013. Some VoIP services were unblocked in 2020 in light of the pandemic, but Telegram not listed as unblocked. | F95: FALSE | G95: FALSE | H95: FALSE | I95: TRUE | J95: Nationwide | K95: Asia | L95: 5106626 | M95: FALSE | N95: FALSE | O95: FALSE | P95: FALSE | Q95: TRUE | R95: FALSE | S95: FALSE | T95: FALSE | U95: TRUE | Y95: Y
A96: OM | B96: 39868 | D96: 112632 | E96: VoIP as a service was banned in Oman on 09/12/2007. WhatsApp launched on 02/24/2009. Some VoIP services were unblocked in 2020 in light of the pandemic, but WhatsApp listed as still blocked. | F96: FALSE | G96: FALSE | H96: FALSE | I96: TRUE | J96: Nationwide | K96: Asia | L96: 5106626 | M96: FALSE | N96: FALSE | O96: FALSE | P96: FALSE | Q96: FALSE | R96: TRUE | S96: FALSE | T96: FALSE | U96: TRUE | Y96: Y
A97: PK | B97: 44302 | C97: 44302 | D97: 4 | E97: Access to popular social media sites blocked ahead of an expected crackdown on Islamists who have protested this week against France over caricatures of the prophet Muhammad in the French satirical magazine Charlie Hebdo. | F97: TRUE | G97: FALSE | H97: FALSE | I97: FALSE | J97: Nationwide | K97: Asia | L97: 220892340 | M97: TRUE | N97: TRUE | O97: TRUE | P97: FALSE | Q97: TRUE | R97: TRUE | S97: TRUE | T97: FALSE | U97: TRUE | V97: Y | Z97: Y
A98: PK | B98: 42533 | C98: 44558 | D98: 48672 | E98: Internet services suspended in the Federally Administered Tribal Areas (FATA) of Pakistan following a dispute at the Torkham border between Afghan and Pakistani forces. Mobile internet service restored 5 and a half years later. | F98: FALSE | G98: FALSE | H98: TRUE | I98: FALSE | J98: Federally Administered Tribal Areas | K98: Asia | M98: FALSE | N98: FALSE | O98: FALSE | P98: FALSE | Q98: FALSE | R98: FALSE | S98: FALSE | T98: FALSE | U98: FALSE | X98: Y
A99: QA | B99: 43018 | D99: 37032 | E99: Popular Voice over IP (VoIP) apps such as Skype, Facetime, Duo, Viber, and WhatsApp were blocked in 2017, October. At the time of conducting the study, Voice Over IP (VoIP) platforms remain blocked. | F99: FALSE | G99: FALSE | H99: FALSE | I99: TRUE | J99: Nationwide | K99: Asia | L99: 2881053 | M99: FALSE | N99: FALSE | O99: FALSE | P99: FALSE | Q99: FALSE | R99: TRUE | S99: FALSE | T99: TRUE | U99: TRUE | Y99: Y
A100: TJ | B100: 44207 | C100: 44208 | D100: 48 | E100: Tajikistan: Authorities somehow find more room for internet censorship. | F100: FALSE | G100: FALSE | H100: TRUE | I100: FALSE | J100: Nationwide | K100: Asia | L100: 9537645 | M100: TRUE | N100: FALSE | O100: FALSE | P100: TRUE | Q100: FALSE | R100: FALSE | S100: FALSE | T100: FALSE | U100: TRUE | V100: Y | Z100: Y
A101: TH | B101: 44123 | D101: 10512 | E101: Thai authorities are reported to have ordered internet providers to block the Telegram messaging app, which has been used by anti-government protesters. | F101: TRUE | G101: FALSE | H101: FALSE | I101: FALSE | J101: Nationwide | K101: Asia | L101: 69799978 | M101: FALSE | N101: FALSE | O101: FALSE | P101: FALSE | Q101: TRUE | R101: FALSE | S101: FALSE | T101: FALSE | U101: TRUE | Y101: Y
A102: TM | B102: 43101 | D102: 35040 | E102: As of 2018, foreign news, opposition websites and international social networks such as Twitter are "often inaccessible". | F102: FALSE | G102: FALSE | H102: TRUE | I102: FALSE | J102: Nationwide | K102: Asia | L102: 6031200 | M102: FALSE | N102: TRUE | O102: FALSE | P102: FALSE | Q102: FALSE | R102: FALSE | S102: FALSE | T102: FALSE | U102: TRUE | Y102: Y
A103: TM | B103: 40422 | D103: 99336 | E103: In September 2010, Facebook was already banned in Turkmenistan. | F103: FALSE | G103: FALSE | H103: TRUE | I103: FALSE | J103: Nationwide | K103: Asia | L103: 6031200 | M103: TRUE | N103: FALSE | O103: FALSE | P103: TRUE | Q103: FALSE | R103: FALSE | S103: FALSE | T103: FALSE | U103: TRUE | Y103: Y
A104: TM | B104: 40148 | D104: 105912 | E104: YouTube was blocked by its only ISP in December 2009, and the ban has been in place in Turkmenistan ever since. | F104: FALSE | G104: FALSE | H104: TRUE | I104: FALSE | J104: Nationwide | K104: Asia | L104: 6031200 | M104: FALSE | N104: FALSE | O104: TRUE | P104: FALSE | Q104: FALSE | R104: FALSE | S104: FALSE | T104: FALSE | U104: TRUE | Y104: Y
...

Sheet updateDate
A1: =IFERROR(__xludf.DUMMYFUNCTION("IMPORTRANGE(""https://docs.google.com/spreadsheets/d/15PEd5n9dX2RsuN-qncR2k1Cl7OyMNdFOFjQgqebZao0/edit#gid=502798689"",""insightsNewsData!G7:H7"")"),"update date") -> update date | B1: =IFERROR(__xludf.DUMMYFUNCTION("""COMPUTED_VALUE"""),45657.0) -> 45657
